Workbook
Name DiscountRate: Einstellungen!$B$3
Name HorizonYears: Einstellungen!$B$4
Name TaxRate: Einstellungen!$B$5
Name VariableNames: Variablen!$A$4:INDEX(Variablen!$A:$A,COUNTA(Variablen!$A:$A))
Name ActionIDs: Actions!$A$2:INDEX(Actions!$A:$A,COUNTA(Actions!$A:$A))
Name KPIList: Helper!$A$2#

Sheet Glossar
A1: Glossar: Begriffe und Abkürzungen
A3: Ziel: Kurze Erklärungen, damit auch Nicht-Finanzleute die Logik nachvollziehen können.
A5: Begriffe
A6: Begriff | B6: Erklärung
A7: CAPEX | B7: Einmalige Investitionsausgaben (z.B. Hardware, Installation). In dieser Datei wird CAPEX in Jahr 0 als Auszahlung angesetzt.
A8: OPEX | B8: Laufende Kosten pro Jahr (z.B. Wartung, Lizenzen). In dieser Datei starten OPEX ab Go-Live und werden im Go-Live-Jahr anteilig gerechnet.
A9: ROI | B9: Return on Investment. Hier vereinfacht: Verhältnis von Netto-Nutzen zu (CAPEX + OPEX) über den Betrachtungszeitraum. Gut für einen schnellen Vergleich, aber weniger sauber als NPV.
A10: NPV / Kapitalwert | B10: Summe aller zukünftigen Cashflows, abgezinst auf heute. Positiv bedeutet: wirtschaftlich attraktiv bei gegebenem Diskontsatz.
A11: Diskontsatz | B11: Zinssatz, mit dem zukünftige Cashflows auf heute abgezinst werden (z.B. WACC). Höherer Diskontsatz macht zukünftige Nutzen weniger wert.
A12: IRR | B12: Interner Zinsfuß. Der Diskontsatz, bei dem der Kapitalwert genau 0 ist. Hilft beim Vergleich von Projekten, kann aber bei untypischen Cashflows irreführend sein.
A13: Payback / Amortisation | B13: Zeitpunkt, an dem die kumulierten Cashflows erstmals wieder positiv sind (Investition hat sich zurückgezahlt). Ignoriert Cashflows nach dem Payback und Diskontierung.
A14: Go-Live | B14: Zeitpunkt, ab dem die Maßnahme wirkt und Nutzen sowie OPEX starten. In dieser Datei: Zieldatum.
A15: Monetarisierung | B15: Übersetzung eines KPI-Impacts in Euro pro Einheit (z.B. EUR/kWh). Kann fix sein oder über eine Variable (z.B. Strompreis je Jahr).
A16: Variable | B16: Zeitreihe mit Kalenderjahren (z.B. Strompreis 2020 bis 2055). Jede Variable hat ein eigenes Startjahr und einen eigenen Horizont.
A17: MACC (pro KPI) | B17: Marginal Abatement Cost Curve. Hier: Kosten pro Einheit KPI-Reduktion (€/Einheit). Berechnet als -NPV / diskontierte KPI-Reduktion. MACC ist nur sinnvoll innerhalb eines KPI, weil Einheiten unterschiedlich sind.

Sheet README
A1: ROI & Investitionsplanung für Nachhaltigkeits-Actions (Vorlage v5)
A3: Zweck: Pro Action und als Portfolio eine transparente Investitionsrechnung (NPV, IRR, ROI, Payback).
A4: Neu: MACC wird pro Nachhaltigkeits-KPI dargestellt (nicht nur CO2).
A6: Schritt-für-Schritt:
A7: 1) Trage Actions im Blatt „Actions“ ein. Blau sind Eingaben. Schwarzer Text sind Formeln oder automatisch gezogene Werte.
A8: 2) Trage bei Bedarf Variablen im Blatt „Variablen“ ein (z.B. Strompreis). Jede Variable hat eigenes Startjahr und eigenen Horizont.
A9: 3) Setze globale Annahmen in „Einstellungen“ (Diskontsatz, TaxRate, Horizont).
A10: 4) Nutze „Action_Rechner“ als Detailansicht je Action.
A11: 5) Nutze „Dashboard“ für die Portfolio-Übersicht und „MACC_KPI“ für MACC pro KPI.
A13: Wichtige Modellannahmen:
A14: • Nutzen und OPEX starten ab Go-Live (Zieldatum). Im Go-Live-Jahr anteilig nach Monaten: (12 - Monat(Go-Live) + 1) / 12.
A15: • CAPEX wird als Auszahlung in Jahr 0 (relativ zum Startjahr) angesetzt.
... A19: Komplexität bewusst niedrig: Das Modell priorisiert Actions. Für Investitionsfreigaben brauchst du in der Praxis oft mehr Details (Timing von CAPEX, Ramp-up, Risiken, Sensitivitäten).

Sheet Einstellungen
A1: Globale Annahmen
A3: Diskontsatz (WACC/Discount Rate) | B3: 0.08 | C3: Dezimal, z.B. 0,08 für 8%
A4: Cashflow-Horizont (Jahre) | B4: 10 | C4: max 20 (in Cashflow-Tabellen)
A5: TaxRate (Steuersatz) | B5: 0.3 | C5: 0 setzen, wenn du Steuern/Abschreibung ignorieren willst
A6: Währung | B6: EUR

Sheet CAPEX_OPEX_Glossar
A1: CAPEX und OPEX (Orientierung)
A3: Kategorie | B3: Typische Inhalte
A4: CAPEX Equipment | B4: Maschinen, Hardware, Anlagen, Sensorik, Ersatzinvestitionen, Gebäudeanpassungen
A5: CAPEX Installation | B5: Montage, Inbetriebnahme, Umbauten, Projektmanagement (einmalig)
A6: CAPEX Software | B6: Einmalige Software-Käufe, Implementierung, Setup, Integrationsaufwand
A7: CAPEX Beratung | B7: Externe Beratung, Engineering, Audits (einmalig)
A8: CAPEX Sonstiges | B8: Schulung (einmalig), Genehmigungen, Messkonzept-Aufbau, sonstige Einmalaufwände
A9: OPEX Wartung | B9: Wartung, Ersatzteile, Service, Kalibrierung
A10: OPEX Lizenzen | B10: SaaS-Abos, laufende Software-Lizenzen
A11: OPEX Personal | B11: Betrieb, Monitoring, Reporting, zusätzliche interne Kapazität
A12: OPEX Sonstiges | B12: Versicherung, Miete, Gebühren, sonstige Betriebskosten

Sheet Variablen
A1: Variablen (kalenderjahresbasiert, pro Variable eigenes Startjahr & Horizont)
A2: Vor Startjahr: leer. Nach Ende (Startjahr + Horizont): konstant. Methode Manuell: Werte direkt in Jahres-Spalten überschreiben.
A3: Variable Name | B3: Beschreibung | C3: Einheit | D3: Methode (Fix/CAGR/Manuell) | E3: Startjahr | F3: Horizont (Jahre) | G3: Wert im Startjahr | H3: Wachstum p.a. (CAGR) | I3: 2018 | J3: 2019 | K3: 2020 | L3: 2021 | M3: 2022 | N3: 2023 | O3: 2024 | P3: 2025 | Q3: 2026 | R3: 2027 | S3: 2028 | T3: 2029 | U3: 2030 | V3: 2031 | W3: 2032 | X3: 2033 | Y3: 2034 | Z3: 2035 | AA3: 2036 | AB3: 2037 | AC3: 2038 | AD3: 2039 | AE3: 2040 | AF3: 2041 | AG3: 2042 | AH3: 2043 | AI3: 2044 | AJ3: 2045 | AK3: 2046 | AL3: 2047 | AM3: 2048 | AN3: 2049 | AO3: 2050 | AP3: 2051 | AQ3: 2052 | AR3: 2053 | AS3: 2054 | AT3: 2055
A4: Strompreis | B4: Strompreis | C4: EUR/kWh | D4: CAGR | E4: 2020 | F4: 25 | G4: 0.22 | H4: 0.03 | I4: =IF($A4="","",IF(2018<$E4,"",IF($D4="Manuell","",IF(2018>$E4+$F4,IF($D4="Fix",$G4,$G4*(1+$H4)^($F4)),IF($D4="Fix",$G4,$G4*(1+$H4)^(2018-$E4)))))) | J4: =IF($A4="","",IF(2019<$E4,"",IF($D4="Manuell","",IF(2019>$E4+$F4,IF($D4="Fix",$G4,$G4*(1+$H4)^($F4)),IF($D4="Fix",$G4,$G4*(1+$H4)^(2019-$E4)))))) | K4: =IF($A4="","",IF(2020<$E4,"",IF($D4="Manuell","",IF(2020>$E4+$F4,IF($D4="Fix",$G4,$G4*(1+$H4)^($F4)),IF($D4="Fix",$G4,$G4*(1+$H4)^(2020-$E4)))))) | L4: =IF($A4="","",IF(2021<$E4,"",IF($D4="Manuell","",IF(2021>$E4+$F4,IF($D4="Fix",$G4,$G4*(1+$H4)^($F4)),IF($D4="Fix",$G4,$G4*(1+$H4)^(2021-$E4)))))) | M4: =IF($A4="","",IF(2022<$E4,"",IF($D4="Manuell","",IF(2022>$E4+$F4,IF($D4="Fix",$G4,$G4*(1+$H4)^($F4)),IF($D4="Fix",$G4,$G4*(1+$H4)^(2022-$E4)))))) | N4: =IF($A4="","",IF(2023<$E4,"",IF($D4="Manuell","",IF(2023>$E4+$F4,IF($D4="Fix",$G4,$G4*(1+$H4)^($F4)),IF($D4="Fix",$G4,$G4*(1+$H4)^(2023-$E4)))))) | O4: =IF($A4="","",IF(2024<$E4,"",IF($D4="Manuell","",IF(2024>$E4+$F4,IF($D4="Fix",$G4,$G4*(1+$H4)^($F4)),IF($D4="Fix",$G4,$G4*(1+$H4)^(2024-$E4)))))) | P4: =IF($A4="","",IF(2025<$E4,"",IF($D4="Manuell","",IF(2025>$E4+$F4,IF($D4="Fix",$G4,$G4*(1+$H4)^($F4)),IF($D4="Fix",$G4,$G4*(1+$H4)^(2025-$E4)))))) | Q4: =IF($A4="","",IF(2026<$E4,"",IF($D4="Manuell","",IF(2026>$E4+$F4,IF($D4="Fix",$G4,$G4*(1+$H4)^($F4)),IF($D4="Fix",$G4,$G4*(1+$H4)^(2026-$E4)))))) | R4: =IF($A4="","",IF(2027<$E4,"",IF($D4="Manuell","",IF(2027>$E4+$F4,IF($D4="Fix",$G4,$G4*(1+$H4)^($F4)),IF($D4="Fix",$G4,$G4*(1+$H4)^(2027-$E4)))))) | S4: =IF($A4="","",IF(2028<$E4,"",IF($D4="Manuell","",IF(2028>$E4+$F4,IF($D4="Fix",$G4,$G4*(1+$H4)^($F4)),IF($D4="Fix",$G4,$G4*(1+$H4)^(2028-$E4)))))) | T4: =IF($A4="","",IF(2029<$E4,"",IF($D4="Manuell","",IF(2029>$E4+$F4,IF($D4="Fix",$G4,$G4*(1+$H4)^($F4)),IF($D4="Fix",$G4,$G4*(1+$H4)^(2029-$E4)))))) | U4: =IF($A4="","",IF(2030<$E4,"",IF($D4="Manuell","",IF(2030>$E4+$F4,IF($D4="Fix",$G4,$G4*(1+$H4)^($F4)),IF($D4="Fix",$G4,$G4*(1+$H4)^(2030-$E4)))))) | V4: =IF($A4="","",IF(2031<$E4,"",IF($D4="Manuell","",IF(2031>$E4+$F4,IF($D4="Fix",$G4,$G4*(1+$H4)^($F4)),IF($D4="Fix",$G4,$G4*(1+$H4)^(2031-$E4)))))) | W4: =IF($A4="","",IF(2032<$E4,"",IF($D4="Manuell","",IF(2032>$E4+$F4,IF($D4="Fix",$G4,$G4*(1+$H4)^($F4)),IF($D4="Fix",$G4,$G4*(1+$H4)^(2032-$E4)))))) | X4: =IF($A4="","",IF(2033<$E4,"",IF($D4="Manuell","",IF(2033>$E4+$F4,IF($D4="Fix",$G4,$G4*(1+$H4)^($F4)),IF($D4="Fix",$G4,$G4*(1+$H4)^(2033-$E4)))))) | Y4: =IF($A4="","",IF(2034<$E4,"",IF($D4="Manuell","",IF(2034>$E4+$F4,IF($D4="Fix",$G4,$G4*(1+$H4)^($F4)),IF($D4="Fix",$G4,$G4*(1+$H4)^(2034-$E4)))))) | Z4: =IF($A4="","",IF(2035<$E4,"",IF($D4="Manuell","",IF(2035>$E4+$F4,IF($D4="Fix",$G4,$G4*(1+$H4)^($F4)),IF($D4="Fix",$G4,$G4*(1+$H4)^(2035-$E4)))))) | AA4: =IF($A4="","",IF(2036<$E4,"",IF($D4="Manuell","",IF(2036>$E4+$F4,IF($D4="Fix",$G4,$G4*(1+$H4)^($F4)),IF($D4="Fix",$G4,$G4*(1+$H4)^(2036-$E4)))))) | AB4: =IF($A4="","",IF(2037<$E4,"",IF($D4="Manuell","",IF(2037>$E4+$F4,IF($D4="Fix",$G4,$G4*(1+$H4)^($F4)),IF($D4="Fix",$G4,$G4*(1+$H4)^(2037-$E4)))))) | AC4: =IF($A4="","",IF(2038<$E4,"",IF($D4="Manuell","",IF(2038>$E4+$F4,IF($D4="Fix",$G4,$G4*(1+$H4)^($F4)),IF($D4="Fix",$G4,$G4*(1+$H4)^(2038-$E4)))))) | AD4: =IF($A4="","",IF(2039<$E4,"",IF($D4="Manuell","",IF(2039>$E4+$F4,IF($D4="Fix",$G4,$G4*(1+$H4)^($F4)),IF($D4="Fix",$G4,$G4*(1+$H4)^(2039-$E4)))))) | AE4: =IF($A4="","",IF(2040<$E4,"",IF($D4="Manuell","",IF(2040>$E4+$F4,IF($D4="Fix",$G4,$G4*(1+$H4)^($F4)),IF($D4="Fix",$G4,$G4*(1+$H4)^(2040-$E4)))))) | AF4: =IF($A4="","",IF(2041<$E4,"",IF($D4="Manuell","",IF(2041>$E4+$F4,IF($D4="Fix",$G4,$G4*(1+$H4)^($F4)),IF($D4="Fix",$G4,$G4*(1+$H4)^(2041-$E4)))))) | AG4: =IF($A4="","",IF(2042<$E4,"",IF($D4="Manuell","",IF(2042>$E4+$F4,IF($D4="Fix",$G4,$G4*(1+$H4)^($F4)),IF($D4="Fix",$G4,$G4*(1+$H4)^(2042-$E4)))))) | AH4: =IF($A4="","",IF(2043<$E4,"",IF($D4="Manuell","",IF(2043>$E4+$F4,IF($D4="Fix",$G4,$G4*(1+$H4)^($F4)),IF($D4="Fix",$G4,$G4*(1+$H4)^(2043-$E4)))))) | AI4: =IF($A4="","",IF(2044<$E4,"",IF($D4="Manuell","",IF(2044>$E4+$F4,IF($D4="Fix",$G4,$G4*(1+$H4)^($F4)),IF($D4="Fix",$G4,$G4*(1+$H4)^(2044-$E4)))))) | AJ4: =IF($A4="","",IF(2045<$E4,"",IF($D4="Manuell","",IF(2045>$E4+$F4,IF($D4="Fix",$G4,$G4*(1+$H4)^($F4)),IF($D4="Fix",$G4,$G4*(1+$H4)^(2045-$E4)))))) | AK4: =IF($A4="","",IF(2046<$E4,"",IF($D4="Manuell","",IF(2046>$E4+$F4,IF($D4="Fix",$G4,$G4*(1+$H4)^($F4)),IF($D4="Fix",$G4,$G4*(1+$H4)^(2046-$E4)))))) | AL4: =IF($A4="","",IF(2047<$E4,"",IF($D4="Manuell","",IF(2047>$E4+$F4,IF($D4="Fix",$G4,$G4*(1+$H4)^($F4)),IF($D4="Fix",$G4,$G4*(1+$H4)^(2047-$E4)))))) | AM4: =IF($A4="","",IF(2048<$E4,"",IF($D4="Manuell","",IF(2048>$E4+$F4,IF($D4="Fix",$G4,$G4*(1+$H4)^($F4)),IF($D4="Fix",$G4,$G4*(1+$H4)^(2048-$E4)))))) | AN4: =IF($A4="","",IF(2049<$E4,"",IF($D4="Manuell","",IF(2049>$E4+$F4,IF($D4="Fix",$G4,$G4*(1+$H4)^($F4)),IF($D4="Fix",$G4,$G4*(1+$H4)^(2049-$E4)))))) | AO4: =IF($A4="","",IF(2050<$E4,"",IF($D4="Manuell","",IF(2050>$E4+$F4,IF($D4="Fix",$G4,$G4*(1+$H4)^($F4)),IF($D4="Fix",$G4,$G4*(1+$H4)^(2050-$E4)))))) | AP4: =IF($A4="","",IF(2051<$E4,"",IF($D4="Manuell","",IF(2051>$E4+$F4,IF($D4="Fix",$G4,$G4*(1+$H4)^($F4)),IF($D4="Fix",$G4,$G4*(1+$H4)^(2051-$E4)))))) | AQ4: =IF($A4="","",IF(2052<$E4,"",IF($D4="Manuell","",IF(2052>$E4+$F4,IF($D4="Fix",$G4,$G4*(1+$H4)^($F4)),IF($D4="Fix",$G4,$G4*(1+$H4)^(2052-$E4)))))) | AR4: =IF($A4="","",IF(2053<$E4,"",IF($D4="Manuell","",IF(2053>$E4+$F4,IF($D4="Fix",$G4,$G4*(1+$H4)^($F4)),IF($D4="Fix",$G4,$G4*(1+$H4)^(2053-$E4)))))) | AS4: =IF($A4="","",IF(2054<$E4,"",IF($D4="Manuell","",IF(2054>$E4+$F4,IF($D4="Fix",$G4,$G4*(1+$H4)^($F4)),IF($D4="Fix",$G4,$G4*(1+$H4)^(2054-$E4)))))) | AT4: =IF($A4="","",IF(2055<$E4,"",IF($D4="Manuell","",IF(2055>$E4+$F4,IF($D4="Fix",$G4,$G4*(1+$H4)^($F4)),IF($D4="Fix",$G4,$G4*(1+$H4)^(2055-$E4))))))
A5: Gaspreis | B5: Gaspreis | C5: EUR/kWh | D5: CAGR | E5: 2020 | F5: 25 | G5: 0.07 | H5: 0.02 | I5: =IF($A5="","",IF(2018<$E5,"",IF($D5="Manuell","",IF(2018>$E5+$F5,IF($D5="Fix",$G5,$G5*(1+$H5)^($F5)),IF($D5="Fix",$G5,$G5*(1+$H5)^(2018-$E5)))))) | J5: =IF($A5="","",IF(2019<$E5,"",IF($D5="Manuell","",IF(2019>$E5+$F5,IF($D5="Fix",$G5,$G5*(1+$H5)^($F5)),IF($D5="Fix",$G5,$G5*(1+$H5)^(2019-$E5)))))) | K5: =IF($A5="","",IF(2020<$E5,"",IF($D5="Manuell","",IF(2020>$E5+$F5,IF($D5="Fix",$G5,$G5*(1+$H5)^($F5)),IF($D5="Fix",$G5,$G5*(1+$H5)^(2020-$E5)))))) | L5: =IF($A5="","",IF(2021<$E5,"",IF($D5="Manuell","",IF(2021>$E5+$F5,IF($D5="Fix",$G5,$G5*(1+$H5)^($F5)),IF($D5="Fix",$G5,$G5*(1+$H5)^(2021-$E5)))))) | M5: =IF($A5="","",IF(2022<$E5,"",IF($D5="Manuell","",IF(2022>$E5+$F5,IF($D5="Fix",$G5,$G5*(1+$H5)^($F5)),IF($D5="Fix",$G5,$G5*(1+$H5)^(2022-$E5)))))) | N5: =IF($A5="","",IF(2023<$E5,"",IF($D5="Manuell","",IF(2023>$E5+$F5,IF($D5="Fix",$G5,$G5*(1+$H5)^($F5)),IF($D5="Fix",$G5,$G5*(1+$H5)^(2023-$E5)))))) | O5: =IF($A5="","",IF(2024<$E5,"",IF($D5="Manuell","",IF(2024>$E5+$F5,IF($D5="Fix",$G5,$G5*(1+$H5)^($F5)),IF($D5="Fix",$G5,$G5*(1+$H5)^(2024-$E5)))))) | P5: =IF($A5="","",IF(2025<$E5,"",IF($D5="Manuell","",IF(2025>$E5+$F5,IF($D5="Fix",$G5,$G5*(1+$H5)^($F5)),IF($D5="Fix",$G5,$G5*(1+$H5)^(2025-$E5)))))) | Q5: =IF($A5="","",IF(2026<$E5,"",IF($D5="Manuell","",IF(2026>$E5+$F5,IF($D5="Fix",$G5,$G5*(1+$H5)^($F5)),IF($D5="Fix",$G5,$G5*(1+$H5)^(2026-$E5)))))) | R5: =IF($A5="","",IF(2027<$E5,"",IF($D5="Manuell","",IF(2027>$E5+$F5,IF($D5="Fix",$G5,$G5*(1+$H5)^($F5)),IF($D5="Fix",$G5,$G5*(1+$H5)^(2027-$E5)))))) | S5: =IF($A5="","",IF(2028<$E5,"",IF($D5="Manuell","",IF(2028>$E5+$F5,IF($D5="Fix",$G5,$G5*(1+$H5)^($F5)),IF($D5="Fix",$G5,$G5*(1+$H5)^(2028-$E5)))))) | T5: =IF($A5="","",IF(2029<$E5,"",IF($D5="Manuell","",IF(2029>$E5+$F5,IF($D5="Fix",$G5,$G5*(1+$H5)^($F5)),IF($D5="Fix",$G5,$G5*(1+$H5)^(2029-$E5)))))) | U5: =IF($A5="","",IF(2030<$E5,"",IF($D5="Manuell","",IF(2030>$E5+$F5,IF($D5="Fix",$G5,$G5*(1+$H5)^($F5)),IF($D5="Fix",$G5,$G5*(1+$H5)^(2030-$E5)))))) | V5: =IF($A5="","",IF(2031<$E5,"",IF($D5="Manuell","",IF(2031>$E5+$F5,IF($D5="Fix",$G5,$G5*(1+$H5)^($F5)),IF($D5="Fix",$G5,$G5*(1+$H5)^(2031-$E5)))))) | W5: =IF($A5="","",IF(2032<$E5,"",IF($D5="Manuell","",IF(2032>$E5+$F5,IF($D5="Fix",$G5,$G5*(1+$H5)^($F5)),IF($D5="Fix",$G5,$G5*(1+$H5)^(2032-$E5)))))) | X5: =IF($A5="","",IF(2033<$E5,"",IF($D5="Manuell","",IF(2033>$E5+$F5,IF($D5="Fix",$G5,$G5*(1+$H5)^($F5)),IF($D5="Fix",$G5,$G5*(1+$H5)^(2033-$E5)))))) | Y5: =IF($A5="","",IF(2034<$E5,"",IF($D5="Manuell","",IF(2034>$E5+$F5,IF($D5="Fix",$G5,$G5*(1+$H5)^($F5)),IF($D5="Fix",$G5,$G5*(1+$H5)^(2034-$E5)))))) | Z5: =IF($A5="","",IF(2035<$E5,"",IF($D5="Manuell","",IF(2035>$E5+$F5,IF($D5="Fix",$G5,$G5*(1+$H5)^($F5)),IF($D5="Fix",$G5,$G5*(1+$H5)^(2035-$E5)))))) | AA5: =IF($A5="","",IF(2036<$E5,"",IF($D5="Manuell","",IF(2036>$E5+$F5,IF($D5="Fix",$G5,$G5*(1+$H5)^($F5)),IF($D5="Fix",$G5,$G5*(1+$H5)^(2036-$E5)))))) | AB5: =IF($A5="","",IF(2037<$E5,"",IF($D5="Manuell","",IF(2037>$E5+$F5,IF($D5="Fix",$G5,$G5*(1+$H5)^($F5)),IF($D5="Fix",$G5,$G5*(1+$H5)^(2037-$E5)))))) | AC5: =IF($A5="","",IF(2038<$E5,"",IF($D5="Manuell","",IF(2038>$E5+$F5,IF($D5="Fix",$G5,$G5*(1+$H5)^($F5)),IF($D5="Fix",$G5,$G5*(1+$H5)^(2038-$E5)))))) | AD5: =IF($A5="","",IF(2039<$E5,"",IF($D5="Manuell","",IF(2039>$E5+$F5,IF($D5="Fix",$G5,$G5*(1+$H5)^($F5)),IF($D5="Fix",$G5,$G5*(1+$H5)^(2039-$E5)))))) | AE5: =IF($A5="","",IF(2040<$E5,"",IF($D5="Manuell","",IF(2040>$E5+$F5,IF($D5="Fix",$G5,$G5*(1+$H5)^($F5)),IF($D5="Fix",$G5,$G5*(1+$H5)^(2040-$E5)))))) | AF5: =IF($A5="","",IF(2041<$E5,"",IF($D5="Manuell","",IF(2041>$E5+$F5,IF($D5="Fix",$G5,$G5*(1+$H5)^($F5)),IF($D5="Fix",$G5,$G5*(1+$H5)^(2041-$E5)))))) | AG5: =IF($A5="","",IF(2042<$E5,"",IF($D5="Manuell","",IF(2042>$E5+$F5,IF($D5="Fix",$G5,$G5*(1+$H5)^($F5)),IF($D5="Fix",$G5,$G5*(1+$H5)^(2042-$E5)))))) | AH5: =IF($A5="","",IF(2043<$E5,"",IF($D5="Manuell","",IF(2043>$E5+$F5,IF($D5="Fix",$G5,$G5*(1+$H5)^($F5)),IF($D5="Fix",$G5,$G5*(1+$H5)^(2043-$E5)))))) | AI5: =IF($A5="","",IF(2044<$E5,"",IF($D5="Manuell","",IF(2044>$E5+$F5,IF($D5="Fix",$G5,$G5*(1+$H5)^($F5)),IF($D5="Fix",$G5,$G5*(1+$H5)^(2044-$E5)))))) | AJ5: =IF($A5="","",IF(2045<$E5,"",IF($D5="Manuell","",IF(2045>$E5+$F5,IF($D5="Fix",$G5,$G5*(1+$H5)^($F5)),IF($D5="Fix",$G5,$G5*(1+$H5)^(2045-$E5)))))) | AK5: =IF($A5="","",IF(2046<$E5,"",IF($D5="Manuell","",IF(2046>$E5+$F5,IF($D5="Fix",$G5,$G5*(1+$H5)^($F5)),IF($D5="Fix",$G5,$G5*(1+$H5)^(2046-$E5)))))) | AL5: =IF($A5="","",IF(2047<$E5,"",IF($D5="Manuell","",IF(2047>$E5+$F5,IF($D5="Fix",$G5,$G5*(1+$H5)^($F5)),IF($D5="Fix",$G5,$G5*(1+$H5)^(2047-$E5)))))) | AM5: =IF($A5="","",IF(2048<$E5,"",IF($D5="Manuell","",IF(2048>$E5+$F5,IF($D5="Fix",$G5,$G5*(1+$H5)^($F5)),IF($D5="Fix",$G5,$G5*(1+$H5)^(2048-$E5)))))) | AN5: =IF($A5="","",IF(2049<$E5,"",IF($D5="Manuell","",IF(2049>$E5+$F5,IF($D5="Fix",$G5,$G5*(1+$H5)^($F5)),IF($D5="Fix",$G5,$G5*(1+$H5)^(2049-$E5)))))) | AO5: =IF($A5="","",IF(2050<$E5,"",IF($D5="Manuell","",IF(2050>$E5+$F5,IF($D5="Fix",$G5,$G5*(1+$H5)^($F5)),IF($D5="Fix",$G5,$G5*(1+$H5)^(2050-$E5)))))) | AP5: =IF($A5="","",IF(2051<$E5,"",IF($D5="Manuell","",IF(2051>$E5+$F5,IF($D5="Fix",$G5,$G5*(1+$H5)^($F5)),IF($D5="Fix",$G5,$G5*(1+$H5)^(2051-$E5)))))) | AQ5: =IF($A5="","",IF(2052<$E5,"",IF($D5="Manuell","",IF(2052>$E5+$F5,IF($D5="Fix",$G5,$G5*(1+$H5)^($F5)),IF($D5="Fix",$G5,$G5*(1+$H5)^(2052-$E5)))))) | AR5: =IF($A5="","",IF(2053<$E5,"",IF($D5="Manuell","",IF(2053>$E5+$F5,IF($D5="Fix",$G5,$G5*(1+$H5)^($F5)),IF($D5="Fix",$G5,$G5*(1+$H5)^(2053-$E5)))))) | AS5: =IF($A5="","",IF(2054<$E5,"",IF($D5="Manuell","",IF(2054>$E5+$F5,IF($D5="Fix",$G5,$G5*(1+$H5)^($F5)),IF($D5="Fix",$G5,$G5*(1+$H5)^(2054-$E5)))))) | AT5: =IF($A5="","",IF(2055<$E5,"",IF($D5="Manuell","",IF(2055>$E5+$F5,IF($D5="Fix",$G5,$G5*(1+$H5)^($F5)),IF($D5="Fix",$G5,$G5*(1+$H5)^(2055-$E5))))))
A6: Dieselpreis | B6: Dieselpreis | C6: EUR/L | D6: CAGR | E6: 2020 | F6: 25 | G6: 1.4 | H6: 0.02 | I6: =IF($A6="","",IF(2018<$E6,"",IF($D6="Manuell","",IF(2018>$E6+$F6,IF($D6="Fix",$G6,$G6*(1+$H6)^($F6)),IF($D6="Fix",$G6,$G6*(1+$H6)^(2018-$E6)))))) | J6: =IF($A6="","",IF(2019<$E6,"",IF($D6="Manuell","",IF(2019>$E6+$F6,IF($D6="Fix",$G6,$G6*(1+$H6)^($F6)),IF($D6="Fix",$G6,$G6*(1+$H6)^(2019-$E6)))))) | K6: =IF($A6="","",IF(2020<$E6,"",IF($D6="Manuell","",IF(2020>$E6+$F6,IF($D6="Fix",$G6,$G6*(1+$H6)^($F6)),IF($D6="Fix",$G6,$G6*(1+$H6)^(2020-$E6)))))) | L6: =IF($A6="","",IF(2021<$E6,"",IF($D6="Manuell","",IF(2021>$E6+$F6,IF($D6="Fix",$G6,$G6*(1+$H6)^($F6)),IF($D6="Fix",$G6,$G6*(1+$H6)^(2021-$E6)))))) | M6: =IF($A6="","",IF(2022<$E6,"",IF($D6="Manuell","",IF(2022>$E6+$F6,IF($D6="Fix",$G6,$G6*(1+$H6)^($F6)),IF($D6="Fix",$G6,$G6*(1+$H6)^(2022-$E6)))))) | N6: =IF($A6="","",IF(2023<$E6,"",IF($D6="Manuell","",IF(2023>$E6+$F6,IF($D6="Fix",$G6,$G6*(1+$H6)^($F6)),IF($D6="Fix",$G6,$G6*(1+$H6)^(2023-$E6)))))) | O6: =IF($A6="","",IF(2024<$E6,"",IF($D6="Manuell","",IF(2024>$E6+$F6,IF($D6="Fix",$G6,$G6*(1+$H6)^($F6)),IF($D6="Fix",$G6,$G6*(1+$H6)^(2024-$E6)))))) | P6: =IF($A6="","",IF(2025<$E6,"",IF($D6="Manuell","",IF(2025>$E6+$F6,IF($D6="Fix",$G6,$G6*(1+$H6)^($F6)),IF($D6="Fix",$G6,$G6*(1+$H6)^(2025-$E6)))))) | Q6: =IF($A6="","",IF(2026<$E6,"",IF($D6="Manuell","",IF(2026>$E6+$F6,IF($D6="Fix",$G6,$G6*(1+$H6)^($F6)),IF($D6="Fix",$G6,$G6*(1+$H6)^(2026-$E6)))))) | R6: =IF($A6="","",IF(2027<$E6,"",IF($D6="Manuell","",IF(2027>$E6+$F6,IF($D6="Fix",$G6,$G6*(1+$H6)^($F6)),IF($D6="Fix",$G6,$G6*(1+$H6)^(2027-$E6)))))) | S6: =IF($A6="","",IF(2028<$E6,"",IF($D6="Manuell","",IF(2028>$E6+$F6,IF($D6="Fix",$G6,$G6*(1+$H6)^($F6)),IF($D6="Fix",$G6,$G6*(1+$H6)^(2028-$E6)))))) | T6: =IF($A6="","",IF(2029<$E6,"",IF($D6="Manuell","",IF(2029>$E6+$F6,IF($D6="Fix",$G6,$G6*(1+$H6)^($F6)),IF($D6="Fix",$G6,$G6*(1+$H6)^(2029-$E6)))))) | U6: =IF($A6="","",IF(2030<$E6,"",IF($D6="Manuell","",IF(2030>$E6+$F6,IF($D6="Fix",$G6,$G6*(1+$H6)^($F6)),IF($D6="Fix",$G6,$G6*(1+$H6)^(2030-$E6)))))) | V6: =IF($A6="","",IF(2031<$E6,"",IF($D6="Manuell","",IF(2031>$E6+$F6,IF($D6="Fix",$G6,$G6*(1+$H6)^($F6)),IF($D6="Fix",$G6,$G6*(1+$H6)^(2031-$E6)))))) | W6: =IF($A6="","",IF(2032<$E6,"",IF($D6="Manuell","",IF(2032>$E6+$F6,IF($D6="Fix",$G6,$G6*(1+$H6)^($F6)),IF($D6="Fix",$G6,$G6*(1+$H6)^(2032-$E6)))))) | X6: =IF($A6="","",IF(2033<$E6,"",IF($D6="Manuell","",IF(2033>$E6+$F6,IF($D6="Fix",$G6,$G6*(1+$H6)^($F6)),IF($D6="Fix",$G6,$G6*(1+$H6)^(2033-$E6)))))) | Y6: =IF($A6="","",IF(2034<$E6,"",IF($D6="Manuell","",IF(2034>$E6+$F6,IF($D6="Fix",$G6,$G6*(1+$H6)^($F6)),IF($D6="Fix",$G6,$G6*(1+$H6)^(2034-$E6)))))) | Z6: =IF($A6="","",IF(2035<$E6,"",IF($D6="Manuell","",IF(2035>$E6+$F6,IF($D6="Fix",$G6,$G6*(1+$H6)^($F6)),IF($D6="Fix",$G6,$G6*(1+$H6)^(2035-$E6)))))) | AA6: =IF($A6="","",IF(2036<$E6,"",IF($D6="Manuell","",IF(2036>$E6+$F6,IF($D6="Fix",$G6,$G6*(1+$H6)^($F6)),IF($D6="Fix",$G6,$G6*(1+$H6)^(2036-$E6)))))) | AB6: =IF($A6="","",IF(2037<$E6,"",IF($D6="Manuell","",IF(2037>$E6+$F6,IF($D6="Fix",$G6,$G6*(1+$H6)^($F6)),IF($D6="Fix",$G6,$G6*(1+$H6)^(2037-$E6)))))) | AC6: =IF($A6="","",IF(2038<$E6,"",IF($D6="Manuell","",IF(2038>$E6+$F6,IF($D6="Fix",$G6,$G6*(1+$H6)^($F6)),IF($D6="Fix",$G6,$G6*(1+$H6)^(2038-$E6)))))) | AD6: =IF($A6="","",IF(2039<$E6,"",IF($D6="Manuell","",IF(2039>$E6+$F6,IF($D6="Fix",$G6,$G6*(1+$H6)^($F6)),IF($D6="Fix",$G6,$G6*(1+$H6)^(2039-$E6)))))) | AE6: =IF($A6="","",IF(2040<$E6,"",IF($D6="Manuell","",IF(2040>$E6+$F6,IF($D6="Fix",$G6,$G6*(1+$H6)^($F6)),IF($D6="Fix",$G6,$G6*(1+$H6)^(2040-$E6)))))) | AF6: =IF($A6="","",IF(2041<$E6,"",IF($D6="Manuell","",IF(2041>$E6+$F6,IF($D6="Fix",$G6,$G6*(1+$H6)^($F6)),IF($D6="Fix",$G6,$G6*(1+$H6)^(2041-$E6)))))) | AG6: =IF($A6="","",IF(2042<$E6,"",IF($D6="Manuell","",IF(2042>$E6+$F6,IF($D6="Fix",$G6,$G6*(1+$H6)^($F6)),IF($D6="Fix",$G6,$G6*(1+$H6)^(2042-$E6)))))) | AH6: =IF($A6="","",IF(2043<$E6,"",IF($D6="Manuell","",IF(2043>$E6+$F6,IF($D6="Fix",$G6,$G6*(1+$H6)^($F6)),IF($D6="Fix",$G6,$G6*(1+$H6)^(2043-$E6)))))) | AI6: =IF($A6="","",IF(2044<$E6,"",IF($D6="Manuell","",IF(2044>$E6+$F6,IF($D6="Fix",$G6,$G6*(1+$H6)^($F6)),IF($D6="Fix",$G6,$G6*(1+$H6)^(2044-$E6)))))) | AJ6: =IF($A6="","",IF(2045<$E6,"",IF($D6="Manuell","",IF(2045>$E6+$F6,IF($D6="Fix",$G6,$G6*(1+$H6)^($F6)),IF($D6="Fix",$G6,$G6*(1+$H6)^(2045-$E6)))))) | AK6: =IF($A6="","",IF(2046<$E6,"",IF($D6="Manuell","",IF(2046>$E6+$F6,IF($D6="Fix",$G6,$G6*(1+$H6)^($F6)),IF($D6="Fix",$G6,$G6*(1+$H6)^(2046-$E6)))))) | AL6: =IF($A6="","",IF(2047<$E6,"",IF($D6="Manuell","",IF(2047>$E6+$F6,IF($D6="Fix",$G6,$G6*(1+$H6)^($F6)),IF($D6="Fix",$G6,$G6*(1+$H6)^(2047-$E6)))))) | AM6: =IF($A6="","",IF(2048<$E6,"",IF($D6="Manuell","",IF(2048>$E6+$F6,IF($D6="Fix",$G6,$G6*(1+$H6)^($F6)),IF($D6="Fix",$G6,$G6*(1+$H6)^(2048-$E6)))))) | AN6: =IF($A6="","",IF(2049<$E6,"",IF($D6="Manuell","",IF(2049>$E6+$F6,IF($D6="Fix",$G6,$G6*(1+$H6)^($F6)),IF($D6="Fix",$G6,$G6*(1+$H6)^(2049-$E6)))))) | AO6: =IF($A6="","",IF(2050<$E6,"",IF($D6="Manuell","",IF(2050>$E6+$F6,IF($D6="Fix",$G6,$G6*(1+$H6)^($F6)),IF($D6="Fix",$G6,$G6*(1+$H6)^(2050-$E6)))))) | AP6: =IF($A6="","",IF(2051<$E6,"",IF($D6="Manuell","",IF(2051>$E6+$F6,IF($D6="Fix",$G6,$G6*(1+$H6)^($F6)),IF($D6="Fix",$G6,$G6*(1+$H6)^(2051-$E6)))))) | AQ6: =IF($A6="","",IF(2052<$E6,"",IF($D6="Manuell","",IF(2052>$E6+$F6,IF($D6="Fix",$G6,$G6*(1+$H6)^($F6)),IF($D6="Fix",$G6,$G6*(1+$H6)^(2052-$E6)))))) | AR6: =IF($A6="","",IF(2053<$E6,"",IF($D6="Manuell","",IF(2053>$E6+$F6,IF($D6="Fix",$G6,$G6*(1+$H6)^($F6)),IF($D6="Fix",$G6,$G6*(1+$H6)^(2053-$E6)))))) | AS6: =IF($A6="","",IF(2054<$E6,"",IF($D6="Manuell","",IF(2054>$E6+$F6,IF($D6="Fix",$G6,$G6*(1+$H6)^($F6)),IF($D6="Fix",$G6,$G6*(1+$H6)^(2054-$E6)))))) | AT6: =IF($A6="","",IF(2055<$E6,"",IF($D6="Manuell","",IF(2055>$E6+$F6,IF($D6="Fix",$G6,$G6*(1+$H6)^($F6)),IF($D6="Fix",$G6,$G6*(1+$H6)^(2055-$E6))))))
A7: Wasserpreis | B7: Wasserpreis | C7: EUR/m3 | D7: CAGR | E7: 2025 | F7: 20 | G7: 2.5 | H7: 0.02 | I7: =IF($A7="","",IF(2018<$E7,"",IF($D7="Manuell","",IF(2018>$E7+$F7,IF($D7="Fix",$G7,$G7*(1+$H7)^($F7)),IF($D7="Fix",$G7,$G7*(1+$H7)^(2018-$E7)))))) | J7: =IF($A7="","",IF(2019<$E7,"",IF($D7="Manuell","",IF(2019>$E7+$F7,IF($D7="Fix",$G7,$G7*(1+$H7)^($F7)),IF($D7="Fix",$G7,$G7*(1+$H7)^(2019-$E7)))))) | K7: =IF($A7="","",IF(2020<$E7,"",IF($D7="Manuell","",IF(2020>$E7+$F7,IF($D7="Fix",$G7,$G7*(1+$H7)^($F7)),IF($D7="Fix",$G7,$G7*(1+$H7)^(2020-$E7)))))) | L7: =IF($A7="","",IF(2021<$E7,"",IF($D7="Manuell","",IF(2021>$E7+$F7,IF($D7="Fix",$G7,$G7*(1+$H7)^($F7)),IF($D7="Fix",$G7,$G7*(1+$H7)^(2021-$E7)))))) | M7: =IF($A7="","",IF(2022<$E7,"",IF($D7="Manuell","",IF(2022>$E7+$F7,IF($D7="Fix",$G7,$G7*(1+$H7)^($F7)),IF($D7="Fix",$G7,$G7*(1+$H7)^(2022-$E7)))))) | N7: =IF($A7="","",IF(2023<$E7,"",IF($D7="Manuell","",IF(2023>$E7+$F7,IF($D7="Fix",$G7,$G7*(1+$H7)^($F7)),IF($D7="Fix",$G7,$G7*(1+$H7)^(2023-$E7)))))) | O7: =IF($A7="","",IF(2024<$E7,"",IF($D7="Manuell","",IF(2024>$E7+$F7,IF($D7="Fix",$G7,$G7*(1+$H7)^($F7)),IF($D7="Fix",$G7,$G7*(1+$H7)^(2024-$E7)))))) | P7: =IF($A7="","",IF(2025<$E7,"",IF($D7="Manuell","",IF(2025>$E7+$F7,IF($D7="Fix",$G7,$G7*(1+$H7)^($F7)),IF($D7="Fix",$G7,$G7*(1+$H7)^(2025-$E7)))))) | Q7: =IF($A7="","",IF(2026<$E7,"",IF($D7="Manuell","",IF(2026>$E7+$F7,IF($D7="Fix",$G7,$G7*(1+$H7)^($F7)),IF($D7="Fix",$G7,$G7*(1+$H7)^(2026-$E7)))))) | R7: =IF($A7="","",IF(2027<$E7,"",IF($D7="Manuell","",IF(2027>$E7+$F7,IF($D7="Fix",$G7,$G7*(1+$H7)^($F7)),IF($D7="Fix",$G7,$G7*(1+$H7)^(2027-$E7)))))) | S7: =IF($A7="","",IF(2028<$E7,"",IF($D7="Manuell","",IF(2028>$E7+$F7,IF($D7="Fix",$G7,$G7*(1+$H7)^($F7)),IF($D7="Fix",$G7,$G7*(1+$H7)^(2028-$E7)))))) | T7: =IF($A7="","",IF(2029<$E7,"",IF($D7="Manuell","",IF(2029>$E7+$F7,IF($D7="Fix",$G7,$G7*(1+$H7)^($F7)),IF($D7="Fix",$G7,$G7*(1+$H7)^(2029-$E7)))))) | U7: =IF($A7="","",IF(2030<$E7,"",IF($D7="Manuell","",IF(2030>$E7+$F7,IF($D7="Fix",$G7,$G7*(1+$H7)^($F7)),IF($D7="Fix",$G7,$G7*(1+$H7)^(2030-$E7)))))) | V7: =IF($A7="","",IF(2031<$E7,"",IF($D7="Manuell","",IF(2031>$E7+$F7,IF($D7="Fix",$G7,$G7*(1+$H7)^($F7)),IF($D7="Fix",$G7,$G7*(1+$H7)^(2031-$E7)))))) | W7: =IF($A7="","",IF(2032<$E7,"",IF($D7="Manuell","",IF(2032>$E7+$F7,IF($D7="Fix",$G7,$G7*(1+$H7)^($F7)),IF($D7="Fix",$G7,$G7*(1+$H7)^(2032-$E7)))))) | X7: =IF($A7="","",IF(2033<$E7,"",IF($D7="Manuell","",IF(2033>$E7+$F7,IF($D7="Fix",$G7,$G7*(1+$H7)^($F7)),IF($D7="Fix",$G7,$G7*(1+$H7)^(2033-$E7)))))) | Y7: =IF($A7="","",IF(2034<$E7,"",IF($D7="Manuell","",IF(2034>$E7+$F7,IF($D7="Fix",$G7,$G7*(1+$H7)^($F7)),IF($D7="Fix",$G7,$G7*(1+$H7)^(2034-$E7)))))) | Z7: =IF($A7="","",IF(2035<$E7,"",IF($D7="Manuell","",IF(2035>$E7+$F7,IF($D7="Fix",$G7,$G7*(1+$H7)^($F7)),IF($D7="Fix",$G7,$G7*(1+$H7)^(2035-$E7)))))) | AA7: =IF($A7="","",IF(2036<$E7,"",IF($D7="Manuell","",IF(2036>$E7+$F7,IF($D7="Fix",$G7,$G7*(1+$H7)^($F7)),IF($D7="Fix",$G7,$G7*(1+$H7)^(2036-$E7)))))) | AB7: =IF($A7="","",IF(2037<$E7,"",IF($D7="Manuell","",IF(2037>$E7+$F7,IF($D7="Fix",$G7,$G7*(1+$H7)^($F7)),IF($D7="Fix",$G7,$G7*(1+$H7)^(2037-$E7)))))) | AC7: =IF($A7="","",IF(2038<$E7,"",IF($D7="Manuell","",IF(2038>$E7+$F7,IF($D7="Fix",$G7,$G7*(1+$H7)^($F7)),IF($D7="Fix",$G7,$G7*(1+$H7)^(2038-$E7)))))) | AD7: =IF($A7="","",IF(2039<$E7,"",IF($D7="Manuell","",IF(2039>$E7+$F7,IF($D7="Fix",$G7,$G7*(1+$H7)^($F7)),IF($D7="Fix",$G7,$G7*(1+$H7)^(2039-$E7)))))) | AE7: =IF($A7="","",IF(2040<$E7,"",IF($D7="Manuell","",IF(2040>$E7+$F7,IF($D7="Fix",$G7,$G7*(1+$H7)^($F7)),IF($D7="Fix",$G7,$G7*(1+$H7)^(2040-$E7)))))) | AF7: =IF($A7="","",IF(2041<$E7,"",IF($D7="Manuell","",IF(2041>$E7+$F7,IF($D7="Fix",$G7,$G7*(1+$H7)^($F7)),IF($D7="Fix",$G7,$G7*(1+$H7)^(2041-$E7)))))) | AG7: =IF($A7="","",IF(2042<$E7,"",IF($D7="Manuell","",IF(2042>$E7+$F7,IF($D7="Fix",$G7,$G7*(1+$H7)^($F7)),IF($D7="Fix",$G7,$G7*(1+$H7)^(2042-$E7)))))) | AH7: =IF($A7="","",IF(2043<$E7,"",IF($D7="Manuell","",IF(2043>$E7+$F7,IF($D7="Fix",$G7,$G7*(1+$H7)^($F7)),IF($D7="Fix",$G7,$G7*(1+$H7)^(2043-$E7)))))) | AI7: =IF($A7="","",IF(2044<$E7,"",IF($D7="Manuell","",IF(2044>$E7+$F7,IF($D7="Fix",$G7,$G7*(1+$H7)^($F7)),IF($D7="Fix",$G7,$G7*(1+$H7)^(2044-$E7)))))) | AJ7: =IF($A7="","",IF(2045<$E7,"",IF($D7="Manuell","",IF(2045>$E7+$F7,IF($D7="Fix",$G7,$G7*(1+$H7)^($F7)),IF($D7="Fix",$G7,$G7*(1+$H7)^(2045-$E7)))))) | AK7: =IF($A7="","",IF(2046<$E7,"",IF($D7="Manuell","",IF(2046>$E7+$F7,IF($D7="Fix",$G7,$G7*(1+$H7)^($F7)),IF($D7="Fix",$G7,$G7*(1+$H7)^(2046-$E7)))))) | AL7: =IF($A7="","",IF(2047<$E7,"",IF($D7="Manuell","",IF(2047>$E7+$F7,IF($D7="Fix",$G7,$G7*(1+$H7)^($F7)),IF($D7="Fix",$G7,$G7*(1+$H7)^(2047-$E7)))))) | AM7: =IF($A7="","",IF(2048<$E7,"",IF($D7="Manuell","",IF(2048>$E7+$F7,IF($D7="Fix",$G7,$G7*(1+$H7)^($F7)),IF($D7="Fix",$G7,$G7*(1+$H7)^(2048-$E7)))))) | AN7: =IF($A7="","",IF(2049<$E7,"",IF($D7="Manuell","",IF(2049>$E7+$F7,IF($D7="Fix",$G7,$G7*(1+$H7)^($F7)),IF($D7="Fix",$G7,$G7*(1+$H7)^(2049-$E7)))))) | AO7: =IF($A7="","",IF(2050<$E7,"",IF($D7="Manuell","",IF(2050>$E7+$F7,IF($D7="Fix",$G7,$G7*(1+$H7)^($F7)),IF($D7="Fix",$G7,$G7*(1+$H7)^(2050-$E7)))))) | AP7: =IF($A7="","",IF(2051<$E7,"",IF($D7="Manuell","",IF(2051>$E7+$F7,IF($D7="Fix",$G7,$G7*(1+$H7)^($F7)),IF($D7="Fix",$G7,$G7*(1+$H7)^(2051-$E7)))))) | AQ7: =IF($A7="","",IF(2052<$E7,"",IF($D7="Manuell","",IF(2052>$E7+$F7,IF($D7="Fix",$G7,$G7*(1+$H7)^($F7)),IF($D7="Fix",$G7,$G7*(1+$H7)^(2052-$E7)))))) | AR7: =IF($A7="","",IF(2053<$E7,"",IF($D7="Manuell","",IF(2053>$E7+$F7,IF($D7="Fix",$G7,$G7*(1+$H7)^($F7)),IF($D7="Fix",$G7,$G7*(1+$H7)^(2053-$E7)))))) | AS7: =IF($A7="","",IF(2054<$E7,"",IF($D7="Manuell","",IF(2054>$E7+$F7,IF($D7="Fix",$G7,$G7*(1+$H7)^($F7)),IF($D7="Fix",$G7,$G7*(1+$H7)^(2054-$E7)))))) | AT7: =IF($A7="","",IF(2055<$E7,"",IF($D7="Manuell","",IF(2055>$E7+$F7,IF($D7="Fix",$G7,$G7*(1+$H7)^($F7)),IF($D7="Fix",$G7,$G7*(1+$H7)^(2055-$E7))))))
A8: Entsorgungspreis | B8: Entsorgung | C8: EUR/t | D8: CAGR | E8: 2025 | F8: 20 | G8: 150 | H8: 0.02 | I8: =IF($A8="","",IF(2018<$E8,"",IF($D8="Manuell","",IF(2018>$E8+$F8,IF($D8="Fix",$G8,$G8*(1+$H8)^($F8)),IF($D8="Fix",$G8,$G8*(1+$H8)^(2018-$E8)))))) | J8: =IF($A8="","",IF(2019<$E8,"",IF($D8="Manuell","",IF(2019>$E8+$F8,IF($D8="Fix",$G8,$G8*(1+$H8)^($F8)),IF($D8="Fix",$G8,$G8*(1+$H8)^(2019-$E8)))))) | K8: =IF($A8="","",IF(2020<$E8,"",IF($D8="Manuell","",IF(2020>$E8+$F8,IF($D8="Fix",$G8,$G8*(1+$H8)^($F8)),IF($D8="Fix",$G8,$G8*(1+$H8)^(2020-$E8)))))) | L8: =IF($A8="","",IF(2021<$E8,"",IF($D8="Manuell","",IF(2021>$E8+$F8,IF($D8="Fix",$G8,$G8*(1+$H8)^($F8)),IF($D8="Fix",$G8,$G8*(1+$H8)^(2021-$E8)))))) | M8: =IF($A8="","",IF(2022<$E8,"",IF($D8="Manuell","",IF(2022>$E8+$F8,IF($D8="Fix",$G8,$G8*(1+$H8)^($F8)),IF($D8="Fix",$G8,$G8*(1+$H8)^(2022-$E8)))))) | N8: =IF($A8="","",IF(2023<$E8,"",IF($D8="Manuell","",IF(2023>$E8+$F8,IF($D8="Fix",$G8,$G8*(1+$H8)^($F8)),IF($D8="Fix",$G8,$G8*(1+$H8)^(2023-$E8)))))) | O8: =IF($A8="","",IF(2024<$E8,"",IF($D8="Manuell","",IF(2024>$E8+$F8,IF($D8="Fix",$G8,$G8*(1+$H8)^($F8)),IF($D8="Fix",$G8,$G8*(1+$H8)^(2024-$E8)))))) | P8: =IF($A8="","",IF(2025<$E8,"",IF($D8="Manuell","",IF(2025>$E8+$F8,IF($D8="Fix",$G8,$G8*(1+$H8)^($F8)),IF($D8="Fix",$G8,$G8*(1+$H8)^(2025-$E8)))))) | Q8: =IF($A8="","",IF(2026<$E8,"",IF($D8="Manuell","",IF(2026>$E8+$F8,IF($D8="Fix",$G8,$G8*(1+$H8)^($F8)),IF($D8="Fix",$G8,$G8*(1+$H8)^(2026-$E8)))))) | R8: =IF($A8="","",IF(2027<$E8,"",IF($D8="Manuell","",IF(2027>$E8+$F8,IF($D8="Fix",$G8,$G8*(1+$H8)^($F8)),IF($D8="Fix",$G8,$G8*(1+$H8)^(2027-$E8)))))) | S8: =IF($A8="","",IF(2028<$E8,"",IF($D8="Manuell","",IF(2028>$E8+$F8,IF($D8="Fix",$G8,$G8*(1+$H8)^($F8)),IF($D8="Fix",$G8,$G8*(1+$H8)^(2028-$E8)))))) | T8: =IF($A8="","",IF(2029<$E8,"",IF($D8="Manuell","",IF(2029>$E8+$F8,IF($D8="Fix",$G8,$G8*(1+$H8)^($F8)),IF($D8="Fix",$G8,$G8*(1+$H8)^(2029-$E8)))))) | U8: =IF($A8="","",IF(2030<$E8,"",IF($D8="Manuell","",IF(2030>$E8+$F8,IF($D8="Fix",$G8,$G8*(1+$H8)^($F8)),IF($D8="Fix",$G8,$G8*(1+$H8)^(2030-$E8)))))) | V8: =IF($A8="","",IF(2031<$E8,"",IF($D8="Manuell","",IF(2031>$E8+$F8,IF($D8="Fix",$G8,$G8*(1+$H8)^($F8)),IF($D8="Fix",$G8,$G8*(1+$H8)^(2031-$E8)))))) | W8: =IF($A8="","",IF(2032<$E8,"",IF($D8="Manuell","",IF(2032>$E8+$F8,IF($D8="Fix",$G8,$G8*(1+$H8)^($F8)),IF($D8="Fix",$G8,$G8*(1+$H8)^(2032-$E8)))))) | X8: =IF($A8="","",IF(2033<$E8,"",IF($D8="Manuell","",IF(2033>$E8+$F8,IF($D8="Fix",$G8,$G8*(1+$H8)^($F8)),IF($D8="Fix",$G8,$G8*(1+$H8)^(2033-$E8)))))) | Y8: =IF($A8="","",IF(2034<$E8,"",IF($D8="Manuell","",IF(2034>$E8+$F8,IF($D8="Fix",$G8,$G8*(1+$H8)^($F8)),IF($D8="Fix",$G8,$G8*(1+$H8)^(2034-$E8)))))) | Z8: =IF($A8="","",IF(2035<$E8,"",IF($D8="Manuell","",IF(2035>$E8+$F8,IF($D8="Fix",$G8,$G8*(1+$H8)^($F8)),IF($D8="Fix",$G8,$G8*(1+$H8)^(2035-$E8)))))) | AA8: =IF($A8="","",IF(2036<$E8,"",IF($D8="Manuell","",IF(2036>$E8+$F8,IF($D8="Fix",$G8,$G8*(1+$H8)^($F8)),IF($D8="Fix",$G8,$G8*(1+$H8)^(2036-$E8)))))) | AB8: =IF($A8="","",IF(2037<$E8,"",IF($D8="Manuell","",IF(2037>$E8+$F8,IF($D8="Fix",$G8,$G8*(1+$H8)^($F8)),IF($D8="Fix",$G8,$G8*(1+$H8)^(2037-$E8)))))) | AC8: =IF($A8="","",IF(2038<$E8,"",IF($D8="Manuell","",IF(2038>$E8+$F8,IF($D8="Fix",$G8,$G8*(1+$H8)^($F8)),IF($D8="Fix",$G8,$G8*(1+$H8)^(2038-$E8)))))) | AD8: =IF($A8="","",IF(2039<$E8,"",IF($D8="Manuell","",IF(2039>$E8+$F8,IF($D8="Fix",$G8,$G8*(1+$H8)^($F8)),IF($D8="Fix",$G8,$G8*(1+$H8)^(2039-$E8)))))) | AE8: =IF($A8="","",IF(2040<$E8,"",IF($D8="Manuell","",IF(2040>$E8+$F8,IF($D8="Fix",$G8,$G8*(1+$H8)^($F8)),IF($D8="Fix",$G8,$G8*(1+$H8)^(2040-$E8)))))) | AF8: =IF($A8="","",IF(2041<$E8,"",IF($D8="Manuell","",IF(2041>$E8+$F8,IF($D8="Fix",$G8,$G8*(1+$H8)^($F8)),IF($D8="Fix",$G8,$G8*(1+$H8)^(2041-$E8)))))) | AG8: =IF($A8="","",IF(2042<$E8,"",IF($D8="Manuell","",IF(2042>$E8+$F8,IF($D8="Fix",$G8,$G8*(1+$H8)^($F8)),IF($D8="Fix",$G8,$G8*(1+$H8)^(2042-$E8)))))) | AH8: =IF($A8="","",IF(2043<$E8,"",IF($D8="Manuell","",IF(2043>$E8+$F8,IF($D8="Fix",$G8,$G8*(1+$H8)^($F8)),IF($D8="Fix",$G8,$G8*(1+$H8)^(2043-$E8)))))) | AI8: =IF($A8="","",IF(2044<$E8,"",IF($D8="Manuell","",IF(2044>$E8+$F8,IF($D8="Fix",$G8,$G8*(1+$H8)^($F8)),IF($D8="Fix",$G8,$G8*(1+$H8)^(2044-$E8)))))) | AJ8: =IF($A8="","",IF(2045<$E8,"",IF($D8="Manuell","",IF(2045>$E8+$F8,IF($D8="Fix",$G8,$G8*(1+$H8)^($F8)),IF($D8="Fix",$G8,$G8*(1+$H8)^(2045-$E8)))))) | AK8: =IF($A8="","",IF(2046<$E8,"",IF($D8="Manuell","",IF(2046>$E8+$F8,IF($D8="Fix",$G8,$G8*(1+$H8)^($F8)),IF($D8="Fix",$G8,$G8*(1+$H8)^(2046-$E8)))))) | AL8: =IF($A8="","",IF(2047<$E8,"",IF($D8="Manuell","",IF(2047>$E8+$F8,IF($D8="Fix",$G8,$G8*(1+$H8)^($F8)),IF($D8="Fix",$G8,$G8*(1+$H8)^(2047-$E8)))))) | AM8: =IF($A8="","",IF(2048<$E8,"",IF($D8="Manuell","",IF(2048>$E8+$F8,IF($D8="Fix",$G8,$G8*(1+$H8)^($F8)),IF($D8="Fix",$G8,$G8*(1+$H8)^(2048-$E8)))))) | AN8: =IF($A8="","",IF(2049<$E8,"",IF($D8="Manuell","",IF(2049>$E8+$F8,IF($D8="Fix",$G8,$G8*(1+$H8)^($F8)),IF($D8="Fix",$G8,$G8*(1+$H8)^(2049-$E8)))))) | AO8: =IF($A8="","",IF(2050<$E8,"",IF($D8="Manuell","",IF(2050>$E8+$F8,IF($D8="Fix",$G8,$G8*(1+$H8)^($F8)),IF($D8="Fix",$G8,$G8*(1+$H8)^(2050-$E8)))))) | AP8: =IF($A8="","",IF(2051<$E8,"",IF($D8="Manuell","",IF(2051>$E8+$F8,IF($D8="Fix",$G8,$G8*(1+$H8)^($F8)),IF($D8="Fix",$G8,$G8*(1+$H8)^(2051-$E8)))))) | AQ8: =IF($A8="","",IF(2052<$E8,"",IF($D8="Manuell","",IF(2052>$E8+$F8,IF($D8="Fix",$G8,$G8*(1+$H8)^($F8)),IF($D8="Fix",$G8,$G8*(1+$H8)^(2052-$E8)))))) | AR8: =IF($A8="","",IF(2053<$E8,"",IF($D8="Manuell","",IF(2053>$E8+$F8,IF($D8="Fix",$G8,$G8*(1+$H8)^($F8)),IF($D8="Fix",$G8,$G8*(1+$H8)^(2053-$E8)))))) | AS8: =IF($A8="","",IF(2054<$E8,"",IF($D8="Manuell","",IF(2054>$E8+$F8,IF($D8="Fix",$G8,$G8*(1+$H8)^($F8)),IF($D8="Fix",$G8,$G8*(1+$H8)^(2054-$E8)))))) | AT8: =IF($A8="","",IF(2055<$E8,"",IF($D8="Manuell","",IF(2055>$E8+$F8,IF($D8="Fix",$G8,$G8*(1+$H8)^($F8)),IF($D8="Fix",$G8,$G8*(1+$H8)^(2055-$E8))))))
A9: Plastikpreis | B9: Kunststoff | C9: EUR/kg | D9: CAGR | E9: 2020 | F9: 20 | G9: 1.8 | H9: 0.01 | I9: =IF($A9="","",IF(2018<$E9,"",IF($D9="Manuell","",IF(2018>$E9+$F9,IF($D9="Fix",$G9,$G9*(1+$H9)^($F9)),IF($D9="Fix",$G9,$G9*(1+$H9)^(2018-$E9)))))) | J9: =IF($A9="","",IF(2019<$E9,"",IF($D9="Manuell","",IF(2019>$E9+$F9,IF($D9="Fix",$G9,$G9*(1+$H9)^($F9)),IF($D9="Fix",$G9,$G9*(1+$H9)^(2019-$E9)))))) | K9: =IF($A9="","",IF(2020<$E9,"",IF($D9="Manuell","",IF(2020>$E9+$F9,IF($D9="Fix",$G9,$G9*(1+$H9)^($F9)),IF($D9="Fix",$G9,$G9*(1+$H9)^(2020-$E9)))))) | L9: =IF($A9="","",IF(2021<$E9,"",IF($D9="Manuell","",IF(2021>$E9+$F9,IF($D9="Fix",$G9,$G9*(1+$H9)^($F9)),IF($D9="Fix",$G9,$G9*(1+$H9)^(2021-$E9)))))) | M9: =IF($A9="","",IF(2022<$E9,"",IF($D9="Manuell","",IF(2022>$E9+$F9,IF($D9="Fix",$G9,$G9*(1+$H9)^($F9)),IF($D9="Fix",$G9,$G9*(1+$H9)^(2022-$E9)))))) | N9: =IF($A9="","",IF(2023<$E9,"",IF($D9="Manuell","",IF(2023>$E9+$F9,IF($D9="Fix",$G9,$G9*(1+$H9)^($F9)),IF($D9="Fix",$G9,$G9*(1+$H9)^(2023-$E9)))))) | O9: =IF($A9="","",IF(2024<$E9,"",IF($D9="Manuell","",IF(2024>$E9+$F9,IF($D9="Fix",$G9,$G9*(1+$H9)^($F9)),IF($D9="Fix",$G9,$G9*(1+$H9)^(2024-$E9)))))) | P9: =IF($A9="","",IF(2025<$E9,"",IF($D9="Manuell","",IF(2025>$E9+$F9,IF($D9="Fix",$G9,$G9*(1+$H9)^($F9)),IF($D9="Fix",$G9,$G9*(1+$H9)^(2025-$E9)))))) | Q9: =IF($A9="","",IF(2026<$E9,"",IF($D9="Manuell","",IF(2026>$E9+$F9,IF($D9="Fix",$G9,$G9*(1+$H9)^($F9)),IF($D9="Fix",$G9,$G9*(1+$H9)^(2026-$E9)))))) | R9: =IF($A9="","",IF(2027<$E9,"",IF($D9="Manuell","",IF(2027>$E9+$F9,IF($D9="Fix",$G9,$G9*(1+$H9)^($F9)),IF($D9="Fix",$G9,$G9*(1+$H9)^(2027-$E9)))))) | S9: =IF($A9="","",IF(2028<$E9,"",IF($D9="Manuell","",IF(2028>$E9+$F9,IF($D9="Fix",$G9,$G9*(1+$H9)^($F9)),IF($D9="Fix",$G9,$G9*(1+$H9)^(2028-$E9)))))) | T9: =IF($A9="","",IF(2029<$E9,"",IF($D9="Manuell","",IF(2029>$E9+$F9,IF($D9="Fix",$G9,$G9*(1+$H9)^($F9)),IF($D9="Fix",$G9,$G9*(1+$H9)^(2029-$E9)))))) | U9: =IF($A9="","",IF(2030<$E9,"",IF($D9="Manuell","",IF(2030>$E9+$F9,IF($D9="Fix",$G9,$G9*(1+$H9)^($F9)),IF($D9="Fix",$G9,$G9*(1+$H9)^(2030-$E9)))))) | V9: =IF($A9="","",IF(2031<$E9,"",IF($D9="Manuell","",IF(2031>$E9+$F9,IF($D9="Fix",$G9,$G9*(1+$H9)^($F9)),IF($D9="Fix",$G9,$G9*(1+$H9)^(2031-$E9)))))) | W9: =IF($A9="","",IF(2032<$E9,"",IF($D9="Manuell","",IF(2032>$E9+$F9,IF($D9="Fix",$G9,$G9*(1+$H9)^($F9)),IF($D9="Fix",$G9,$G9*(1+$H9)^(2032-$E9)))))) | X9: =IF($A9="","",IF(2033<$E9,"",IF($D9="Manuell","",IF(2033>$E9+$F9,IF($D9="Fix",$G9,$G9*(1+$H9)^($F9)),IF($D9="Fix",$G9,$G9*(1+$H9)^(2033-$E9)))))) | Y9: =IF($A9="","",IF(2034<$E9,"",IF($D9="Manuell","",IF(2034>$E9+$F9,IF($D9="Fix",$G9,$G9*(1+$H9)^($F9)),IF($D9="Fix",$G9,$G9*(1+$H9)^(2034-$E9)))))) | Z9: =IF($A9="","",IF(2035<$E9,"",IF($D9="Manuell","",IF(2035>$E9+$F9,IF($D9="Fix",$G9,$G9*(1+$H9)^($F9)),IF($D9="Fix",$G9,$G9*(1+$H9)^(2035-$E9)))))) | AA9: =IF($A9="","",IF(2036<$E9,"",IF($D9="Manuell","",IF(2036>$E9+$F9,IF($D9="Fix",$G9,$G9*(1+$H9)^($F9)),IF($D9="Fix",$G9,$G9*(1+$H9)^(2036-$E9)))))) | AB9: =IF($A9="","",IF(2037<$E9,"",IF($D9="Manuell","",IF(2037>$E9+$F9,IF($D9="Fix",$G9,$G9*(1+$H9)^($F9)),IF($D9="Fix",$G9,$G9*(1+$H9)^(2037-$E9)))))) | AC9: =IF($A9="","",IF(2038<$E9,"",IF($D9="Manuell","",IF(2038>$E9+$F9,IF($D9="Fix",$G9,$G9*(1+$H9)^($F9)),IF($D9="Fix",$G9,$G9*(1+$H9)^(2038-$E9)))))) | AD9: =IF($A9="","",IF(2039<$E9,"",IF($D9="Manuell","",IF(2039>$E9+$F9,IF($D9="Fix",$G9,$G9*(1+$H9)^($F9)),IF($D9="Fix",$G9,$G9*(1+$H9)^(2039-$E9)))))) | AE9: =IF($A9="","",IF(2040<$E9,"",IF($D9="Manuell","",IF(2040>$E9+$F9,IF($D9="Fix",$G9,$G9*(1+$H9)^($F9)),IF($D9="Fix",$G9,$G9*(1+$H9)^(2040-$E9)))))) | AF9: =IF($A9="","",IF(2041<$E9,"",IF($D9="Manuell","",IF(2041>$E9+$F9,IF($D9="Fix",$G9,$G9*(1+$H9)^($F9)),IF($D9="Fix",$G9,$G9*(1+$H9)^(2041-$E9)))))) | AG9: =IF($A9="","",IF(2042<$E9,"",IF($D9="Manuell","",IF(2042>$E9+$F9,IF($D9="Fix",$G9,$G9*(1+$H9)^($F9)),IF($D9="Fix",$G9,$G9*(1+$H9)^(2042-$E9)))))) | AH9: =IF($A9="","",IF(2043<$E9,"",IF($D9="Manuell","",IF(2043>$E9+$F9,IF($D9="Fix",$G9,$G9*(1+$H9)^($F9)),IF($D9="Fix",$G9,$G9*(1+$H9)^(2043-$E9)))))) | AI9: =IF($A9="","",IF(2044<$E9,"",IF($D9="Manuell","",IF(2044>$E9+$F9,IF($D9="Fix",$G9,$G9*(1+$H9)^($F9)),IF($D9="Fix",$G9,$G9*(1+$H9)^(2044-$E9)))))) | AJ9: =IF($A9="","",IF(2045<$E9,"",IF($D9="Manuell","",IF(2045>$E9+$F9,IF($D9="Fix",$G9,$G9*(1+$H9)^($F9)),IF($D9="Fix",$G9,$G9*(1+$H9)^(2045-$E9)))))) | AK9: =IF($A9="","",IF(2046<$E9,"",IF($D9="Manuell","",IF(2046>$E9+$F9,IF($D9="Fix",$G9,$G9*(1+$H9)^($F9)),IF($D9="Fix",$G9,$G9*(1+$H9)^(2046-$E9)))))) | AL9: =IF($A9="","",IF(2047<$E9,"",IF($D9="Manuell","",IF(2047>$E9+$F9,IF($D9="Fix",$G9,$G9*(1+$H9)^($F9)),IF($D9="Fix",$G9,$G9*(1+$H9)^(2047-$E9)))))) | AM9: =IF($A9="","",IF(2048<$E9,"",IF($D9="Manuell","",IF(2048>$E9+$F9,IF($D9="Fix",$G9,$G9*(1+$H9)^($F9)),IF($D9="Fix",$G9,$G9*(1+$H9)^(2048-$E9)))))) | AN9: =IF($A9="","",IF(2049<$E9,"",IF($D9="Manuell","",IF(2049>$E9+$F9,IF($D9="Fix",$G9,$G9*(1+$H9)^($F9)),IF($D9="Fix",$G9,$G9*(1+$H9)^(2049-$E9)))))) | AO9: =IF($A9="","",IF(2050<$E9,"",IF($D9="Manuell","",IF(2050>$E9+$F9,IF($D9="Fix",$G9,$G9*(1+$H9)^($F9)),IF($D9="Fix",$G9,$G9*(1+$H9)^(2050-$E9)))))) | AP9: =IF($A9="","",IF(2051<$E9,"",IF($D9="Manuell","",IF(2051>$E9+$F9,IF($D9="Fix",$G9,$G9*(1+$H9)^($F9)),IF($D9="Fix",$G9,$G9*(1+$H9)^(2051-$E9)))))) | AQ9: =IF($A9="","",IF(2052<$E9,"",IF($D9="Manuell","",IF(2052>$E9+$F9,IF($D9="Fix",$G9,$G9*(1+$H9)^($F9)),IF($D9="Fix",$G9,$G9*(1+$H9)^(2052-$E9)))))) | AR9: =IF($A9="","",IF(2053<$E9,"",IF($D9="Manuell","",IF(2053>$E9+$F9,IF($D9="Fix",$G9,$G9*(1+$H9)^($F9)),IF($D9="Fix",$G9,$G9*(1+$H9)^(2053-$E9)))))) | AS9: =IF($A9="","",IF(2054<$E9,"",IF($D9="Manuell","",IF(2054>$E9+$F9,IF($D9="Fix",$G9,$G9*(1+$H9)^($F9)),IF($D9="Fix",$G9,$G9*(1+$H9)^(2054-$E9)))))) | AT9: =IF($A9="","",IF(2055<$E9,"",IF($D9="Manuell","",IF(2055>$E9+$F9,IF($D9="Fix",$G9,$G9*(1+$H9)^($F9)),IF($D9="Fix",$G9,$G9*(1+$H9)^(2055-$E9))))))
I10: =IF($A10="","",IF(2018<$E10,"",IF($D10="Manuell","",IF(2018>$E10+$F10,IF($D10="Fix",$G10,$G10*(1+$H10)^($F10)),IF($D10="Fix",$G10,$G10*(1+$H10)^(2018-$E10)))))) | J10: =IF($A10="","",IF(2019<$E10,"",IF($D10="Manuell","",IF(2019>$E10+$F10,IF($D10="Fix",$G10,$G10*(1+$H10)^($F10)),IF($D10="Fix",$G10,$G10*(1+$H10)^(2019-$E10)))))) | K10: =IF($A10="","",IF(2020<$E10,"",IF($D10="Manuell","",IF(2020>$E10+$F10,IF($D10="Fix",$G10,$G10*(1+$H10)^($F10)),IF($D10="Fix",$G10,$G10*(1+$H10)^(2020-$E10)))))) | L10: =IF($A10="","",IF(2021<$E10,"",IF($D10="Manuell","",IF(2021>$E10+$F10,IF($D10="Fix",$G10,$G10*(1+$H10)^($F10)),IF($D10="Fix",$G10,$G10*(1+$H10)^(2021-$E10)))))) | M10: =IF($A10="","",IF(2022<$E10,"",IF($D10="Manuell","",IF(2022>$E10+$F10,IF($D10="Fix",$G10,$G10*(1+$H10)^($F10)),IF($D10="Fix",$G10,$G10*(1+$H10)^(2022-$E10)))))) | N10: =IF($A10="","",IF(2023<$E10,"",IF($D10="Manuell","",IF(2023>$E10+$F10,IF($D10="Fix",$G10,$G10*(1+$H10)^($F10)),IF($D10="Fix",$G10,$G10*(1+$H10)^(2023-$E10)))))) | O10: =IF($A10="","",IF(2024<$E10,"",IF($D10="Manuell","",IF(2024>$E10+$F10,IF($D10="Fix",$G10,$G10*(1+$H10)^($F10)),IF($D10="Fix",$G10,$G10*(1+$H10)^(2024-$E10)))))) | P10: =IF($A10="","",IF(2025<$E10,"",IF($D10="Manuell","",IF(2025>$E10+$F10,IF($D10="Fix",$G10,$G10*(1+$H10)^($F10)),IF($D10="Fix",$G10,$G10*(1+$H10)^(2025-$E10)))))) | Q10: =IF($A10="","",IF(2026<$E10,"",IF($D10="Manuell","",IF(2026>$E10+$F10,IF($D10="Fix",$G10,$G10*(1+$H10)^($F10)),IF($D10="Fix",$G10,$G10*(1+$H10)^(2026-$E10)))))) | R10: =IF($A10="","",IF(2027<$E10,"",IF($D10="Manuell","",IF(2027>$E10+$F10,IF($D10="Fix",$G10,$G10*(1+$H10)^($F10)),IF($D10="Fix",$G10,$G10*(1+$H10)^(2027-$E10)))))) | S10: =IF($A10="","",IF(2028<$E10,"",IF($D10="Manuell","",IF(2028>$E10+$F10,IF($D10="Fix",$G10,$G10*(1+$H10)^($F10)),IF($D10="Fix",$G10,$G10*(1+$H10)^(2028-$E10)))))) | T10: =IF($A10="","",IF(2029<$E10,"",IF($D10="Manuell","",IF(2029>$E10+$F10,IF($D10="Fix",$G10,$G10*(1+$H10)^($F10)),IF($D10="Fix",$G10,$G10*(1+$H10)^(2029-$E10)))))) | U10: =IF($A10="","",IF(2030<$E10,"",IF($D10="Manuell","",IF(2030>$E10+$F10,IF($D10="Fix",$G10,$G10*(1+$H10)^($F10)),IF($D10="Fix",$G10,$G10*(1+$H10)^(2030-$E10)))))) | V10: =IF($A10="","",IF(2031<$E10,"",IF($D10="Manuell","",IF(2031>$E10+$F10,IF($D10="Fix",$G10,$G10*(1+$H10)^($F10)),IF($D10="Fix",$G10,$G10*(1+$H10)^(2031-$E10)))))) | W10: =IF($A10="","",IF(2032<$E10,"",IF($D10="Manuell","",IF(2032>$E10+$F10,IF($D10="Fix",$G10,$G10*(1+$H10)^($F10)),IF($D10="Fix",$G10,$G10*(1+$H10)^(2032-$E10)))))) | X10: =IF($A10="","",IF(2033<$E10,"",IF($D10="Manuell","",IF(2033>$E10+$F10,IF($D10="Fix",$G10,$G10*(1+$H10)^($F10)),IF($D10="Fix",$G10,$G10*(1+$H10)^(2033-$E10)))))) | Y10: =IF($A10="","",IF(2034<$E10,"",IF($D10="Manuell","",IF(2034>$E10+$F10,IF($D10="Fix",$G10,$G10*(1+$H10)^($F10)),IF($D10="Fix",$G10,$G10*(1+$H10)^(2034-$E10)))))) | Z10: =IF($A10="","",IF(2035<$E10,"",IF($D10="Manuell","",IF(2035>$E10+$F10,IF($D10="Fix",$G10,$G10*(1+$H10)^($F10)),IF($D10="Fix",$G10,$G10*(1+$H10)^(2035-$E10)))))) | AA10: =IF($A10="","",IF(2036<$E10,"",IF($D10="Manuell","",IF(2036>$E10+$F10,IF($D10="Fix",$G10,$G10*(1+$H10)^($F10)),IF($D10="Fix",$G10,$G10*(1+$H10)^(2036-$E10)))))) | AB10: =IF($A10="","",IF(2037<$E10,"",IF($D10="Manuell","",IF(2037>$E10+$F10,IF($D10="Fix",$G10,$G10*(1+$H10)^($F10)),IF($D10="Fix",$G10,$G10*(1+$H10)^(2037-$E10)))))) | AC10: =IF($A10="","",IF(2038<$E10,"",IF($D10="Manuell","",IF(2038>$E10+$F10,IF($D10="Fix",$G10,$G10*(1+$H10)^($F10)),IF($D10="Fix",$G10,$G10*(1+$H10)^(2038-$E10)))))) | AD10: =IF($A10="","",IF(2039<$E10,"",IF($D10="Manuell","",IF(2039>$E10+$F10,IF($D10="Fix",$G10,$G10*(1+$H10)^($F10)),IF($D10="Fix",$G10,$G10*(1+$H10)^(2039-$E10)))))) | AE10: =IF($A10="","",IF(2040<$E10,"",IF($D10="Manuell","",IF(2040>$E10+$F10,IF($D10="Fix",$G10,$G10*(1+$H10)^($F10)),IF($D10="Fix",$G10,$G10*(1+$H10)^(2040-$E10)))))) | AF10: =IF($A10="","",IF(2041<$E10,"",IF($D10="Manuell","",IF(2041>$E10+$F10,IF($D10="Fix",$G10,$G10*(1+$H10)^($F10)),IF($D10="Fix",$G10,$G10*(1+$H10)^(2041-$E10)))))) | AG10: =IF($A10="","",IF(2042<$E10,"",IF($D10="Manuell","",IF(2042>$E10+$F10,IF($D10="Fix",$G10,$G10*(1+$H10)^($F10)),IF($D10="Fix",$G10,$G10*(1+$H10)^(2042-$E10)))))) | AH10: =IF($A10="","",IF(2043<$E10,"",IF($D10="Manuell","",IF(2043>$E10+$F10,IF($D10="Fix",$G10,$G10*(1+$H10)^($F10)),IF($D10="Fix",$G10,$G10*(1+$H10)^(2043-$E10)))))) | AI10: =IF($A10="","",IF(2044<$E10,"",IF($D10="Manuell","",IF(2044>$E10+$F10,IF($D10="Fix",$G10,$G10*(1+$H10)^($F10)),IF($D10="Fix",$G10,$G10*(1+$H10)^(2044-$E10)))))) | AJ10: =IF($A10="","",IF(2045<$E10,"",IF($D10="Manuell","",IF(2045>$E10+$F10,IF($D10="Fix",$G10,$G10*(1+$H10)^($F10)),IF($D10="Fix",$G10,$G10*(1+$H10)^(2045-$E10)))))) | AK10: =IF($A10="","",IF(2046<$E10,"",IF($D10="Manuell","",IF(2046>$E10+$F10,IF($D10="Fix",$G10,$G10*(1+$H10)^($F10)),IF($D10="Fix",$G10,$G10*(1+$H10)^(2046-$E10)))))) | AL10: =IF($A10="","",IF(2047<$E10,"",IF($D10="Manuell","",IF(2047>$E10+$F10,IF($D10="Fix",$G10,$G10*(1+$H10)^($F10)),IF($D10="Fix",$G10,$G10*(1+$H10)^(2047-$E10)))))) | AM10: =IF($A10="","",IF(2048<$E10,"",IF($D10="Manuell","",IF(2048>$E10+$F10,IF($D10="Fix",$G10,$G10*(1+$H10)^($F10)),IF($D10="Fix",$G10,$G10*(1+$H10)^(2048-$E10)))))) | AN10: =IF($A10="","",IF(2049<$E10,"",IF($D10="Manuell","",IF(2049>$E10+$F10,IF($D10="Fix",$G10,$G10*(1+$H10)^($F10)),IF($D10="Fix",$G10,$G10*(1+$H10)^(2049-$E10)))))) | AO10: =IF($A10="","",IF(2050<$E10,"",IF($D10="Manuell","",IF(2050>$E10+$F10,IF($D10="Fix",$G10,$G10*(1+$H10)^($F10)),IF($D10="Fix",$G10,$G10*(1+$H10)^(2050-$E10)))))) | AP10: =IF($A10="","",IF(2051<$E10,"",IF($D10="Manuell","",IF(2051>$E10+$F10,IF($D10="Fix",$G10,$G10*(1+$H10)^($F10)),IF($D10="Fix",$G10,$G10*(1+$H10)^(2051-$E10)))))) | AQ10: =IF($A10="","",IF(2052<$E10,"",IF($D10="Manuell","",IF(2052>$E10+$F10,IF($D10="Fix",$G10,$G10*(1+$H10)^($F10)),IF($D10="Fix",$G10,$G10*(1+$H10)^(2052-$E10)))))) | AR10: =IF($A10="","",IF(2053<$E10,"",IF($D10="Manuell","",IF(2053>$E10+$F10,IF($D10="Fix",$G10,$G10*(1+$H10)^($F10)),IF($D10="Fix",$G10,$G10*(1+$H10)^(2053-$E10)))))) | AS10: =IF($A10="","",IF(2054<$E10,"",IF($D10="Manuell","",IF(2054>$E10+$F10,IF($D10="Fix",$G10,$G10*(1+$H10)^($F10)),IF($D10="Fix",$G10,$G10*(1+$H10)^(2054-$E10)))))) | AT10: =IF($A10="","",IF(2055<$E10,"",IF($D10="Manuell","",IF(2055>$E10+$F10,IF($D10="Fix",$G10,$G10*(1+$H10)^($F10)),IF($D10="Fix",$G10,$G10*(1+$H10)^(2055-$E10))))))
I11: =IF($A11="","",IF(2018<$E11,"",IF($D11="Manuell","",IF(2018>$E11+$F11,IF($D11="Fix",$G11,$G11*(1+$H11)^($F11)),IF($D11="Fix",$G11,$G11*(1+$H11)^(2018-$E11)))))) | J11: =IF($A11="","",IF(2019<$E11,"",IF($D11="Manuell","",IF(2019>$E11+$F11,IF($D11="Fix",$G11,$G11*(1+$H11)^($F11)),IF($D11="Fix",$G11,$G11*(1+$H11)^(2019-$E11)))))) | K11: =IF($A11="","",IF(2020<$E11,"",IF($D11="Manuell","",IF(2020>$E11+$F11,IF($D11="Fix",$G11,$G11*(1+$H11)^($F11)),IF($D11="Fix",$G11,$G11*(1+$H11)^(2020-$E11)))))) | L11: =IF($A11="","",IF(2021<$E11,"",IF($D11="Manuell","",IF(2021>$E11+$F11,IF($D11="Fix",$G11,$G11*(1+$H11)^($F11)),IF($D11="Fix",$G11,$G11*(1+$H11)^(2021-$E11)))))) | M11: =IF($A11="","",IF(2022<$E11,"",IF($D11="Manuell","",IF(2022>$E11+$F11,IF($D11="Fix",$G11,$G11*(1+$H11)^($F11)),IF($D11="Fix",$G11,$G11*(1+$H11)^(2022-$E11)))))) | N11: =IF($A11="","",IF(2023<$E11,"",IF($D11="Manuell","",IF(2023>$E11+$F11,IF($D11="Fix",$G11,$G11*(1+$H11)^($F11)),IF($D11="Fix",$G11,$G11*(1+$H11)^(2023-$E11)))))) | O11: =IF($A11="","",IF(2024<$E11,"",IF($D11="Manuell","",IF(2024>$E11+$F11,IF($D11="Fix",$G11,$G11*(1+$H11)^($F11)),IF($D11="Fix",$G11,$G11*(1+$H11)^(2024-$E11)))))) | P11: =IF($A11="","",IF(2025<$E11,"",IF($D11="Manuell","",IF(2025>$E11+$F11,IF($D11="Fix",$G11,$G11*(1+$H11)^($F11)),IF($D11="Fix",$G11,$G11*(1+$H11)^(2025-$E11)))))) | Q11: =IF($A11="","",IF(2026<$E11,"",IF($D11="Manuell","",IF(2026>$E11+$F11,IF($D11="Fix",$G11,$G11*(1+$H11)^($F11)),IF($D11="Fix",$G11,$G11*(1+$H11)^(2026-$E11)))))) | R11: =IF($A11="","",IF(2027<$E11,"",IF($D11="Manuell","",IF(2027>$E11+$F11,IF($D11="Fix",$G11,$G11*(1+$H11)^($F11)),IF($D11="Fix",$G11,$G11*(1+$H11)^(2027-$E11)))))) | S11: =IF($A11="","",IF(2028<$E11,"",IF($D11="Manuell","",IF(2028>$E11+$F11,IF($D11="Fix",$G11,$G11*(1+$H11)^($F11)),IF($D11="Fix",$G11,$G11*(1+$H11)^(2028-$E11)))))) | T11: =IF($A11="","",IF(2029<$E11,"",IF($D11="Manuell","",IF(2029>$E11+$F11,IF($D11="Fix",$G11,$G11*(1+$H11)^($F11)),IF($D11="Fix",$G11,$G11*(1+$H11)^(2029-$E11)))))) | U11: =IF($A11="","",IF(2030<$E11,"",IF($D11="Manuell","",IF(2030>$E11+$F11,IF($D11="Fix",$G11,$G11*(1+$H11)^($F11)),IF($D11="Fix",$G11,$G11*(1+$H11)^(2030-$E11)))))) | V11: =IF($A11="","",IF(2031<$E11,"",IF($D11="Manuell","",IF(2031>$E11+$F11,IF($D11="Fix",$G11,$G11*(1+$H11)^($F11)),IF($D11="Fix",$G11,$G11*(1+$H11)^(2031-$E11)))))) | W11: =IF($A11="","",IF(2032<$E11,"",IF($D11="Manuell","",IF(2032>$E11+$F11,IF($D11="Fix",$G11,$G11*(1+$H11)^($F11)),IF($D11="Fix",$G11,$G11*(1+$H11)^(2032-$E11)))))) | X11: =IF($A11="","",IF(2033<$E11,"",IF($D11="Manuell","",IF(2033>$E11+$F11,IF($D11="Fix",$G11,$G11*(1+$H11)^($F11)),IF($D11="Fix",$G11,$G11*(1+$H11)^(2033-$E11)))))) | Y11: =IF($A11="","",IF(2034<$E11,"",IF($D11="Manuell","",IF(2034>$E11+$F11,IF($D11="Fix",$G11,$G11*(1+$H11)^($F11)),IF($D11="Fix",$G11,$G11*(1+$H11)^(2034-$E11)))))) | Z11: =IF($A11="","",IF(2035<$E11,"",IF($D11="Manuell","",IF(2035>$E11+$F11,IF($D11="Fix",$G11,$G11*(1+$H11)^($F11)),IF($D11="Fix",$G11,$G11*(1+$H11)^(2035-$E11)))))) | AA11: =IF($A11="","",IF(2036<$E11,"",IF($D11="Manuell","",IF(2036>$E11+$F11,IF($D11="Fix",$G11,$G11*(1+$H11)^($F11)),IF($D11="Fix",$G11,$G11*(1+$H11)^(2036-$E11)))))) | AB11: =IF($A11="","",IF(2037<$E11,"",IF($D11="Manuell","",IF(2037>$E11+$F11,IF($D11="Fix",$G11,$G11*(1+$H11)^($F11)),IF($D11="Fix",$G11,$G11*(1+$H11)^(2037-$E11)))))) | AC11: =IF($A11="","",IF(2038<$E11,"",IF($D11="Manuell","",IF(2038>$E11+$F11,IF($D11="Fix",$G11,$G11*(1+$H11)^($F11)),IF($D11="Fix",$G11,$G11*(1+$H11)^(2038-$E11)))))) | AD11: =IF($A11="","",IF(2039<$E11,"",IF($D11="Manuell","",IF(2039>$E11+$F11,IF($D11="Fix",$G11,$G11*(1+$H11)^($F11)),IF($D11="Fix",$G11,$G11*(1+$H11)^(2039-$E11)))))) | AE11: =IF($A11="","",IF(2040<$E11,"",IF($D11="Manuell","",IF(2040>$E11+$F11,IF($D11="Fix",$G11,$G11*(1+$H11)^($F11)),IF($D11="Fix",$G11,$G11*(1+$H11)^(2040-$E11)))))) | AF11: =IF($A11="","",IF(2041<$E11,"",IF($D11="Manuell","",IF(2041>$E11+$F11,IF($D11="Fix",$G11,$G11*(1+$H11)^($F11)),IF($D11="Fix",$G11,$G11*(1+$H11)^(2041-$E11)))))) | AG11: =IF($A11="","",IF(2042<$E11,"",IF($D11="Manuell","",IF(2042>$E11+$F11,IF($D11="Fix",$G11,$G11*(1+$H11)^($F11)),IF($D11="Fix",$G11,$G11*(1+$H11)^(2042-$E11)))))) | AH11: =IF($A11="","",IF(2043<$E11,"",IF($D11="Manuell","",IF(2043>$E11+$F11,IF($D11="Fix",$G11,$G11*(1+$H11)^($F11)),IF($D11="Fix",$G11,$G11*(1+$H11)^(2043-$E11)))))) | AI11: =IF($A11="","",IF(2044<$E11,"",IF($D11="Manuell","",IF(2044>$E11+$F11,IF($D11="Fix",$G11,$G11*(1+$H11)^($F11)),IF($D11="Fix",$G11,$G11*(1+$H11)^(2044-$E11)))))) | AJ11: =IF($A11="","",IF(2045<$E11,"",IF($D11="Manuell","",IF(2045>$E11+$F11,IF($D11="Fix",$G11,$G11*(1+$H11)^($F11)),IF($D11="Fix",$G11,$G11*(1+$H11)^(2045-$E11)))))) | AK11: =IF($A11="","",IF(2046<$E11,"",IF($D11="Manuell","",IF(2046>$E11+$F11,IF($D11="Fix",$G11,$G11*(1+$H11)^($F11)),IF($D11="Fix",$G11,$G11*(1+$H11)^(2046-$E11)))))) | AL11: =IF($A11="","",IF(2047<$E11,"",IF($D11="Manuell","",IF(2047>$E11+$F11,IF($D11="Fix",$G11,$G11*(1+$H11)^($F11)),IF($D11="Fix",$G11,$G11*(1+$H11)^(2047-$E11)))))) | AM11: =IF($A11="","",IF(2048<$E11,"",IF($D11="Manuell","",IF(2048>$E11+$F11,IF($D11="Fix",$G11,$G11*(1+$H11)^($F11)),IF($D11="Fix",$G11,$G11*(1+$H11)^(2048-$E11)))))) | AN11: =IF($A11="","",IF(2049<$E11,"",IF($D11="Manuell","",IF(2049>$E11+$F11,IF($D11="Fix",$G11,$G11*(1+$H11)^($F11)),IF($D11="Fix",$G11,$G11*(1+$H11)^(2049-$E11)))))) | AO11: =IF($A11="","",IF(2050<$E11,"",IF($D11="Manuell","",IF(2050>$E11+$F11,IF($D11="Fix",$G11,$G11*(1+$H11)^($F11)),IF($D11="Fix",$G11,$G11*(1+$H11)^(2050-$E11)))))) | AP11: =IF($A11="","",IF(2051<$E11,"",IF($D11="Manuell","",IF(2051>$E11+$F11,IF($D11="Fix",$G11,$G11*(1+$H11)^($F11)),IF($D11="Fix",$G11,$G11*(1+$H11)^(2051-$E11)))))) | AQ11: =IF($A11="","",IF(2052<$E11,"",IF($D11="Manuell","",IF(2052>$E11+$F11,IF($D11="Fix",$G11,$G11*(1+$H11)^($F11)),IF($D11="Fix",$G11,$G11*(1+$H11)^(2052-$E11)))))) | AR11: =IF($A11="","",IF(2053<$E11,"",IF($D11="Manuell","",IF(2053>$E11+$F11,IF($D11="Fix",$G11,$G11*(1+$H11)^($F11)),IF($D11="Fix",$G11,$G11*(1+$H11)^(2053-$E11)))))) | AS11: =IF($A11="","",IF(2054<$E11,"",IF($D11="Manuell","",IF(2054>$E11+$F11,IF($D11="Fix",$G11,$G11*(1+$H11)^($F11)),IF($D11="Fix",$G11,$G11*(1+$H11)^(2054-$E11)))))) | AT11: =IF($A11="","",IF(2055<$E11,"",IF($D11="Manuell","",IF(2055>$E11+$F11,IF($D11="Fix",$G11,$G11*(1+$H11)^($F11)),IF($D11="Fix",$G11,$G11*(1+$H11)^(2055-$E11))))))
I12: =IF($A12="","",IF(2018<$E12,"",IF($D12="Manuell","",IF(2018>$E12+$F12,IF($D12="Fix",$G12,$G12*(1+$H12)^($F12)),IF($D12="Fix",$G12,$G12*(1+$H12)^(2018-$E12)))))) | J12: =IF($A12="","",IF(2019<$E12,"",IF($D12="Manuell","",IF(2019>$E12+$F12,IF($D12="Fix",$G12,$G12*(1+$H12)^($F12)),IF($D12="Fix",$G12,$G12*(1+$H12)^(2019-$E12)))))) | K12: =IF($A12="","",IF(2020<$E12,"",IF($D12="Manuell","",IF(2020>$E12+$F12,IF($D12="Fix",$G12,$G12*(1+$H12)^($F12)),IF($D12="Fix",$G12,$G12*(1+$H12)^(2020-$E12)))))) | L12: =IF($A12="","",IF(2021<$E12,"",IF($D12="Manuell","",IF(2021>$E12+$F12,IF($D12="Fix",$G12,$G12*(1+$H12)^($F12)),IF($D12="Fix",$G12,$G12*(1+$H12)^(2021-$E12)))))) | M12: =IF($A12="","",IF(2022<$E12,"",IF($D12="Manuell","",IF(2022>$E12+$F12,IF($D12="Fix",$G12,$G12*(1+$H12)^($F12)),IF($D12="Fix",$G12,$G12*(1+$H12)^(2022-$E12)))))) | N12: =IF($A12="","",IF(2023<$E12,"",IF($D12="Manuell","",IF(2023>$E12+$F12,IF($D12="Fix",$G12,$G12*(1+$H12)^($F12)),IF($D12="Fix",$G12,$G12*(1+$H12)^(2023-$E12)))))) | O12: =IF($A12="","",IF(2024<$E12,"",IF($D12="Manuell","",IF(2024>$E12+$F12,IF($D12="Fix",$G12,$G12*(1+$H12)^($F12)),IF($D12="Fix",$G12,$G12*(1+$H12)^(2024-$E12)))))) | P12: =IF($A12="","",IF(2025<$E12,"",IF($D12="Manuell","",IF(2025>$E12+$F12,IF($D12="Fix",$G12,$G12*(1+$H12)^($F12)),IF($D12="Fix",$G12,$G12*(1+$H12)^(2025-$E12)))))) | Q12: =IF($A12="","",IF(2026<$E12,"",IF($D12="Manuell","",IF(2026>$E12+$F12,IF($D12="Fix",$G12,$G12*(1+$H12)^($F12)),IF($D12="Fix",$G12,$G12*(1+$H12)^(2026-$E12)))))) | R12: =IF($A12="","",IF(2027<$E12,"",IF($D12="Manuell","",IF(2027>$E12+$F12,IF($D12="Fix",$G12,$G12*(1+$H12)^($F12)),IF($D12="Fix",$G12,$G12*(1+$H12)^(2027-$E12)))))) | S12: =IF($A12="","",IF(2028<$E12,"",IF($D12="Manuell","",IF(2028>$E12+$F12,IF($D12="Fix",$G12,$G12*(1+$H12)^($F12)),IF($D12="Fix",$G12,$G12*(1+$H12)^(2028-$E12)))))) | T12: =IF($A12="","",IF(2029<$E12,"",IF($D12="Manuell","",IF(2029>$E12+$F12,IF($D12="Fix",$G12,$G12*(1+$H12)^($F12)),IF($D12="Fix",$G12,$G12*(1+$H12)^(2029-$E12)))))) | U12: =IF($A12="","",IF(2030<$E12,"",IF($D12="Manuell","",IF(2030>$E12+$F12,IF($D12="Fix",$G12,$G12*(1+$H12)^($F12)),IF($D12="Fix",$G12,$G12*(1+$H12)^(2030-$E12)))))) | V12: =IF($A12="","",IF(2031<$E12,"",IF($D12="Manuell","",IF(2031>$E12+$F12,IF($D12="Fix",$G12,$G12*(1+$H12)^($F12)),IF($D12="Fix",$G12,$G12*(1+$H12)^(2031-$E12)))))) | W12: =IF($A12="","",IF(2032<$E12,"",IF($D12="Manuell","",IF(2032>$E12+$F12,IF($D12="Fix",$G12,$G12*(1+$H12)^($F12)),IF($D12="Fix",$G12,$G12*(1+$H12)^(2032-$E12)))))) | X12: =IF($A12="","",IF(2033<$E12,"",IF($D12="Manuell","",IF(2033>$E12+$F12,IF($D12="Fix",$G12,$G12*(1+$H12)^($F12)),IF($D12="Fix",$G12,$G12*(1+$H12)^(2033-$E12)))))) | Y12: =IF($A12="","",IF(2034<$E12,"",IF($D12="Manuell","",IF(2034>$E12+$F12,IF($D12="Fix",$G12,$G12*(1+$H12)^($F12)),IF($D12="Fix",$G12,$G12*(1+$H12)^(2034-$E12)))))) | Z12: =IF($A12="","",IF(2035<$E12,"",IF($D12="Manuell","",IF(2035>$E12+$F12,IF($D12="Fix",$G12,$G12*(1+$H12)^($F12)),IF($D12="Fix",$G12,$G12*(1+$H12)^(2035-$E12)))))) | AA12: =IF($A12="","",IF(2036<$E12,"",IF($D12="Manuell","",IF(2036>$E12+$F12,IF($D12="Fix",$G12,$G12*(1+$H12)^($F12)),IF($D12="Fix",$G12,$G12*(1+$H12)^(2036-$E12)))))) | AB12: =IF($A12="","",IF(2037<$E12,"",IF($D12="Manuell","",IF(2037>$E12+$F12,IF($D12="Fix",$G12,$G12*(1+$H12)^($F12)),IF($D12="Fix",$G12,$G12*(1+$H12)^(2037-$E12)))))) | AC12: =IF($A12="","",IF(2038<$E12,"",IF($D12="Manuell","",IF(2038>$E12+$F12,IF($D12="Fix",$G12,$G12*(1+$H12)^($F12)),IF($D12="Fix",$G12,$G12*(1+$H12)^(2038-$E12)))))) | AD12: =IF($A12="","",IF(2039<$E12,"",IF($D12="Manuell","",IF(2039>$E12+$F12,IF($D12="Fix",$G12,$G12*(1+$H12)^($F12)),IF($D12="Fix",$G12,$G12*(1+$H12)^(2039-$E12)))))) | AE12: =IF($A12="","",IF(2040<$E12,"",IF($D12="Manuell","",IF(2040>$E12+$F12,IF($D12="Fix",$G12,$G12*(1+$H12)^($F12)),IF($D12="Fix",$G12,$G12*(1+$H12)^(2040-$E12)))))) | AF12: =IF($A12="","",IF(2041<$E12,"",IF($D12="Manuell","",IF(2041>$E12+$F12,IF($D12="Fix",$G12,$G12*(1+$H12)^($F12)),IF($D12="Fix",$G12,$G12*(1+$H12)^(2041-$E12)))))) | AG12: =IF($A12="","",IF(2042<$E12,"",IF($D12="Manuell","",IF(2042>$E12+$F12,IF($D12="Fix",$G12,$G12*(1+$H12)^($F12)),IF($D12="Fix",$G12,$G12*(1+$H12)^(2042-$E12)))))) | AH12: =IF($A12="","",IF(2043<$E12,"",IF($D12="Manuell","",IF(2043>$E12+$F12,IF($D12="Fix",$G12,$G12*(1+$H12)^($F12)),IF($D12="Fix",$G12,$G12*(1+$H12)^(2043-$E12)))))) | AI12: =IF($A12="","",IF(2044<$E12,"",IF($D12="Manuell","",IF(2044>$E12+$F12,IF($D12="Fix",$G12,$G12*(1+$H12)^($F12)),IF($D12="Fix",$G12,$G12*(1+$H12)^(2044-$E12)))))) | AJ12: =IF($A12="","",IF(2045<$E12,"",IF($D12="Manuell","",IF(2045>$E12+$F12,IF($D12="Fix",$G12,$G12*(1+$H12)^($F12)),IF($D12="Fix",$G12,$G12*(1+$H12)^(2045-$E12)))))) | AK12: =IF($A12="","",IF(2046<$E12,"",IF($D12="Manuell","",IF(2046>$E12+$F12,IF($D12="Fix",$G12,$G12*(1+$H12)^($F12)),IF($D12="Fix",$G12,$G12*(1+$H12)^(2046-$E12)))))) | AL12: =IF($A12="","",IF(2047<$E12,"",IF($D12="Manuell","",IF(2047>$E12+$F12,IF($D12="Fix",$G12,$G12*(1+$H12)^($F12)),IF($D12="Fix",$G12,$G12*(1+$H12)^(2047-$E12)))))) | AM12: =IF($A12="","",IF(2048<$E12,"",IF($D12="Manuell","",IF(2048>$E12+$F12,IF($D12="Fix",$G12,$G12*(1+$H12)^($F12)),IF($D12="Fix",$G12,$G12*(1+$H12)^(2048-$E12)))))) | AN12: =IF($A12="","",IF(2049<$E12,"",IF($D12="Manuell","",IF(2049>$E12+$F12,IF($D12="Fix",$G12,$G12*(1+$H12)^($F12)),IF($D12="Fix",$G12,$G12*(1+$H12)^(2049-$E12)))))) | AO12: =IF($A12="","",IF(2050<$E12,"",IF($D12="Manuell","",IF(2050>$E12+$F12,IF($D12="Fix",$G12,$G12*(1+$H12)^($F12)),IF($D12="Fix",$G12,$G12*(1+$H12)^(2050-$E12)))))) | AP12: =IF($A12="","",IF(2051<$E12,"",IF($D12="Manuell","",IF(2051>$E12+$F12,IF($D12="Fix",$G12,$G12*(1+$H12)^($F12)),IF($D12="Fix",$G12,$G12*(1+$H12)^(2051-$E12)))))) | AQ12: =IF($A12="","",IF(2052<$E12,"",IF($D12="Manuell","",IF(2052>$E12+$F12,IF($D12="Fix",$G12,$G12*(1+$H12)^($F12)),IF($D12="Fix",$G12,$G12*(1+$H12)^(2052-$E12)))))) | AR12: =IF($A12="","",IF(2053<$E12,"",IF($D12="Manuell","",IF(2053>$E12+$F12,IF($D12="Fix",$G12,$G12*(1+$H12)^($F12)),IF($D12="Fix",$G12,$G12*(1+$H12)^(2053-$E12)))))) | AS12: =IF($A12="","",IF(2054<$E12,"",IF($D12="Manuell","",IF(2054>$E12+$F12,IF($D12="Fix",$G12,$G12*(1+$H12)^($F12)),IF($D12="Fix",$G12,$G12*(1+$H12)^(2054-$E12)))))) | AT12: =IF($A12="","",IF(2055<$E12,"",IF($D12="Manuell","",IF(2055>$E12+$F12,IF($D12="Fix",$G12,$G12*(1+$H12)^($F12)),IF($D12="Fix",$G12,$G12*(1+$H12)^(2055-$E12))))))
I13: =IF($A13="","",IF(2018<$E13,"",IF($D13="Manuell","",IF(2018>$E13+$F13,IF($D13="Fix",$G13,$G13*(1+$H13)^($F13)),IF($D13="Fix",$G13,$G13*(1+$H13)^(2018-$E13)))))) | J13: =IF($A13="","",IF(2019<$E13,"",IF($D13="Manuell","",IF(2019>$E13+$F13,IF($D13="Fix",$G13,$G13*(1+$H13)^($F13)),IF($D13="Fix",$G13,$G13*(1+$H13)^(2019-$E13)))))) | K13: =IF($A13="","",IF(2020<$E13,"",IF($D13="Manuell","",IF(2020>$E13+$F13,IF($D13="Fix",$G13,$G13*(1+$H13)^($F13)),IF($D13="Fix",$G13,$G13*(1+$H13)^(2020-$E13)))))) | L13: =IF($A13="","",IF(2021<$E13,"",IF($D13="Manuell","",IF(2021>$E13+$F13,IF($D13="Fix",$G13,$G13*(1+$H13)^($F13)),IF($D13="Fix",$G13,$G13*(1+$H13)^(2021-$E13)))))) | M13: =IF($A13="","",IF(2022<$E13,"",IF($D13="Manuell","",IF(2022>$E13+$F13,IF($D13="Fix",$G13,$G13*(1+$H13)^($F13)),IF($D13="Fix",$G13,$G13*(1+$H13)^(2022-$E13)))))) | N13: =IF($A13="","",IF(2023<$E13,"",IF($D13="Manuell","",IF(2023>$E13+$F13,IF($D13="Fix",$G13,$G13*(1+$H13)^($F13)),IF($D13="Fix",$G13,$G13*(1+$H13)^(2023-$E13)))))) | O13: =IF($A13="","",IF(2024<$E13,"",IF($D13="Manuell","",IF(2024>$E13+$F13,IF($D13="Fix",$G13,$G13*(1+$H13)^($F13)),IF($D13="Fix",$G13,$G13*(1+$H13)^(2024-$E13)))))) | P13: =IF($A13="","",IF(2025<$E13,"",IF($D13="Manuell","",IF(2025>$E13+$F13,IF($D13="Fix",$G13,$G13*(1+$H13)^($F13)),IF($D13="Fix",$G13,$G13*(1+$H13)^(2025-$E13)))))) | Q13: =IF($A13="","",IF(2026<$E13,"",IF($D13="Manuell","",IF(2026>$E13+$F13,IF($D13="Fix",$G13,$G13*(1+$H13)^($F13)),IF($D13="Fix",$G13,$G13*(1+$H13)^(2026-$E13)))))) | R13: =IF($A13="","",IF(2027<$E13,"",IF($D13="Manuell","",IF(2027>$E13+$F13,IF($D13="Fix",$G13,$G13*(1+$H13)^($F13)),IF($D13="Fix",$G13,$G13*(1+$H13)^(2027-$E13)))))) | S13: =IF($A13="","",IF(2028<$E13,"",IF($D13="Manuell","",IF(2028>$E13+$F13,IF($D13="Fix",$G13,$G13*(1+$H13)^($F13)),IF($D13="Fix",$G13,$G13*(1+$H13)^(2028-$E13)))))) | T13: =IF($A13="","",IF(2029<$E13,"",IF($D13="Manuell","",IF(2029>$E13+$F13,IF($D13="Fix",$G13,$G13*(1+$H13)^($F13)),IF($D13="Fix",$G13,$G13*(1+$H13)^(2029-$E13)))))) | U13: =IF($A13="","",IF(2030<$E13,"",IF($D13="Manuell","",IF(2030>$E13+$F13,IF($D13="Fix",$G13,$G13*(1+$H13)^($F13)),IF($D13="Fix",$G13,$G13*(1+$H13)^(2030-$E13)))))) | V13: =IF($A13="","",IF(2031<$E13,"",IF($D13="Manuell","",IF(2031>$E13+$F13,IF($D13="Fix",$G13,$G13*(1+$H13)^($F13)),IF($D13="Fix",$G13,$G13*(1+$H13)^(2031-$E13)))))) | W13: =IF($A13="","",IF(2032<$E13,"",IF($D13="Manuell","",IF(2032>$E13+$F13,IF($D13="Fix",$G13,$G13*(1+$H13)^($F13)),IF($D13="Fix",$G13,$G13*(1+$H13)^(2032-$E13)))))) | X13: =IF($A13="","",IF(2033<$E13,"",IF($D13="Manuell","",IF(2033>$E13+$F13,IF($D13="Fix",$G13,$G13*(1+$H13)^($F13)),IF($D13="Fix",$G13,$G13*(1+$H13)^(2033-$E13)))))) | Y13: =IF($A13="","",IF(2034<$E13,"",IF($D13="Manuell","",IF(2034>$E13+$F13,IF($D13="Fix",$G13,$G13*(1+$H13)^($F13)),IF($D13="Fix",$G13,$G13*(1+$H13)^(2034-$E13)))))) | Z13: =IF($A13="","",IF(2035<$E13,"",IF($D13="Manuell","",IF(2035>$E13+$F13,IF($D13="Fix",$G13,$G13*(1+$H13)^($F13)),IF($D13="Fix",$G13,$G13*(1+$H13)^(2035-$E13)))))) | AA13: =IF($A13="","",IF(2036<$E13,"",IF($D13="Manuell","",IF(2036>$E13+$F13,IF($D13="Fix",$G13,$G13*(1+$H13)^($F13)),IF($D13="Fix",$G13,$G13*(1+$H13)^(2036-$E13)))))) | AB13: =IF($A13="","",IF(2037<$E13,"",IF($D13="Manuell","",IF(2037>$E13+$F13,IF($D13="Fix",$G13,$G13*(1+$H13)^($F13)),IF($D13="Fix",$G13,$G13*(1+$H13)^(2037-$E13)))))) | AC13: =IF($A13="","",IF(2038<$E13,"",IF($D13="Manuell","",IF(2038>$E13+$F13,IF($D13="Fix",$G13,$G13*(1+$H13)^($F13)),IF($D13="Fix",$G13,$G13*(1+$H13)^(2038-$E13)))))) | AD13: =IF($A13="","",IF(2039<$E13,"",IF($D13="Manuell","",IF(2039>$E13+$F13,IF($D13="Fix",$G13,$G13*(1+$H13)^($F13)),IF($D13="Fix",$G13,$G13*(1+$H13)^(2039-$E13)))))) | AE13: =IF($A13="","",IF(2040<$E13,"",IF($D13="Manuell","",IF(2040>$E13+$F13,IF($D13="Fix",$G13,$G13*(1+$H13)^($F13)),IF($D13="Fix",$G13,$G13*(1+$H13)^(2040-$E13)))))) | AF13: =IF($A13="","",IF(2041<$E13,"",IF($D13="Manuell","",IF(2041>$E13+$F13,IF($D13="Fix",$G13,$G13*(1+$H13)^($F13)),IF($D13="Fix",$G13,$G13*(1+$H13)^(2041-$E13)))))) | AG13: =IF($A13="","",IF(2042<$E13,"",IF($D13="Manuell","",IF(2042>$E13+$F13,IF($D13="Fix",$G13,$G13*(1+$H13)^($F13)),IF($D13="Fix",$G13,$G13*(1+$H13)^(2042-$E13)))))) | AH13: =IF($A13="","",IF(2043<$E13,"",IF($D13="Manuell","",IF(2043>$E13+$F13,IF($D13="Fix",$G13,$G13*(1+$H13)^($F13)),IF($D13="Fix",$G13,$G13*(1+$H13)^(2043-$E13)))))) | AI13: =IF($A13="","",IF(2044<$E13,"",IF($D13="Manuell","",IF(2044>$E13+$F13,IF($D13="Fix",$G13,$G13*(1+$H13)^($F13)),IF($D13="Fix",$G13,$G13*(1+$H13)^(2044-$E13)))))) | AJ13: =IF($A13="","",IF(2045<$E13,"",IF($D13="Manuell","",IF(2045>$E13+$F13,IF($D13="Fix",$G13,$G13*(1+$H13)^($F13)),IF($D13="Fix",$G13,$G13*(1+$H13)^(2045-$E13)))))) | AK13: =IF($A13="","",IF(2046<$E13,"",IF($D13="Manuell","",IF(2046>$E13+$F13,IF($D13="Fix",$G13,$G13*(1+$H13)^($F13)),IF($D13="Fix",$G13,$G13*(1+$H13)^(2046-$E13)))))) | AL13: =IF($A13="","",IF(2047<$E13,"",IF($D13="Manuell","",IF(2047>$E13+$F13,IF($D13="Fix",$G13,$G13*(1+$H13)^($F13)),IF($D13="Fix",$G13,$G13*(1+$H13)^(2047-$E13)))))) | AM13: =IF($A13="","",IF(2048<$E13,"",IF($D13="Manuell","",IF(2048>$E13+$F13,IF($D13="Fix",$G13,$G13*(1+$H13)^($F13)),IF($D13="Fix",$G13,$G13*(1+$H13)^(2048-$E13)))))) | AN13: =IF($A13="","",IF(2049<$E13,"",IF($D13="Manuell","",IF(2049>$E13+$F13,IF($D13="Fix",$G13,$G13*(1+$H13)^($F13)),IF($D13="Fix",$G13,$G13*(1+$H13)^(2049-$E13)))))) | AO13: =IF($A13="","",IF(2050<$E13,"",IF($D13="Manuell","",IF(2050>$E13+$F13,IF($D13="Fix",$G13,$G13*(1+$H13)^($F13)),IF($D13="Fix",$G13,$G13*(1+$H13)^(2050-$E13)))))) | AP13: =IF($A13="","",IF(2051<$E13,"",IF($D13="Manuell","",IF(2051>$E13+$F13,IF($D13="Fix",$G13,$G13*(1+$H13)^($F13)),IF($D13="Fix",$G13,$G13*(1+$H13)^(2051-$E13)))))) | AQ13: =IF($A13="","",IF(2052<$E13,"",IF($D13="Manuell","",IF(2052>$E13+$F13,IF($D13="Fix",$G13,$G13*(1+$H13)^($F13)),IF($D13="Fix",$G13,$G13*(1+$H13)^(2052-$E13)))))) | AR13: =IF($A13="","",IF(2053<$E13,"",IF($D13="Manuell","",IF(2053>$E13+$F13,IF($D13="Fix",$G13,$G13*(1+$H13)^($F13)),IF($D13="Fix",$G13,$G13*(1+$H13)^(2053-$E13)))))) | AS13: =IF($A13="","",IF(2054<$E13,"",IF($D13="Manuell","",IF(2054>$E13+$F13,IF($D13="Fix",$G13,$G13*(1+$H13)^($F13)),IF($D13="Fix",$G13,$G13*(1+$H13)^(2054-$E13)))))) | AT13: =IF($A13="","",IF(2055<$E13,"",IF($D13="Manuell","",IF(2055>$E13+$F13,IF($D13="Fix",$G13,$G13*(1+$H13)^($F13)),IF($D13="Fix",$G13,$G13*(1+$H13)^(2055-$E13))))))
I14: =IF($A14="","",IF(2018<$E14,"",IF($D14="Manuell","",IF(2018>$E14+$F14,IF($D14="Fix",$G14,$G14*(1+$H14)^($F14)),IF($D14="Fix",$G14,$G14*(1+$H14)^(2018-$E14)))))) | J14: =IF($A14="","",IF(2019<$E14,"",IF($D14="Manuell","",IF(2019>$E14+$F14,IF($D14="Fix",$G14,$G14*(1+$H14)^($F14)),IF($D14="Fix",$G14,$G14*(1+$H14)^(2019-$E14)))))) | K14: =IF($A14="","",IF(2020<$E14,"",IF($D14="Manuell","",IF(2020>$E14+$F14,IF($D14="Fix",$G14,$G14*(1+$H14)^($F14)),IF($D14="Fix",$G14,$G14*(1+$H14)^(2020-$E14)))))) | L14: =IF($A14="","",IF(2021<$E14,"",IF($D14="Manuell","",IF(2021>$E14+$F14,IF($D14="Fix",$G14,$G14*(1+$H14)^($F14)),IF($D14="Fix",$G14,$G14*(1+$H14)^(2021-$E14)))))) | M14: =IF($A14="","",IF(2022<$E14,"",IF($D14="Manuell","",IF(2022>$E14+$F14,IF($D14="Fix",$G14,$G14*(1+$H14)^($F14)),IF($D14="Fix",$G14,$G14*(1+$H14)^(2022-$E14)))))) | N14: =IF($A14="","",IF(2023<$E14,"",IF($D14="Manuell","",IF(2023>$E14+$F14,IF($D14="Fix",$G14,$G14*(1+$H14)^($F14)),IF($D14="Fix",$G14,$G14*(1+$H14)^(2023-$E14)))))) | O14: =IF($A14="","",IF(2024<$E14,"",IF($D14="Manuell","",IF(2024>$E14+$F14,IF($D14="Fix",$G14,$G14*(1+$H14)^($F14)),IF($D14="Fix",$G14,$G14*(1+$H14)^(2024-$E14)))))) | P14: =IF($A14="","",IF(2025<$E14,"",IF($D14="Manuell","",IF(2025>$E14+$F14,IF($D14="Fix",$G14,$G14*(1+$H14)^($F14)),IF($D14="Fix",$G14,$G14*(1+$H14)^(2025-$E14)))))) | Q14: =IF($A14="","",IF(2026<$E14,"",IF($D14="Manuell","",IF(2026>$E14+$F14,IF($D14="Fix",$G14,$G14*(1+$H14)^($F14)),IF($D14="Fix",$G14,$G14*(1+$H14)^(2026-$E14)))))) | R14: =IF($A14="","",IF(2027<$E14,"",IF($D14="Manuell","",IF(2027>$E14+$F14,IF($D14="Fix",$G14,$G14*(1+$H14)^($F14)),IF($D14="Fix",$G14,$G14*(1+$H14)^(2027-$E14)))))) | S14: =IF($A14="","",IF(2028<$E14,"",IF($D14="Manuell","",IF(2028>$E14+$F14,IF($D14="Fix",$G14,$G14*(1+$H14)^($F14)),IF($D14="Fix",$G14,$G14*(1+$H14)^(2028-$E14)))))) | T14: =IF($A14="","",IF(2029<$E14,"",IF($D14="Manuell","",IF(2029>$E14+$F14,IF($D14="Fix",$G14,$G14*(1+$H14)^($F14)),IF($D14="Fix",$G14,$G14*(1+$H14)^(2029-$E14)))))) | U14: =IF($A14="","",IF(2030<$E14,"",IF($D14="Manuell","",IF(2030>$E14+$F14,IF($D14="Fix",$G14,$G14*(1+$H14)^($F14)),IF($D14="Fix",$G14,$G14*(1+$H14)^(2030-$E14)))))) | V14: =IF($A14="","",IF(2031<$E14,"",IF($D14="Manuell","",IF(2031>$E14+$F14,IF($D14="Fix",$G14,$G14*(1+$H14)^($F14)),IF($D14="Fix",$G14,$G14*(1+$H14)^(2031-$E14)))))) | W14: =IF($A14="","",IF(2032<$E14,"",IF($D14="Manuell","",IF(2032>$E14+$F14,IF($D14="Fix",$G14,$G14*(1+$H14)^($F14)),IF($D14="Fix",$G14,$G14*(1+$H14)^(2032-$E14)))))) | X14: =IF($A14="","",IF(2033<$E14,"",IF($D14="Manuell","",IF(2033>$E14+$F14,IF($D14="Fix",$G14,$G14*(1+$H14)^($F14)),IF($D14="Fix",$G14,$G14*(1+$H14)^(2033-$E14)))))) | Y14: =IF($A14="","",IF(2034<$E14,"",IF($D14="Manuell","",IF(2034>$E14+$F14,IF($D14="Fix",$G14,$G14*(1+$H14)^($F14)),IF($D14="Fix",$G14,$G14*(1+$H14)^(2034-$E14)))))) | Z14: =IF($A14="","",IF(2035<$E14,"",IF($D14="Manuell","",IF(2035>$E14+$F14,IF($D14="Fix",$G14,$G14*(1+$H14)^($F14)),IF($D14="Fix",$G14,$G14*(1+$H14)^(2035-$E14)))))) | AA14: =IF($A14="","",IF(2036<$E14,"",IF($D14="Manuell","",IF(2036>$E14+$F14,IF($D14="Fix",$G14,$G14*(1+$H14)^($F14)),IF($D14="Fix",$G14,$G14*(1+$H14)^(2036-$E14)))))) | AB14: =IF($A14="","",IF(2037<$E14,"",IF($D14="Manuell","",IF(2037>$E14+$F14,IF($D14="Fix",$G14,$G14*(1+$H14)^($F14)),IF($D14="Fix",$G14,$G14*(1+$H14)^(2037-$E14)))))) | AC14: =IF($A14="","",IF(2038<$E14,"",IF($D14="Manuell","",IF(2038>$E14+$F14,IF($D14="Fix",$G14,$G14*(1+$H14)^($F14)),IF($D14="Fix",$G14,$G14*(1+$H14)^(2038-$E14)))))) | AD14: =IF($A14="","",IF(2039<$E14,"",IF($D14="Manuell","",IF(2039>$E14+$F14,IF($D14="Fix",$G14,$G14*(1+$H14)^($F14)),IF($D14="Fix",$G14,$G14*(1+$H14)^(2039-$E14)))))) | AE14: =IF($A14="","",IF(2040<$E14,"",IF($D14="Manuell","",IF(2040>$E14+$F14,IF($D14="Fix",$G14,$G14*(1+$H14)^($F14)),IF($D14="Fix",$G14,$G14*(1+$H14)^(2040-$E14)))))) | AF14: =IF($A14="","",IF(2041<$E14,"",IF($D14="Manuell","",IF(2041>$E14+$F14,IF($D14="Fix",$G14,$G14*(1+$H14)^($F14)),IF($D14="Fix",$G14,$G14*(1+$H14)^(2041-$E14)))))) | AG14: =IF($A14="","",IF(2042<$E14,"",IF($D14="Manuell","",IF(2042>$E14+$F14,IF($D14="Fix",$G14,$G14*(1+$H14)^($F14)),IF($D14="Fix",$G14,$G14*(1+$H14)^(2042-$E14)))))) | AH14: =IF($A14="","",IF(2043<$E14,"",IF($D14="Manuell","",IF(2043>$E14+$F14,IF($D14="Fix",$G14,$G14*(1+$H14)^($F14)),IF($D14="Fix",$G14,$G14*(1+$H14)^(2043-$E14)))))) | AI14: =IF($A14="","",IF(2044<$E14,"",IF($D14="Manuell","",IF(2044>$E14+$F14,IF($D14="Fix",$G14,$G14*(1+$H14)^($F14)),IF($D14="Fix",$G14,$G14*(1+$H14)^(2044-$E14)))))) | AJ14: =IF($A14="","",IF(2045<$E14,"",IF($D14="Manuell","",IF(2045>$E14+$F14,IF($D14="Fix",$G14,$G14*(1+$H14)^($F14)),IF($D14="Fix",$G14,$G14*(1+$H14)^(2045-$E14)))))) | AK14: =IF($A14="","",IF(2046<$E14,"",IF($D14="Manuell","",IF(2046>$E14+$F14,IF($D14="Fix",$G14,$G14*(1+$H14)^($F14)),IF($D14="Fix",$G14,$G14*(1+$H14)^(2046-$E14)))))) | AL14: =IF($A14="","",IF(2047<$E14,"",IF($D14="Manuell","",IF(2047>$E14+$F14,IF($D14="Fix",$G14,$G14*(1+$H14)^($F14)),IF($D14="Fix",$G14,$G14*(1+$H14)^(2047-$E14)))))) | AM14: =IF($A14="","",IF(2048<$E14,"",IF($D14="Manuell","",IF(2048>$E14+$F14,IF($D14="Fix",$G14,$G14*(1+$H14)^($F14)),IF($D14="Fix",$G14,$G14*(1+$H14)^(2048-$E14)))))) | AN14: =IF($A14="","",IF(2049<$E14,"",IF($D14="Manuell","",IF(2049>$E14+$F14,IF($D14="Fix",$G14,$G14*(1+$H14)^($F14)),IF($D14="Fix",$G14,$G14*(1+$H14)^(2049-$E14)))))) | AO14: =IF($A14="","",IF(2050<$E14,"",IF($D14="Manuell","",IF(2050>$E14+$F14,IF($D14="Fix",$G14,$G14*(1+$H14)^($F14)),IF($D14="Fix",$G14,$G14*(1+$H14)^(2050-$E14)))))) | AP14: =IF($A14="","",IF(2051<$E14,"",IF($D14="Manuell","",IF(2051>$E14+$F14,IF($D14="Fix",$G14,$G14*(1+$H14)^($F14)),IF($D14="Fix",$G14,$G14*(1+$H14)^(2051-$E14)))))) | AQ14: =IF($A14="","",IF(2052<$E14,"",IF($D14="Manuell","",IF(2052>$E14+$F14,IF($D14="Fix",$G14,$G14*(1+$H14)^($F14)),IF($D14="Fix",$G14,$G14*(1+$H14)^(2052-$E14)))))) | AR14: =IF($A14="","",IF(2053<$E14,"",IF($D14="Manuell","",IF(2053>$E14+$F14,IF($D14="Fix",$G14,$G14*(1+$H14)^($F14)),IF($D14="Fix",$G14,$G14*(1+$H14)^(2053-$E14)))))) | AS14: =IF($A14="","",IF(2054<$E14,"",IF($D14="Manuell","",IF(2054>$E14+$F14,IF($D14="Fix",$G14,$G14*(1+$H14)^($F14)),IF($D14="Fix",$G14,$G14*(1+$H14)^(2054-$E14)))))) | AT14: =IF($A14="","",IF(2055<$E14,"",IF($D14="Manuell","",IF(2055>$E14+$F14,IF($D14="Fix",$G14,$G14*(1+$H14)^($F14)),IF($D14="Fix",$G14,$G14*(1+$H14)^(2055-$E14))))))
I15: =IF($A15="","",IF(2018<$E15,"",IF($D15="Manuell","",IF(2018>$E15+$F15,IF($D15="Fix",$G15,$G15*(1+$H15)^($F15)),IF($D15="Fix",$G15,$G15*(1+$H15)^(2018-$E15)))))) | J15: =IF($A15="","",IF(2019<$E15,"",IF($D15="Manuell","",IF(2019>$E15+$F15,IF($D15="Fix",$G15,$G15*(1+$H15)^($F15)),IF($D15="Fix",$G15,$G15*(1+$H15)^(2019-$E15)))))) | K15: =IF($A15="","",IF(2020<$E15,"",IF($D15="Manuell","",IF(2020>$E15+$F15,IF($D15="Fix",$G15,$G15*(1+$H15)^($F15)),IF($D15="Fix",$G15,$G15*(1+$H15)^(2020-$E15)))))) | L15: =IF($A15="","",IF(2021<$E15,"",IF($D15="Manuell","",IF(2021>$E15+$F15,IF($D15="Fix",$G15,$G15*(1+$H15)^($F15)),IF($D15="Fix",$G15,$G15*(1+$H15)^(2021-$E15)))))) | M15: =IF($A15="","",IF(2022<$E15,"",IF($D15="Manuell","",IF(2022>$E15+$F15,IF($D15="Fix",$G15,$G15*(1+$H15)^($F15)),IF($D15="Fix",$G15,$G15*(1+$H15)^(2022-$E15)))))) | N15: =IF($A15="","",IF(2023<$E15,"",IF($D15="Manuell","",IF(2023>$E15+$F15,IF($D15="Fix",$G15,$G15*(1+$H15)^($F15)),IF($D15="Fix",$G15,$G15*(1+$H15)^(2023-$E15)))))) | O15: =IF($A15="","",IF(2024<$E15,"",IF($D15="Manuell","",IF(2024>$E15+$F15,IF($D15="Fix",$G15,$G15*(1+$H15)^($F15)),IF($D15="Fix",$G15,$G15*(1+$H15)^(2024-$E15)))))) | P15: =IF($A15="","",IF(2025<$E15,"",IF($D15="Manuell","",IF(2025>$E15+$F15,IF($D15="Fix",$G15,$G15*(1+$H15)^($F15)),IF($D15="Fix",$G15,$G15*(1+$H15)^(2025-$E15)))))) | Q15: =IF($A15="","",IF(2026<$E15,"",IF($D15="Manuell","",IF(2026>$E15+$F15,IF($D15="Fix",$G15,$G15*(1+$H15)^($F15)),IF($D15="Fix",$G15,$G15*(1+$H15)^(2026-$E15)))))) | R15: =IF($A15="","",IF(2027<$E15,"",IF($D15="Manuell","",IF(2027>$E15+$F15,IF($D15="Fix",$G15,$G15*(1+$H15)^($F15)),IF($D15="Fix",$G15,$G15*(1+$H15)^(2027-$E15)))))) | S15: =IF($A15="","",IF(2028<$E15,"",IF($D15="Manuell","",IF(2028>$E15+$F15,IF($D15="Fix",$G15,$G15*(1+$H15)^($F15)),IF($D15="Fix",$G15,$G15*(1+$H15)^(2028-$E15)))))) | T15: =IF($A15="","",IF(2029<$E15,"",IF($D15="Manuell","",IF(2029>$E15+$F15,IF($D15="Fix",$G15,$G15*(1+$H15)^($F15)),IF($D15="Fix",$G15,$G15*(1+$H15)^(2029-$E15)))))) | U15: =IF($A15="","",IF(2030<$E15,"",IF($D15="Manuell","",IF(2030>$E15+$F15,IF($D15="Fix",$G15,$G15*(1+$H15)^($F15)),IF($D15="Fix",$G15,$G15*(1+$H15)^(2030-$E15)))))) | V15: =IF($A15="","",IF(2031<$E15,"",IF($D15="Manuell","",IF(2031>$E15+$F15,IF($D15="Fix",$G15,$G15*(1+$H15)^($F15)),IF($D15="Fix",$G15,$G15*(1+$H15)^(2031-$E15)))))) | W15: =IF($A15="","",IF(2032<$E15,"",IF($D15="Manuell","",IF(2032>$E15+$F15,IF($D15="Fix",$G15,$G15*(1+$H15)^($F15)),IF($D15="Fix",$G15,$G15*(1+$H15)^(2032-$E15)))))) | X15: =IF($A15="","",IF(2033<$E15,"",IF($D15="Manuell","",IF(2033>$E15+$F15,IF($D15="Fix",$G15,$G15*(1+$H15)^($F15)),IF($D15="Fix",$G15,$G15*(1+$H15)^(2033-$E15)))))) | Y15: =IF($A15="","",IF(2034<$E15,"",IF($D15="Manuell","",IF(2034>$E15+$F15,IF($D15="Fix",$G15,$G15*(1+$H15)^($F15)),IF($D15="Fix",$G15,$G15*(1+$H15)^(2034-$E15)))))) | Z15: =IF($A15="","",IF(2035<$E15,"",IF($D15="Manuell","",IF(2035>$E15+$F15,IF($D15="Fix",$G15,$G15*(1+$H15)^($F15)),IF($D15="Fix",$G15,$G15*(1+$H15)^(2035-$E15)))))) | AA15: =IF($A15="","",IF(2036<$E15,"",IF($D15="Manuell","",IF(2036>$E15+$F15,IF($D15="Fix",$G15,$G15*(1+$H15)^($F15)),IF($D15="Fix",$G15,$G15*(1+$H15)^(2036-$E15)))))) | AB15: =IF($A15="","",IF(2037<$E15,"",IF($D15="Manuell","",IF(2037>$E15+$F15,IF($D15="Fix",$G15,$G15*(1+$H15)^($F15)),IF($D15="Fix",$G15,$G15*(1+$H15)^(2037-$E15)))))) | AC15: =IF($A15="","",IF(2038<$E15,"",IF($D15="Manuell","",IF(2038>$E15+$F15,IF($D15="Fix",$G15,$G15*(1+$H15)^($F15)),IF($D15="Fix",$G15,$G15*(1+$H15)^(2038-$E15)))))) | AD15: =IF($A15="","",IF(2039<$E15,"",IF($D15="Manuell","",IF(2039>$E15+$F15,IF($D15="Fix",$G15,$G15*(1+$H15)^($F15)),IF($D15="Fix",$G15,$G15*(1+$H15)^(2039-$E15)))))) | AE15: =IF($A15="","",IF(2040<$E15,"",IF($D15="Manuell","",IF(2040>$E15+$F15,IF($D15="Fix",$G15,$G15*(1+$H15)^($F15)),IF($D15="Fix",$G15,$G15*(1+$H15)^(2040-$E15)))))) | AF15: =IF($A15="","",IF(2041<$E15,"",IF($D15="Manuell","",IF(2041>$E15+$F15,IF($D15="Fix",$G15,$G15*(1+$H15)^($F15)),IF($D15="Fix",$G15,$G15*(1+$H15)^(2041-$E15)))))) | AG15: =IF($A15="","",IF(2042<$E15,"",IF($D15="Manuell","",IF(2042>$E15+$F15,IF($D15="Fix",$G15,$G15*(1+$H15)^($F15)),IF($D15="Fix",$G15,$G15*(1+$H15)^(2042-$E15)))))) | AH15: =IF($A15="","",IF(2043<$E15,"",IF($D15="Manuell","",IF(2043>$E15+$F15,IF($D15="Fix",$G15,$G15*(1+$H15)^($F15)),IF($D15="Fix",$G15,$G15*(1+$H15)^(2043-$E15)))))) | AI15: =IF($A15="","",IF(2044<$E15,"",IF($D15="Manuell","",IF(2044>$E15+$F15,IF($D15="Fix",$G15,$G15*(1+$H15)^($F15)),IF($D15="Fix",$G15,$G15*(1+$H15)^(2044-$E15)))))) | AJ15: =IF($A15="","",IF(2045<$E15,"",IF($D15="Manuell","",IF(2045>$E15+$F15,IF($D15="Fix",$G15,$G15*(1+$H15)^($F15)),IF($D15="Fix",$G15,$G15*(1+$H15)^(2045-$E15)))))) | AK15: =IF($A15="","",IF(2046<$E15,"",IF($D15="Manuell","",IF(2046>$E15+$F15,IF($D15="Fix",$G15,$G15*(1+$H15)^($F15)),IF($D15="Fix",$G15,$G15*(1+$H15)^(2046-$E15)))))) | AL15: =IF($A15="","",IF(2047<$E15,"",IF($D15="Manuell","",IF(2047>$E15+$F15,IF($D15="Fix",$G15,$G15*(1+$H15)^($F15)),IF($D15="Fix",$G15,$G15*(1+$H15)^(2047-$E15)))))) | AM15: =IF($A15="","",IF(2048<$E15,"",IF($D15="Manuell","",IF(2048>$E15+$F15,IF($D15="Fix",$G15,$G15*(1+$H15)^($F15)),IF($D15="Fix",$G15,$G15*(1+$H15)^(2048-$E15)))))) | AN15: =IF($A15="","",IF(2049<$E15,"",IF($D15="Manuell","",IF(2049>$E15+$F15,IF($D15="Fix",$G15,$G15*(1+$H15)^($F15)),IF($D15="Fix",$G15,$G15*(1+$H15)^(2049-$E15)))))) | AO15: =IF($A15="","",IF(2050<$E15,"",IF($D15="Manuell","",IF(2050>$E15+$F15,IF($D15="Fix",$G15,$G15*(1+$H15)^($F15)),IF($D15="Fix",$G15,$G15*(1+$H15)^(2050-$E15)))))) | AP15: =IF($A15="","",IF(2051<$E15,"",IF($D15="Manuell","",IF(2051>$E15+$F15,IF($D15="Fix",$G15,$G15*(1+$H15)^($F15)),IF($D15="Fix",$G15,$G15*(1+$H15)^(2051-$E15)))))) | AQ15: =IF($A15="","",IF(2052<$E15,"",IF($D15="Manuell","",IF(2052>$E15+$F15,IF($D15="Fix",$G15,$G15*(1+$H15)^($F15)),IF($D15="Fix",$G15,$G15*(1+$H15)^(2052-$E15)))))) | AR15: =IF($A15="","",IF(2053<$E15,"",IF($D15="Manuell","",IF(2053>$E15+$F15,IF($D15="Fix",$G15,$G15*(1+$H15)^($F15)),IF($D15="Fix",$G15,$G15*(1+$H15)^(2053-$E15)))))) | AS15: =IF($A15="","",IF(2054<$E15,"",IF($D15="Manuell","",IF(2054>$E15+$F15,IF($D15="Fix",$G15,$G15*(1+$H15)^($F15)),IF($D15="Fix",$G15,$G15*(1+$H15)^(2054-$E15)))))) | AT15: =IF($A15="","",IF(2055<$E15,"",IF($D15="Manuell","",IF(2055>$E15+$F15,IF($D15="Fix",$G15,$G15*(1+$H15)^($F15)),IF($D15="Fix",$G15,$G15*(1+$H15)^(2055-$E15))))))
I16: =IF($A16="","",IF(2018<$E16,"",IF($D16="Manuell","",IF(2018>$E16+$F16,IF($D16="Fix",$G16,$G16*(1+$H16)^($F16)),IF($D16="Fix",$G16,$G16*(1+$H16)^(2018-$E16)))))) | J16: =IF($A16="","",IF(2019<$E16,"",IF($D16="Manuell","",IF(2019>$E16+$F16,IF($D16="Fix",$G16,$G16*(1+$H16)^($F16)),IF($D16="Fix",$G16,$G16*(1+$H16)^(2019-$E16)))))) | K16: =IF($A16="","",IF(2020<$E16,"",IF($D16="Manuell","",IF(2020>$E16+$F16,IF($D16="Fix",$G16,$G16*(1+$H16)^($F16)),IF($D16="Fix",$G16,$G16*(1+$H16)^(2020-$E16)))))) | L16: =IF($A16="","",IF(2021<$E16,"",IF($D16="Manuell","",IF(2021>$E16+$F16,IF($D16="Fix",$G16,$G16*(1+$H16)^($F16)),IF($D16="Fix",$G16,$G16*(1+$H16)^(2021-$E16)))))) | M16: =IF($A16="","",IF(2022<$E16,"",IF($D16="Manuell","",IF(2022>$E16+$F16,IF($D16="Fix",$G16,$G16*(1+$H16)^($F16)),IF($D16="Fix",$G16,$G16*(1+$H16)^(2022-$E16)))))) | N16: =IF($A16="","",IF(2023<$E16,"",IF($D16="Manuell","",IF(2023>$E16+$F16,IF($D16="Fix",$G16,$G16*(1+$H16)^($F16)),IF($D16="Fix",$G16,$G16*(1+$H16)^(2023-$E16)))))) | O16: =IF($A16="","",IF(2024<$E16,"",IF($D16="Manuell","",IF(2024>$E16+$F16,IF($D16="Fix",$G16,$G16*(1+$H16)^($F16)),IF($D16="Fix",$G16,$G16*(1+$H16)^(2024-$E16)))))) | P16: =IF($A16="","",IF(2025<$E16,"",IF($D16="Manuell","",IF(2025>$E16+$F16,IF($D16="Fix",$G16,$G16*(1+$H16)^($F16)),IF($D16="Fix",$G16,$G16*(1+$H16)^(2025-$E16)))))) | Q16: =IF($A16="","",IF(2026<$E16,"",IF($D16="Manuell","",IF(2026>$E16+$F16,IF($D16="Fix",$G16,$G16*(1+$H16)^($F16)),IF($D16="Fix",$G16,$G16*(1+$H16)^(2026-$E16)))))) | R16: =IF($A16="","",IF(2027<$E16,"",IF($D16="Manuell","",IF(2027>$E16+$F16,IF($D16="Fix",$G16,$G16*(1+$H16)^($F16)),IF($D16="Fix",$G16,$G16*(1+$H16)^(2027-$E16)))))) | S16: =IF($A16="","",IF(2028<$E16,"",IF($D16="Manuell","",IF(2028>$E16+$F16,IF($D16="Fix",$G16,$G16*(1+$H16)^($F16)),IF($D16="Fix",$G16,$G16*(1+$H16)^(2028-$E16)))))) | T16: =IF($A16="","",IF(2029<$E16,"",IF($D16="Manuell","",IF(2029>$E16+$F16,IF($D16="Fix",$G16,$G16*(1+$H16)^($F16)),IF($D16="Fix",$G16,$G16*(1+$H16)^(2029-$E16)))))) | U16: =IF($A16="","",IF(2030<$E16,"",IF($D16="Manuell","",IF(2030>$E16+$F16,IF($D16="Fix",$G16,$G16*(1+$H16)^($F16)),IF($D16="Fix",$G16,$G16*(1+$H16)^(2030-$E16)))))) | V16: =IF($A16="","",IF(2031<$E16,"",IF($D16="Manuell","",IF(2031>$E16+$F16,IF($D16="Fix",$G16,$G16*(1+$H16)^($F16)),IF($D16="Fix",$G16,$G16*(1+$H16)^(2031-$E16)))))) | W16: =IF($A16="","",IF(2032<$E16,"",IF($D16="Manuell","",IF(2032>$E16+$F16,IF($D16="Fix",$G16,$G16*(1+$H16)^($F16)),IF($D16="Fix",$G16,$G16*(1+$H16)^(2032-$E16)))))) | X16: =IF($A16="","",IF(2033<$E16,"",IF($D16="Manuell","",IF(2033>$E16+$F16,IF($D16="Fix",$G16,$G16*(1+$H16)^($F16)),IF($D16="Fix",$G16,$G16*(1+$H16)^(2033-$E16)))))) | Y16: =IF($A16="","",IF(2034<$E16,"",IF($D16="Manuell","",IF(2034>$E16+$F16,IF($D16="Fix",$G16,$G16*(1+$H16)^($F16)),IF($D16="Fix",$G16,$G16*(1+$H16)^(2034-$E16)))))) | Z16: =IF($A16="","",IF(2035<$E16,"",IF($D16="Manuell","",IF(2035>$E16+$F16,IF($D16="Fix",$G16,$G16*(1+$H16)^($F16)),IF($D16="Fix",$G16,$G16*(1+$H16)^(2035-$E16)))))) | AA16: =IF($A16="","",IF(2036<$E16,"",IF($D16="Manuell","",IF(2036>$E16+$F16,IF($D16="Fix",$G16,$G16*(1+$H16)^($F16)),IF($D16="Fix",$G16,$G16*(1+$H16)^(2036-$E16)))))) | AB16: =IF($A16="","",IF(2037<$E16,"",IF($D16="Manuell","",IF(2037>$E16+$F16,IF($D16="Fix",$G16,$G16*(1+$H16)^($F16)),IF($D16="Fix",$G16,$G16*(1+$H16)^(2037-$E16)))))) | AC16: =IF($A16="","",IF(2038<$E16,"",IF($D16="Manuell","",IF(2038>$E16+$F16,IF($D16="Fix",$G16,$G16*(1+$H16)^($F16)),IF($D16="Fix",$G16,$G16*(1+$H16)^(2038-$E16)))))) | AD16: =IF($A16="","",IF(2039<$E16,"",IF($D16="Manuell","",IF(2039>$E16+$F16,IF($D16="Fix",$G16,$G16*(1+$H16)^($F16)),IF($D16="Fix",$G16,$G16*(1+$H16)^(2039-$E16)))))) | AE16: =IF($A16="","",IF(2040<$E16,"",IF($D16="Manuell","",IF(2040>$E16+$F16,IF($D16="Fix",$G16,$G16*(1+$H16)^($F16)),IF($D16="Fix",$G16,$G16*(1+$H16)^(2040-$E16)))))) | AF16: =IF($A16="","",IF(2041<$E16,"",IF($D16="Manuell","",IF(2041>$E16+$F16,IF($D16="Fix",$G16,$G16*(1+$H16)^($F16)),IF($D16="Fix",$G16,$G16*(1+$H16)^(2041-$E16)))))) | AG16: =IF($A16="","",IF(2042<$E16,"",IF($D16="Manuell","",IF(2042>$E16+$F16,IF($D16="Fix",$G16,$G16*(1+$H16)^($F16)),IF($D16="Fix",$G16,$G16*(1+$H16)^(2042-$E16)))))) | AH16: =IF($A16="","",IF(2043<$E16,"",IF($D16="Manuell","",IF(2043>$E16+$F16,IF($D16="Fix",$G16,$G16*(1+$H16)^($F16)),IF($D16="Fix",$G16,$G16*(1+$H16)^(2043-$E16)))))) | AI16: =IF($A16="","",IF(2044<$E16,"",IF($D16="Manuell","",IF(2044>$E16+$F16,IF($D16="Fix",$G16,$G16*(1+$H16)^($F16)),IF($D16="Fix",$G16,$G16*(1+$H16)^(2044-$E16)))))) | AJ16: =IF($A16="","",IF(2045<$E16,"",IF($D16="Manuell","",IF(2045>$E16+$F16,IF($D16="Fix",$G16,$G16*(1+$H16)^($F16)),IF($D16="Fix",$G16,$G16*(1+$H16)^(2045-$E16)))))) | AK16: =IF($A16="","",IF(2046<$E16,"",IF($D16="Manuell","",IF(2046>$E16+$F16,IF($D16="Fix",$G16,$G16*(1+$H16)^($F16)),IF($D16="Fix",$G16,$G16*(1+$H16)^(2046-$E16)))))) | AL16: =IF($A16="","",IF(2047<$E16,"",IF($D16="Manuell","",IF(2047>$E16+$F16,IF($D16="Fix",$G16,$G16*(1+$H16)^($F16)),IF($D16="Fix",$G16,$G16*(1+$H16)^(2047-$E16)))))) | AM16: =IF($A16="","",IF(2048<$E16,"",IF($D16="Manuell","",IF(2048>$E16+$F16,IF($D16="Fix",$G16,$G16*(1+$H16)^($F16)),IF($D16="Fix",$G16,$G16*(1+$H16)^(2048-$E16)))))) | AN16: =IF($A16="","",IF(2049<$E16,"",IF($D16="Manuell","",IF(2049>$E16+$F16,IF($D16="Fix",$G16,$G16*(1+$H16)^($F16)),IF($D16="Fix",$G16,$G16*(1+$H16)^(2049-$E16)))))) | AO16: =IF($A16="","",IF(2050<$E16,"",IF($D16="Manuell","",IF(2050>$E16+$F16,IF($D16="Fix",$G16,$G16*(1+$H16)^($F16)),IF($D16="Fix",$G16,$G16*(1+$H16)^(2050-$E16)))))) | AP16: =IF($A16="","",IF(2051<$E16,"",IF($D16="Manuell","",IF(2051>$E16+$F16,IF($D16="Fix",$G16,$G16*(1+$H16)^($F16)),IF($D16="Fix",$G16,$G16*(1+$H16)^(2051-$E16)))))) | AQ16: =IF($A16="","",IF(2052<$E16,"",IF($D16="Manuell","",IF(2052>$E16+$F16,IF($D16="Fix",$G16,$G16*(1+$H16)^($F16)),IF($D16="Fix",$G16,$G16*(1+$H16)^(2052-$E16)))))) | AR16: =IF($A16="","",IF(2053<$E16,"",IF($D16="Manuell","",IF(2053>$E16+$F16,IF($D16="Fix",$G16,$G16*(1+$H16)^($F16)),IF($D16="Fix",$G16,$G16*(1+$H16)^(2053-$E16)))))) | AS16: =IF($A16="","",IF(2054<$E16,"",IF($D16="Manuell","",IF(2054>$E16+$F16,IF($D16="Fix",$G16,$G16*(1+$H16)^($F16)),IF($D16="Fix",$G16,$G16*(1+$H16)^(2054-$E16)))))) | AT16: =IF($A16="","",IF(2055<$E16,"",IF($D16="Manuell","",IF(2055>$E16+$F16,IF($D16="Fix",$G16,$G16*(1+$H16)^($F16)),IF($D16="Fix",$G16,$G16*(1+$H16)^(2055-$E16))))))
I17: =IF($A17="","",IF(2018<$E17,"",IF($D17="Manuell","",IF(2018>$E17+$F17,IF($D17="Fix",$G17,$G17*(1+$H17)^($F17)),IF($D17="Fix",$G17,$G17*(1+$H17)^(2018-$E17)))))) | J17: =IF($A17="","",IF(2019<$E17,"",IF($D17="Manuell","",IF(2019>$E17+$F17,IF($D17="Fix",$G17,$G17*(1+$H17)^($F17)),IF($D17="Fix",$G17,$G17*(1+$H17)^(2019-$E17)))))) | K17: =IF($A17="","",IF(2020<$E17,"",IF($D17="Manuell","",IF(2020>$E17+$F17,IF($D17="Fix",$G17,$G17*(1+$H17)^($F17)),IF($D17="Fix",$G17,$G17*(1+$H17)^(2020-$E17)))))) | L17: =IF($A17="","",IF(2021<$E17,"",IF($D17="Manuell","",IF(2021>$E17+$F17,IF($D17="Fix",$G17,$G17*(1+$H17)^($F17)),IF($D17="Fix",$G17,$G17*(1+$H17)^(2021-$E17)))))) | M17: =IF($A17="","",IF(2022<$E17,"",IF($D17="Manuell","",IF(2022>$E17+$F17,IF($D17="Fix",$G17,$G17*(1+$H17)^($F17)),IF($D17="Fix",$G17,$G17*(1+$H17)^(2022-$E17)))))) | N17: =IF($A17="","",IF(2023<$E17,"",IF($D17="Manuell","",IF(2023>$E17+$F17,IF($D17="Fix",$G17,$G17*(1+$H17)^($F17)),IF($D17="Fix",$G17,$G17*(1+$H17)^(2023-$E17)))))) | O17: =IF($A17="","",IF(2024<$E17,"",IF($D17="Manuell","",IF(2024>$E17+$F17,IF($D17="Fix",$G17,$G17*(1+$H17)^($F17)),IF($D17="Fix",$G17,$G17*(1+$H17)^(2024-$E17)))))) | P17: =IF($A17="","",IF(2025<$E17,"",IF($D17="Manuell","",IF(2025>$E17+$F17,IF($D17="Fix",$G17,$G17*(1+$H17)^($F17)),IF($D17="Fix",$G17,$G17*(1+$H17)^(2025-$E17)))))) | Q17: =IF($A17="","",IF(2026<$E17,"",IF($D17="Manuell","",IF(2026>$E17+$F17,IF($D17="Fix",$G17,$G17*(1+$H17)^($F17)),IF($D17="Fix",$G17,$G17*(1+$H17)^(2026-$E17)))))) | R17: =IF($A17="","",IF(2027<$E17,"",IF($D17="Manuell","",IF(2027>$E17+$F17,IF($D17="Fix",$G17,$G17*(1+$H17)^($F17)),IF($D17="Fix",$G17,$G17*(1+$H17)^(2027-$E17)))))) | S17: =IF($A17="","",IF(2028<$E17,"",IF($D17="Manuell","",IF(2028>$E17+$F17,IF($D17="Fix",$G17,$G17*(1+$H17)^($F17)),IF($D17="Fix",$G17,$G17*(1+$H17)^(2028-$E17)))))) | T17: =IF($A17="","",IF(2029<$E17,"",IF($D17="Manuell","",IF(2029>$E17+$F17,IF($D17="Fix",$G17,$G17*(1+$H17)^($F17)),IF($D17="Fix",$G17,$G17*(1+$H17)^(2029-$E17)))))) | U17: =IF($A17="","",IF(2030<$E17,"",IF($D17="Manuell","",IF(2030>$E17+$F17,IF($D17="Fix",$G17,$G17*(1+$H17)^($F17)),IF($D17="Fix",$G17,$G17*(1+$H17)^(2030-$E17)))))) | V17: =IF($A17="","",IF(2031<$E17,"",IF($D17="Manuell","",IF(2031>$E17+$F17,IF($D17="Fix",$G17,$G17*(1+$H17)^($F17)),IF($D17="Fix",$G17,$G17*(1+$H17)^(2031-$E17)))))) | W17: =IF($A17="","",IF(2032<$E17,"",IF($D17="Manuell","",IF(2032>$E17+$F17,IF($D17="Fix",$G17,$G17*(1+$H17)^($F17)),IF($D17="Fix",$G17,$G17*(1+$H17)^(2032-$E17)))))) | X17: =IF($A17="","",IF(2033<$E17,"",IF($D17="Manuell","",IF(2033>$E17+$F17,IF($D17="Fix",$G17,$G17*(1+$H17)^($F17)),IF($D17="Fix",$G17,$G17*(1+$H17)^(2033-$E17)))))) | Y17: =IF($A17="","",IF(2034<$E17,"",IF($D17="Manuell","",IF(2034>$E17+$F17,IF($D17="Fix",$G17,$G17*(1+$H17)^($F17)),IF($D17="Fix",$G17,$G17*(1+$H17)^(2034-$E17)))))) | Z17: =IF($A17="","",IF(2035<$E17,"",IF($D17="Manuell","",IF(2035>$E17+$F17,IF($D17="Fix",$G17,$G17*(1+$H17)^($F17)),IF($D17="Fix",$G17,$G17*(1+$H17)^(2035-$E17)))))) | AA17: =IF($A17="","",IF(2036<$E17,"",IF($D17="Manuell","",IF(2036>$E17+$F17,IF($D17="Fix",$G17,$G17*(1+$H17)^($F17)),IF($D17="Fix",$G17,$G17*(1+$H17)^(2036-$E17)))))) | AB17: =IF($A17="","",IF(2037<$E17,"",IF($D17="Manuell","",IF(2037>$E17+$F17,IF($D17="Fix",$G17,$G17*(1+$H17)^($F17)),IF($D17="Fix",$G17,$G17*(1+$H17)^(2037-$E17)))))) | AC17: =IF($A17="","",IF(2038<$E17,"",IF($D17="Manuell","",IF(2038>$E17+$F17,IF($D17="Fix",$G17,$G17*(1+$H17)^($F17)),IF($D17="Fix",$G17,$G17*(1+$H17)^(2038-$E17)))))) | AD17: =IF($A17="","",IF(2039<$E17,"",IF($D17="Manuell","",IF(2039>$E17+$F17,IF($D17="Fix",$G17,$G17*(1+$H17)^($F17)),IF($D17="Fix",$G17,$G17*(1+$H17)^(2039-$E17)))))) | AE17: =IF($A17="","",IF(2040<$E17,"",IF($D17="Manuell","",IF(2040>$E17+$F17,IF($D17="Fix",$G17,$G17*(1+$H17)^($F17)),IF($D17="Fix",$G17,$G17*(1+$H17)^(2040-$E17)))))) | AF17: =IF($A17="","",IF(2041<$E17,"",IF($D17="Manuell","",IF(2041>$E17+$F17,IF($D17="Fix",$G17,$G17*(1+$H17)^($F17)),IF($D17="Fix",$G17,$G17*(1+$H17)^(2041-$E17)))))) | AG17: =IF($A17="","",IF(2042<$E17,"",IF($D17="Manuell","",IF(2042>$E17+$F17,IF($D17="Fix",$G17,$G17*(1+$H17)^($F17)),IF($D17="Fix",$G17,$G17*(1+$H17)^(2042-$E17)))))) | AH17: =IF($A17="","",IF(2043<$E17,"",IF($D17="Manuell","",IF(2043>$E17+$F17,IF($D17="Fix",$G17,$G17*(1+$H17)^($F17)),IF($D17="Fix",$G17,$G17*(1+$H17)^(2043-$E17)))))) | AI17: =IF($A17="","",IF(2044<$E17,"",IF($D17="Manuell","",IF(2044>$E17+$F17,IF($D17="Fix",$G17,$G17*(1+$H17)^($F17)),IF($D17="Fix",$G17,$G17*(1+$H17)^(2044-$E17)))))) | AJ17: =IF($A17="","",IF(2045<$E17,"",IF($D17="Manuell","",IF(2045>$E17+$F17,IF($D17="Fix",$G17,$G17*(1+$H17)^($F17)),IF($D17="Fix",$G17,$G17*(1+$H17)^(2045-$E17)))))) | AK17: =IF($A17="","",IF(2046<$E17,"",IF($D17="Manuell","",IF(2046>$E17+$F17,IF($D17="Fix",$G17,$G17*(1+$H17)^($F17)),IF($D17="Fix",$G17,$G17*(1+$H17)^(2046-$E17)))))) | AL17: =IF($A17="","",IF(2047<$E17,"",IF($D17="Manuell","",IF(2047>$E17+$F17,IF($D17="Fix",$G17,$G17*(1+$H17)^($F17)),IF($D17="Fix",$G17,$G17*(1+$H17)^(2047-$E17)))))) | AM17: =IF($A17="","",IF(2048<$E17,"",IF($D17="Manuell","",IF(2048>$E17+$F17,IF($D17="Fix",$G17,$G17*(1+$H17)^($F17)),IF($D17="Fix",$G17,$G17*(1+$H17)^(2048-$E17)))))) | AN17: =IF($A17="","",IF(2049<$E17,"",IF($D17="Manuell","",IF(2049>$E17+$F17,IF($D17="Fix",$G17,$G17*(1+$H17)^($F17)),IF($D17="Fix",$G17,$G17*(1+$H17)^(2049-$E17)))))) | AO17: =IF($A17="","",IF(2050<$E17,"",IF($D17="Manuell","",IF(2050>$E17+$F17,IF($D17="Fix",$G17,$G17*(1+$H17)^($F17)),IF($D17="Fix",$G17,$G17*(1+$H17)^(2050-$E17)))))) | AP17: =IF($A17="","",IF(2051<$E17,"",IF($D17="Manuell","",IF(2051>$E17+$F17,IF($D17="Fix",$G17,$G17*(1+$H17)^($F17)),IF($D17="Fix",$G17,$G17*(1+$H17)^(2051-$E17)))))) | AQ17: =IF($A17="","",IF(2052<$E17,"",IF($D17="Manuell","",IF(2052>$E17+$F17,IF($D17="Fix",$G17,$G17*(1+$H17)^($F17)),IF($D17="Fix",$G17,$G17*(1+$H17)^(2052-$E17)))))) | AR17: =IF($A17="","",IF(2053<$E17,"",IF($D17="Manuell","",IF(2053>$E17+$F17,IF($D17="Fix",$G17,$G17*(1+$H17)^($F17)),IF($D17="Fix",$G17,$G17*(1+$H17)^(2053-$E17)))))) | AS17: =IF($A17="","",IF(2054<$E17,"",IF($D17="Manuell","",IF(2054>$E17+$F17,IF($D17="Fix",$G17,$G17*(1+$H17)^($F17)),IF($D17="Fix",$G17,$G17*(1+$H17)^(2054-$E17)))))) | AT17: =IF($A17="","",IF(2055<$E17,"",IF($D17="Manuell","",IF(2055>$E17+$F17,IF($D17="Fix",$G17,$G17*(1+$H17)^($F17)),IF($D17="Fix",$G17,$G17*(1+$H17)^(2055-$E17))))))
I18: =IF($A18="","",IF(2018<$E18,"",IF($D18="Manuell","",IF(2018>$E18+$F18,IF($D18="Fix",$G18,$G18*(1+$H18)^($F18)),IF($D18="Fix",$G18,$G18*(1+$H18)^(2018-$E18)))))) | J18: =IF($A18="","",IF(2019<$E18,"",IF($D18="Manuell","",IF(2019>$E18+$F18,IF($D18="Fix",$G18,$G18*(1+$H18)^($F18)),IF($D18="Fix",$G18,$G18*(1+$H18)^(2019-$E18)))))) | K18: =IF($A18="","",IF(2020<$E18,"",IF($D18="Manuell","",IF(2020>$E18+$F18,IF($D18="Fix",$G18,$G18*(1+$H18)^($F18)),IF($D18="Fix",$G18,$G18*(1+$H18)^(2020-$E18)))))) | L18: =IF($A18="","",IF(2021<$E18,"",IF($D18="Manuell","",IF(2021>$E18+$F18,IF($D18="Fix",$G18,$G18*(1+$H18)^($F18)),IF($D18="Fix",$G18,$G18*(1+$H18)^(2021-$E18)))))) | M18: =IF($A18="","",IF(2022<$E18,"",IF($D18="Manuell","",IF(2022>$E18+$F18,IF($D18="Fix",$G18,$G18*(1+$H18)^($F18)),IF($D18="Fix",$G18,$G18*(1+$H18)^(2022-$E18)))))) | N18: =IF($A18="","",IF(2023<$E18,"",IF($D18="Manuell","",IF(2023>$E18+$F18,IF($D18="Fix",$G18,$G18*(1+$H18)^($F18)),IF($D18="Fix",$G18,$G18*(1+$H18)^(2023-$E18)))))) | O18: =IF($A18="","",IF(2024<$E18,"",IF($D18="Manuell","",IF(2024>$E18+$F18,IF($D18="Fix",$G18,$G18*(1+$H18)^($F18)),IF($D18="Fix",$G18,$G18*(1+$H18)^(2024-$E18)))))) | P18: =IF($A18="","",IF(2025<$E18,"",IF($D18="Manuell","",IF(2025>$E18+$F18,IF($D18="Fix",$G18,$G18*(1+$H18)^($F18)),IF($D18="Fix",$G18,$G18*(1+$H18)^(2025-$E18)))))) | Q18: =IF($A18="","",IF(2026<$E18,"",IF($D18="Manuell","",IF(2026>$E18+$F18,IF($D18="Fix",$G18,$G18*(1+$H18)^($F18)),IF($D18="Fix",$G18,$G18*(1+$H18)^(2026-$E18)))))) | R18: =IF($A18="","",IF(2027<$E18,"",IF($D18="Manuell","",IF(2027>$E18+$F18,IF($D18="Fix",$G18,$G18*(1+$H18)^($F18)),IF($D18="Fix",$G18,$G18*(1+$H18)^(2027-$E18)))))) | S18: =IF($A18="","",IF(2028<$E18,"",IF($D18="Manuell","",IF(2028>$E18+$F18,IF($D18="Fix",$G18,$G18*(1+$H18)^($F18)),IF($D18="Fix",$G18,$G18*(1+$H18)^(2028-$E18)))))) | T18: =IF($A18="","",IF(2029<$E18,"",IF($D18="Manuell","",IF(2029>$E18+$F18,IF($D18="Fix",$G18,$G18*(1+$H18)^($F18)),IF($D18="Fix",$G18,$G18*(1+$H18)^(2029-$E18)))))) | U18: =IF($A18="","",IF(2030<$E18,"",IF($D18="Manuell","",IF(2030>$E18+$F18,IF($D18="Fix",$G18,$G18*(1+$H18)^($F18)),IF($D18="Fix",$G18,$G18*(1+$H18)^(2030-$E18)))))) | V18: =IF($A18="","",IF(2031<$E18,"",IF($D18="Manuell","",IF(2031>$E18+$F18,IF($D18="Fix",$G18,$G18*(1+$H18)^($F18)),IF($D18="Fix",$G18,$G18*(1+$H18)^(2031-$E18)))))) | W18: =IF($A18="","",IF(2032<$E18,"",IF($D18="Manuell","",IF(2032>$E18+$F18,IF($D18="Fix",$G18,$G18*(1+$H18)^($F18)),IF($D18="Fix",$G18,$G18*(1+$H18)^(2032-$E18)))))) | X18: =IF($A18="","",IF(2033<$E18,"",IF($D18="Manuell","",IF(2033>$E18+$F18,IF($D18="Fix",$G18,$G18*(1+$H18)^($F18)),IF($D18="Fix",$G18,$G18*(1+$H18)^(2033-$E18)))))) | Y18: =IF($A18="","",IF(2034<$E18,"",IF($D18="Manuell","",IF(2034>$E18+$F18,IF($D18="Fix",$G18,$G18*(1+$H18)^($F18)),IF($D18="Fix",$G18,$G18*(1+$H18)^(2034-$E18)))))) | Z18: =IF($A18="","",IF(2035<$E18,"",IF($D18="Manuell","",IF(2035>$E18+$F18,IF($D18="Fix",$G18,$G18*(1+$H18)^($F18)),IF($D18="Fix",$G18,$G18*(1+$H18)^(2035-$E18)))))) | AA18: =IF($A18="","",IF(2036<$E18,"",IF($D18="Manuell","",IF(2036>$E18+$F18,IF($D18="Fix",$G18,$G18*(1+$H18)^($F18)),IF($D18="Fix",$G18,$G18*(1+$H18)^(2036-$E18)))))) | AB18: =IF($A18="","",IF(2037<$E18,"",IF($D18="Manuell","",IF(2037>$E18+$F18,IF($D18="Fix",$G18,$G18*(1+$H18)^($F18)),IF($D18="Fix",$G18,$G18*(1+$H18)^(2037-$E18)))))) | AC18: =IF($A18="","",IF(2038<$E18,"",IF($D18="Manuell","",IF(2038>$E18+$F18,IF($D18="Fix",$G18,$G18*(1+$H18)^($F18)),IF($D18="Fix",$G18,$G18*(1+$H18)^(2038-$E18)))))) | AD18: =IF($A18="","",IF(2039<$E18,"",IF($D18="Manuell","",IF(2039>$E18+$F18,IF($D18="Fix",$G18,$G18*(1+$H18)^($F18)),IF($D18="Fix",$G18,$G18*(1+$H18)^(2039-$E18)))))) | AE18: =IF($A18="","",IF(2040<$E18,"",IF($D18="Manuell","",IF(2040>$E18+$F18,IF($D18="Fix",$G18,$G18*(1+$H18)^($F18)),IF($D18="Fix",$G18,$G18*(1+$H18)^(2040-$E18)))))) | AF18: =IF($A18="","",IF(2041<$E18,"",IF($D18="Manuell","",IF(2041>$E18+$F18,IF($D18="Fix",$G18,$G18*(1+$H18)^($F18)),IF($D18="Fix",$G18,$G18*(1+$H18)^(2041-$E18)))))) | AG18: =IF($A18="","",IF(2042<$E18,"",IF($D18="Manuell","",IF(2042>$E18+$F18,IF($D18="Fix",$G18,$G18*(1+$H18)^($F18)),IF($D18="Fix",$G18,$G18*(1+$H18)^(2042-$E18)))))) | AH18: =IF($A18="","",IF(2043<$E18,"",IF($D18="Manuell","",IF(2043>$E18+$F18,IF($D18="Fix",$G18,$G18*(1+$H18)^($F18)),IF($D18="Fix",$G18,$G18*(1+$H18)^(2043-$E18)))))) | AI18: =IF($A18="","",IF(2044<$E18,"",IF($D18="Manuell","",IF(2044>$E18+$F18,IF($D18="Fix",$G18,$G18*(1+$H18)^($F18)),IF($D18="Fix",$G18,$G18*(1+$H18)^(2044-$E18)))))) | AJ18: =IF($A18="","",IF(2045<$E18,"",IF($D18="Manuell","",IF(2045>$E18+$F18,IF($D18="Fix",$G18,$G18*(1+$H18)^($F18)),IF($D18="Fix",$G18,$G18*(1+$H18)^(2045-$E18)))))) | AK18: =IF($A18="","",IF(2046<$E18,"",IF($D18="Manuell","",IF(2046>$E18+$F18,IF($D18="Fix",$G18,$G18*(1+$H18)^($F18)),IF($D18="Fix",$G18,$G18*(1+$H18)^(2046-$E18)))))) | AL18: =IF($A18="","",IF(2047<$E18,"",IF($D18="Manuell","",IF(2047>$E18+$F18,IF($D18="Fix",$G18,$G18*(1+$H18)^($F18)),IF($D18="Fix",$G18,$G18*(1+$H18)^(2047-$E18)))))) | AM18: =IF($A18="","",IF(2048<$E18,"",IF($D18="Manuell","",IF(2048>$E18+$F18,IF($D18="Fix",$G18,$G18*(1+$H18)^($F18)),IF($D18="Fix",$G18,$G18*(1+$H18)^(2048-$E18)))))) | AN18: =IF($A18="","",IF(2049<$E18,"",IF($D18="Manuell","",IF(2049>$E18+$F18,IF($D18="Fix",$G18,$G18*(1+$H18)^($F18)),IF($D18="Fix",$G18,$G18*(1+$H18)^(2049-$E18)))))) | AO18: =IF($A18="","",IF(2050<$E18,"",IF($D18="Manuell","",IF(2050>$E18+$F18,IF($D18="Fix",$G18,$G18*(1+$H18)^($F18)),IF($D18="Fix",$G18,$G18*(1+$H18)^(2050-$E18)))))) | AP18: =IF($A18="","",IF(2051<$E18,"",IF($D18="Manuell","",IF(2051>$E18+$F18,IF($D18="Fix",$G18,$G18*(1+$H18)^($F18)),IF($D18="Fix",$G18,$G18*(1+$H18)^(2051-$E18)))))) | AQ18: =IF($A18="","",IF(2052<$E18,"",IF($D18="Manuell","",IF(2052>$E18+$F18,IF($D18="Fix",$G18,$G18*(1+$H18)^($F18)),IF($D18="Fix",$G18,$G18*(1+$H18)^(2052-$E18)))))) | AR18: =IF($A18="","",IF(2053<$E18,"",IF($D18="Manuell","",IF(2053>$E18+$F18,IF($D18="Fix",$G18,$G18*(1+$H18)^($F18)),IF($D18="Fix",$G18,$G18*(1+$H18)^(2053-$E18)))))) | AS18: =IF($A18="","",IF(2054<$E18,"",IF($D18="Manuell","",IF(2054>$E18+$F18,IF($D18="Fix",$G18,$G18*(1+$H18)^($F18)),IF($D18="Fix",$G18,$G18*(1+$H18)^(2054-$E18)))))) | AT18: =IF($A18="","",IF(2055<$E18,"",IF($D18="Manuell","",IF(2055>$E18+$F18,IF($D18="Fix",$G18,$G18*(1+$H18)^($F18)),IF($D18="Fix",$G18,$G18*(1+$H18)^(2055-$E18))))))
I19: =IF($A19="","",IF(2018<$E19,"",IF($D19="Manuell","",IF(2018>$E19+$F19,IF($D19="Fix",$G19,$G19*(1+$H19)^($F19)),IF($D19="Fix",$G19,$G19*(1+$H19)^(2018-$E19)))))) | J19: =IF($A19="","",IF(2019<$E19,"",IF($D19="Manuell","",IF(2019>$E19+$F19,IF($D19="Fix",$G19,$G19*(1+$H19)^($F19)),IF($D19="Fix",$G19,$G19*(1+$H19)^(2019-$E19)))))) | K19: =IF($A19="","",IF(2020<$E19,"",IF($D19="Manuell","",IF(2020>$E19+$F19,IF($D19="Fix",$G19,$G19*(1+$H19)^($F19)),IF($D19="Fix",$G19,$G19*(1+$H19)^(2020-$E19)))))) | L19: =IF($A19="","",IF(2021<$E19,"",IF($D19="Manuell","",IF(2021>$E19+$F19,IF($D19="Fix",$G19,$G19*(1+$H19)^($F19)),IF($D19="Fix",$G19,$G19*(1+$H19)^(2021-$E19)))))) | M19: =IF($A19="","",IF(2022<$E19,"",IF($D19="Manuell","",IF(2022>$E19+$F19,IF($D19="Fix",$G19,$G19*(1+$H19)^($F19)),IF($D19="Fix",$G19,$G19*(1+$H19)^(2022-$E19)))))) | N19: =IF($A19="","",IF(2023<$E19,"",IF($D19="Manuell","",IF(2023>$E19+$F19,IF($D19="Fix",$G19,$G19*(1+$H19)^($F19)),IF($D19="Fix",$G19,$G19*(1+$H19)^(2023-$E19)))))) | O19: =IF($A19="","",IF(2024<$E19,"",IF($D19="Manuell","",IF(2024>$E19+$F19,IF($D19="Fix",$G19,$G19*(1+$H19)^($F19)),IF($D19="Fix",$G19,$G19*(1+$H19)^(2024-$E19)))))) | P19: =IF($A19="","",IF(2025<$E19,"",IF($D19="Manuell","",IF(2025>$E19+$F19,IF($D19="Fix",$G19,$G19*(1+$H19)^($F19)),IF($D19="Fix",$G19,$G19*(1+$H19)^(2025-$E19)))))) | Q19: =IF($A19="","",IF(2026<$E19,"",IF($D19="Manuell","",IF(2026>$E19+$F19,IF($D19="Fix",$G19,$G19*(1+$H19)^($F19)),IF($D19="Fix",$G19,$G19*(1+$H19)^(2026-$E19)))))) | R19: =IF($A19="","",IF(2027<$E19,"",IF($D19="Manuell","",IF(2027>$E19+$F19,IF($D19="Fix",$G19,$G19*(1+$H19)^($F19)),IF($D19="Fix",$G19,$G19*(1+$H19)^(2027-$E19)))))) | S19: =IF($A19="","",IF(2028<$E19,"",IF($D19="Manuell","",IF(2028>$E19+$F19,IF($D19="Fix",$G19,$G19*(1+$H19)^($F19)),IF($D19="Fix",$G19,$G19*(1+$H19)^(2028-$E19)))))) | T19: =IF($A19="","",IF(2029<$E19,"",IF($D19="Manuell","",IF(2029>$E19+$F19,IF($D19="Fix",$G19,$G19*(1+$H19)^($F19)),IF($D19="Fix",$G19,$G19*(1+$H19)^(2029-$E19)))))) | U19: =IF($A19="","",IF(2030<$E19,"",IF($D19="Manuell","",IF(2030>$E19+$F19,IF($D19="Fix",$G19,$G19*(1+$H19)^($F19)),IF($D19="Fix",$G19,$G19*(1+$H19)^(2030-$E19)))))) | V19: =IF($A19="","",IF(2031<$E19,"",IF($D19="Manuell","",IF(2031>$E19+$F19,IF($D19="Fix",$G19,$G19*(1+$H19)^($F19)),IF($D19="Fix",$G19,$G19*(1+$H19)^(2031-$E19)))))) | W19: =IF($A19="","",IF(2032<$E19,"",IF($D19="Manuell","",IF(2032>$E19+$F19,IF($D19="Fix",$G19,$G19*(1+$H19)^($F19)),IF($D19="Fix",$G19,$G19*(1+$H19)^(2032-$E19)))))) | X19: =IF($A19="","",IF(2033<$E19,"",IF($D19="Manuell","",IF(2033>$E19+$F19,IF($D19="Fix",$G19,$G19*(1+$H19)^($F19)),IF($D19="Fix",$G19,$G19*(1+$H19)^(2033-$E19)))))) | Y19: =IF($A19="","",IF(2034<$E19,"",IF($D19="Manuell","",IF(2034>$E19+$F19,IF($D19="Fix",$G19,$G19*(1+$H19)^($F19)),IF($D19="Fix",$G19,$G19*(1+$H19)^(2034-$E19)))))) | Z19: =IF($A19="","",IF(2035<$E19,"",IF($D19="Manuell","",IF(2035>$E19+$F19,IF($D19="Fix",$G19,$G19*(1+$H19)^($F19)),IF($D19="Fix",$G19,$G19*(1+$H19)^(2035-$E19)))))) | AA19: =IF($A19="","",IF(2036<$E19,"",IF($D19="Manuell","",IF(2036>$E19+$F19,IF($D19="Fix",$G19,$G19*(1+$H19)^($F19)),IF($D19="Fix",$G19,$G19*(1+$H19)^(2036-$E19)))))) | AB19: =IF($A19="","",IF(2037<$E19,"",IF($D19="Manuell","",IF(2037>$E19+$F19,IF($D19="Fix",$G19,$G19*(1+$H19)^($F19)),IF($D19="Fix",$G19,$G19*(1+$H19)^(2037-$E19)))))) | AC19: =IF($A19="","",IF(2038<$E19,"",IF($D19="Manuell","",IF(2038>$E19+$F19,IF($D19="Fix",$G19,$G19*(1+$H19)^($F19)),IF($D19="Fix",$G19,$G19*(1+$H19)^(2038-$E19)))))) | AD19: =IF($A19="","",IF(2039<$E19,"",IF($D19="Manuell","",IF(2039>$E19+$F19,IF($D19="Fix",$G19,$G19*(1+$H19)^($F19)),IF($D19="Fix",$G19,$G19*(1+$H19)^(2039-$E19)))))) | AE19: =IF($A19="","",IF(2040<$E19,"",IF($D19="Manuell","",IF(2040>$E19+$F19,IF($D19="Fix",$G19,$G19*(1+$H19)^($F19)),IF($D19="Fix",$G19,$G19*(1+$H19)^(2040-$E19)))))) | AF19: =IF($A19="","",IF(2041<$E19,"",IF($D19="Manuell","",IF(2041>$E19+$F19,IF($D19="Fix",$G19,$G19*(1+$H19)^($F19)),IF($D19="Fix",$G19,$G19*(1+$H19)^(2041-$E19)))))) | AG19: =IF($A19="","",IF(2042<$E19,"",IF($D19="Manuell","",IF(2042>$E19+$F19,IF($D19="Fix",$G19,$G19*(1+$H19)^($F19)),IF($D19="Fix",$G19,$G19*(1+$H19)^(2042-$E19)))))) | AH19: =IF($A19="","",IF(2043<$E19,"",IF($D19="Manuell","",IF(2043>$E19+$F19,IF($D19="Fix",$G19,$G19*(1+$H19)^($F19)),IF($D19="Fix",$G19,$G19*(1+$H19)^(2043-$E19)))))) | AI19: =IF($A19="","",IF(2044<$E19,"",IF($D19="Manuell","",IF(2044>$E19+$F19,IF($D19="Fix",$G19,$G19*(1+$H19)^($F19)),IF($D19="Fix",$G19,$G19*(1+$H19)^(2044-$E19)))))) | AJ19: =IF($A19="","",IF(2045<$E19,"",IF($D19="Manuell","",IF(2045>$E19+$F19,IF($D19="Fix",$G19,$G19*(1+$H19)^($F19)),IF($D19="Fix",$G19,$G19*(1+$H19)^(2045-$E19)))))) | AK19: =IF($A19="","",IF(2046<$E19,"",IF($D19="Manuell","",IF(2046>$E19+$F19,IF($D19="Fix",$G19,$G19*(1+$H19)^($F19)),IF($D19="Fix",$G19,$G19*(1+$H19)^(2046-$E19)))))) | AL19: =IF($A19="","",IF(2047<$E19,"",IF($D19="Manuell","",IF(2047>$E19+$F19,IF($D19="Fix",$G19,$G19*(1+$H19)^($F19)),IF($D19="Fix",$G19,$G19*(1+$H19)^(2047-$E19)))))) | AM19: =IF($A19="","",IF(2048<$E19,"",IF($D19="Manuell","",IF(2048>$E19+$F19,IF($D19="Fix",$G19,$G19*(1+$H19)^($F19)),IF($D19="Fix",$G19,$G19*(1+$H19)^(2048-$E19)))))) | AN19: =IF($A19="","",IF(2049<$E19,"",IF($D19="Manuell","",IF(2049>$E19+$F19,IF($D19="Fix",$G19,$G19*(1+$H19)^($F19)),IF($D19="Fix",$G19,$G19*(1+$H19)^(2049-$E19)))))) | AO19: =IF($A19="","",IF(2050<$E19,"",IF($D19="Manuell","",IF(2050>$E19+$F19,IF($D19="Fix",$G19,$G19*(1+$H19)^($F19)),IF($D19="Fix",$G19,$G19*(1+$H19)^(2050-$E19)))))) | AP19: =IF($A19="","",IF(2051<$E19,"",IF($D19="Manuell","",IF(2051>$E19+$F19,IF($D19="Fix",$G19,$G19*(1+$H19)^($F19)),IF($D19="Fix",$G19,$G19*(1+$H19)^(2051-$E19)))))) | AQ19: =IF($A19="","",IF(2052<$E19,"",IF($D19="Manuell","",IF(2052>$E19+$F19,IF($D19="Fix",$G19,$G19*(1+$H19)^($F19)),IF($D19="Fix",$G19,$G19*(1+$H19)^(2052-$E19)))))) | AR19: =IF($A19="","",IF(2053<$E19,"",IF($D19="Manuell","",IF(2053>$E19+$F19,IF($D19="Fix",$G19,$G19*(1+$H19)^($F19)),IF($D19="Fix",$G19,$G19*(1+$H19)^(2053-$E19)))))) | AS19: =IF($A19="","",IF(2054<$E19,"",IF($D19="Manuell","",IF(2054>$E19+$F19,IF($D19="Fix",$G19,$G19*(1+$H19)^($F19)),IF($D19="Fix",$G19,$G19*(1+$H19)^(2054-$E19)))))) | AT19: =IF($A19="","",IF(2055<$E19,"",IF($D19="Manuell","",IF(2055>$E19+$F19,IF($D19="Fix",$G19,$G19*(1+$H19)^($F19)),IF($D19="Fix",$G19,$G19*(1+$H19)^(2055-$E19))))))
I20: =IF($A20="","",IF(2018<$E20,"",IF($D20="Manuell","",IF(2018>$E20+$F20,IF($D20="Fix",$G20,$G20*(1+$H20)^($F20)),IF($D20="Fix",$G20,$G20*(1+$H20)^(2018-$E20)))))) | J20: =IF($A20="","",IF(2019<$E20,"",IF($D20="Manuell","",IF(2019>$E20+$F20,IF($D20="Fix",$G20,$G20*(1+$H20)^($F20)),IF($D20="Fix",$G20,$G20*(1+$H20)^(2019-$E20)))))) | K20: =IF($A20="","",IF(2020<$E20,"",IF($D20="Manuell","",IF(2020>$E20+$F20,IF($D20="Fix",$G20,$G20*(1+$H20)^($F20)),IF($D20="Fix",$G20,$G20*(1+$H20)^(2020-$E20)))))) | L20: =IF($A20="","",IF(2021<$E20,"",IF($D20="Manuell","",IF(2021>$E20+$F20,IF($D20="Fix",$G20,$G20*(1+$H20)^($F20)),IF($D20="Fix",$G20,$G20*(1+$H20)^(2021-$E20)))))) | M20: =IF($A20="","",IF(2022<$E20,"",IF($D20="Manuell","",IF(2022>$E20+$F20,IF($D20="Fix",$G20,$G20*(1+$H20)^($F20)),IF($D20="Fix",$G20,$G20*(1+$H20)^(2022-$E20)))))) | N20: =IF($A20="","",IF(2023<$E20,"",IF($D20="Manuell","",IF(2023>$E20+$F20,IF($D20="Fix",$G20,$G20*(1+$H20)^($F20)),IF($D20="Fix",$G20,$G20*(1+$H20)^(2023-$E20)))))) | O20: =IF($A20="","",IF(2024<$E20,"",IF($D20="Manuell","",IF(2024>$E20+$F20,IF($D20="Fix",$G20,$G20*(1+$H20)^($F20)),IF($D20="Fix",$G20,$G20*(1+$H20)^(2024-$E20)))))) | P20: =IF($A20="","",IF(2025<$E20,"",IF($D20="Manuell","",IF(2025>$E20+$F20,IF($D20="Fix",$G20,$G20*(1+$H20)^($F20)),IF($D20="Fix",$G20,$G20*(1+$H20)^(2025-$E20)))))) | Q20: =IF($A20="","",IF(2026<$E20,"",IF($D20="Manuell","",IF(2026>$E20+$F20,IF($D20="Fix",$G20,$G20*(1+$H20)^($F20)),IF($D20="Fix",$G20,$G20*(1+$H20)^(2026-$E20)))))) | R20: =IF($A20="","",IF(2027<$E20,"",IF($D20="Manuell","",IF(2027>$E20+$F20,IF($D20="Fix",$G20,$G20*(1+$H20)^($F20)),IF($D20="Fix",$G20,$G20*(1+$H20)^(2027-$E20)))))) | S20: =IF($A20="","",IF(2028<$E20,"",IF($D20="Manuell","",IF(2028>$E20+$F20,IF($D20="Fix",$G20,$G20*(1+$H20)^($F20)),IF($D20="Fix",$G20,$G20*(1+$H20)^(2028-$E20)))))) | T20: =IF($A20="","",IF(2029<$E20,"",IF($D20="Manuell","",IF(2029>$E20+$F20,IF($D20="Fix",$G20,$G20*(1+$H20)^($F20)),IF($D20="Fix",$G20,$G20*(1+$H20)^(2029-$E20)))))) | U20: =IF($A20="","",IF(2030<$E20,"",IF($D20="Manuell","",IF(2030>$E20+$F20,IF($D20="Fix",$G20,$G20*(1+$H20)^($F20)),IF($D20="Fix",$G20,$G20*(1+$H20)^(2030-$E20)))))) | V20: =IF($A20="","",IF(2031<$E20,"",IF($D20="Manuell","",IF(2031>$E20+$F20,IF($D20="Fix",$G20,$G20*(1+$H20)^($F20)),IF($D20="Fix",$G20,$G20*(1+$H20)^(2031-$E20)))))) | W20: =IF($A20="","",IF(2032<$E20,"",IF($D20="Manuell","",IF(2032>$E20+$F20,IF($D20="Fix",$G20,$G20*(1+$H20)^($F20)),IF($D20="Fix",$G20,$G20*(1+$H20)^(2032-$E20)))))) | X20: =IF($A20="","",IF(2033<$E20,"",IF($D20="Manuell","",IF(2033>$E20+$F20,IF($D20="Fix",$G20,$G20*(1+$H20)^($F20)),IF($D20="Fix",$G20,$G20*(1+$H20)^(2033-$E20)))))) | Y20: =IF($A20="","",IF(2034<$E20,"",IF($D20="Manuell","",IF(2034>$E20+$F20,IF($D20="Fix",$G20,$G20*(1+$H20)^($F20)),IF($D20="Fix",$G20,$G20*(1+$H20)^(2034-$E20)))))) | Z20: =IF($A20="","",IF(2035<$E20,"",IF($D20="Manuell","",IF(2035>$E20+$F20,IF($D20="Fix",$G20,$G20*(1+$H20)^($F20)),IF($D20="Fix",$G20,$G20*(1+$H20)^(2035-$E20)))))) | AA20: =IF($A20="","",IF(2036<$E20,"",IF($D20="Manuell","",IF(2036>$E20+$F20,IF($D20="Fix",$G20,$G20*(1+$H20)^($F20)),IF($D20="Fix",$G20,$G20*(1+$H20)^(2036-$E20)))))) | AB20: =IF($A20="","",IF(2037<$E20,"",IF($D20="Manuell","",IF(2037>$E20+$F20,IF($D20="Fix",$G20,$G20*(1+$H20)^($F20)),IF($D20="Fix",$G20,$G20*(1+$H20)^(2037-$E20)))))) | AC20: =IF($A20="","",IF(2038<$E20,"",IF($D20="Manuell","",IF(2038>$E20+$F20,IF($D20="Fix",$G20,$G20*(1+$H20)^($F20)),IF($D20="Fix",$G20,$G20*(1+$H20)^(2038-$E20)))))) | AD20: =IF($A20="","",IF(2039<$E20,"",IF($D20="Manuell","",IF(2039>$E20+$F20,IF($D20="Fix",$G20,$G20*(1+$H20)^($F20)),IF($D20="Fix",$G20,$G20*(1+$H20)^(2039-$E20)))))) | AE20: =IF($A20="","",IF(2040<$E20,"",IF($D20="Manuell","",IF(2040>$E20+$F20,IF($D20="Fix",$G20,$G20*(1+$H20)^($F20)),IF($D20="Fix",$G20,$G20*(1+$H20)^(2040-$E20)))))) | AF20: =IF($A20="","",IF(2041<$E20,"",IF($D20="Manuell","",IF(2041>$E20+$F20,IF($D20="Fix",$G20,$G20*(1+$H20)^($F20)),IF($D20="Fix",$G20,$G20*(1+$H20)^(2041-$E20)))))) | AG20: =IF($A20="","",IF(2042<$E20,"",IF($D20="Manuell","",IF(2042>$E20+$F20,IF($D20="Fix",$G20,$G20*(1+$H20)^($F20)),IF($D20="Fix",$G20,$G20*(1+$H20)^(2042-$E20)))))) | AH20: =IF($A20="","",IF(2043<$E20,"",IF($D20="Manuell","",IF(2043>$E20+$F20,IF($D20="Fix",$G20,$G20*(1+$H20)^($F20)),IF($D20="Fix",$G20,$G20*(1+$H20)^(2043-$E20)))))) | AI20: =IF($A20="","",IF(2044<$E20,"",IF($D20="Manuell","",IF(2044>$E20+$F20,IF($D20="Fix",$G20,$G20*(1+$H20)^($F20)),IF($D20="Fix",$G20,$G20*(1+$H20)^(2044-$E20)))))) | AJ20: =IF($A20="","",IF(2045<$E20,"",IF($D20="Manuell","",IF(2045>$E20+$F20,IF($D20="Fix",$G20,$G20*(1+$H20)^($F20)),IF($D20="Fix",$G20,$G20*(1+$H20)^(2045-$E20)))))) | AK20: =IF($A20="","",IF(2046<$E20,"",IF($D20="Manuell","",IF(2046>$E20+$F20,IF($D20="Fix",$G20,$G20*(1+$H20)^($F20)),IF($D20="Fix",$G20,$G20*(1+$H20)^(2046-$E20)))))) | AL20: =IF($A20="","",IF(2047<$E20,"",IF($D20="Manuell","",IF(2047>$E20+$F20,IF($D20="Fix",$G20,$G20*(1+$H20)^($F20)),IF($D20="Fix",$G20,$G20*(1+$H20)^(2047-$E20)))))) | AM20: =IF($A20="","",IF(2048<$E20,"",IF($D20="Manuell","",IF(2048>$E20+$F20,IF($D20="Fix",$G20,$G20*(1+$H20)^($F20)),IF($D20="Fix",$G20,$G20*(1+$H20)^(2048-$E20)))))) | AN20: =IF($A20="","",IF(2049<$E20,"",IF($D20="Manuell","",IF(2049>$E20+$F20,IF($D20="Fix",$G20,$G20*(1+$H20)^($F20)),IF($D20="Fix",$G20,$G20*(1+$H20)^(2049-$E20)))))) | AO20: =IF($A20="","",IF(2050<$E20,"",IF($D20="Manuell","",IF(2050>$E20+$F20,IF($D20="Fix",$G20,$G20*(1+$H20)^($F20)),IF($D20="Fix",$G20,$G20*(1+$H20)^(2050-$E20)))))) | AP20: =IF($A20="","",IF(2051<$E20,"",IF($D20="Manuell","",IF(2051>$E20+$F20,IF($D20="Fix",$G20,$G20*(1+$H20)^($F20)),IF($D20="Fix",$G20,$G20*(1+$H20)^(2051-$E20)))))) | AQ20: =IF($A20="","",IF(2052<$E20,"",IF($D20="Manuell","",IF(2052>$E20+$F20,IF($D20="Fix",$G20,$G20*(1+$H20)^($F20)),IF($D20="Fix",$G20,$G20*(1+$H20)^(2052-$E20)))))) | AR20: =IF($A20="","",IF(2053<$E20,"",IF($D20="Manuell","",IF(2053>$E20+$F20,IF($D20="Fix",$G20,$G20*(1+$H20)^($F20)),IF($D20="Fix",$G20,$G20*(1+$H20)^(2053-$E20)))))) | AS20: =IF($A20="","",IF(2054<$E20,"",IF($D20="Manuell","",IF(2054>$E20+$F20,IF($D20="Fix",$G20,$G20*(1+$H20)^($F20)),IF($D20="Fix",$G20,$G20*(1+$H20)^(2054-$E20)))))) | AT20: =IF($A20="","",IF(2055<$E20,"",IF($D20="Manuell","",IF(2055>$E20+$F20,IF($D20="Fix",$G20,$G20*(1+$H20)^($F20)),IF($D20="Fix",$G20,$G20*(1+$H20)^(2055-$E20))))))
I21: =IF($A21="","",IF(2018<$E21,"",IF($D21="Manuell","",IF(2018>$E21+$F21,IF($D21="Fix",$G21,$G21*(1+$H21)^($F21)),IF($D21="Fix",$G21,$G21*(1+$H21)^(2018-$E21)))))) | J21: =IF($A21="","",IF(2019<$E21,"",IF($D21="Manuell","",IF(2019>$E21+$F21,IF($D21="Fix",$G21,$G21*(1+$H21)^($F21)),IF($D21="Fix",$G21,$G21*(1+$H21)^(2019-$E21)))))) | K21: =IF($A21="","",IF(2020<$E21,"",IF($D21="Manuell","",IF(2020>$E21+$F21,IF($D21="Fix",$G21,$G21*(1+$H21)^($F21)),IF($D21="Fix",$G21,$G21*(1+$H21)^(2020-$E21)))))) | L21: =IF($A21="","",IF(2021<$E21,"",IF($D21="Manuell","",IF(2021>$E21+$F21,IF($D21="Fix",$G21,$G21*(1+$H21)^($F21)),IF($D21="Fix",$G21,$G21*(1+$H21)^(2021-$E21)))))) | M21: =IF($A21="","",IF(2022<$E21,"",IF($D21="Manuell","",IF(2022>$E21+$F21,IF($D21="Fix",$G21,$G21*(1+$H21)^($F21)),IF($D21="Fix",$G21,$G21*(1+$H21)^(2022-$E21)))))) | N21: =IF($A21="","",IF(2023<$E21,"",IF($D21="Manuell","",IF(2023>$E21+$F21,IF($D21="Fix",$G21,$G21*(1+$H21)^($F21)),IF($D21="Fix",$G21,$G21*(1+$H21)^(2023-$E21)))))) | O21: =IF($A21="","",IF(2024<$E21,"",IF($D21="Manuell","",IF(2024>$E21+$F21,IF($D21="Fix",$G21,$G21*(1+$H21)^($F21)),IF($D21="Fix",$G21,$G21*(1+$H21)^(2024-$E21)))))) | P21: =IF($A21="","",IF(2025<$E21,"",IF($D21="Manuell","",IF(2025>$E21+$F21,IF($D21="Fix",$G21,$G21*(1+$H21)^($F21)),IF($D21="Fix",$G21,$G21*(1+$H21)^(2025-$E21)))))) | Q21: =IF($A21="","",IF(2026<$E21,"",IF($D21="Manuell","",IF(2026>$E21+$F21,IF($D21="Fix",$G21,$G21*(1+$H21)^($F21)),IF($D21="Fix",$G21,$G21*(1+$H21)^(2026-$E21)))))) | R21: =IF($A21="","",IF(2027<$E21,"",IF($D21="Manuell","",IF(2027>$E21+$F21,IF($D21="Fix",$G21,$G21*(1+$H21)^($F21)),IF($D21="Fix",$G21,$G21*(1+$H21)^(2027-$E21)))))) | S21: =IF($A21="","",IF(2028<$E21,"",IF($D21="Manuell","",IF(2028>$E21+$F21,IF($D21="Fix",$G21,$G21*(1+$H21)^($F21)),IF($D21="Fix",$G21,$G21*(1+$H21)^(2028-$E21)))))) | T21: =IF($A21="","",IF(2029<$E21,"",IF($D21="Manuell","",IF(2029>$E21+$F21,IF($D21="Fix",$G21,$G21*(1+$H21)^($F21)),IF($D21="Fix",$G21,$G21*(1+$H21)^(2029-$E21)))))) | U21: =IF($A21="","",IF(2030<$E21,"",IF($D21="Manuell","",IF(2030>$E21+$F21,IF($D21="Fix",$G21,$G21*(1+$H21)^($F21)),IF($D21="Fix",$G21,$G21*(1+$H21)^(2030-$E21)))))) | V21: =IF($A21="","",IF(2031<$E21,"",IF($D21="Manuell","",IF(2031>$E21+$F21,IF($D21="Fix",$G21,$G21*(1+$H21)^($F21)),IF($D21="Fix",$G21,$G21*(1+$H21)^(2031-$E21)))))) | W21: =IF($A21="","",IF(2032<$E21,"",IF($D21="Manuell","",IF(2032>$E21+$F21,IF($D21="Fix",$G21,$G21*(1+$H21)^($F21)),IF($D21="Fix",$G21,$G21*(1+$H21)^(2032-$E21)))))) | X21: =IF($A21="","",IF(2033<$E21,"",IF($D21="Manuell","",IF(2033>$E21+$F21,IF($D21="Fix",$G21,$G21*(1+$H21)^($F21)),IF($D21="Fix",$G21,$G21*(1+$H21)^(2033-$E21)))))) | Y21: =IF($A21="","",IF(2034<$E21,"",IF($D21="Manuell","",IF(2034>$E21+$F21,IF($D21="Fix",$G21,$G21*(1+$H21)^($F21)),IF($D21="Fix",$G21,$G21*(1+$H21)^(2034-$E21)))))) | Z21: =IF($A21="","",IF(2035<$E21,"",IF($D21="Manuell","",IF(2035>$E21+$F21,IF($D21="Fix",$G21,$G21*(1+$H21)^($F21)),IF($D21="Fix",$G21,$G21*(1+$H21)^(2035-$E21)))))) | AA21: =IF($A21="","",IF(2036<$E21,"",IF($D21="Manuell","",IF(2036>$E21+$F21,IF($D21="Fix",$G21,$G21*(1+$H21)^($F21)),IF($D21="Fix",$G21,$G21*(1+$H21)^(2036-$E21)))))) | AB21: =IF($A21="","",IF(2037<$E21,"",IF($D21="Manuell","",IF(2037>$E21+$F21,IF($D21="Fix",$G21,$G21*(1+$H21)^($F21)),IF($D21="Fix",$G21,$G21*(1+$H21)^(2037-$E21)))))) | AC21: =IF($A21="","",IF(2038<$E21,"",IF($D21="Manuell","",IF(2038>$E21+$F21,IF($D21="Fix",$G21,$G21*(1+$H21)^($F21)),IF($D21="Fix",$G21,$G21*(1+$H21)^(2038-$E21)))))) | AD21: =IF($A21="","",IF(2039<$E21,"",IF($D21="Manuell","",IF(2039>$E21+$F21,IF($D21="Fix",$G21,$G21*(1+$H21)^($F21)),IF($D21="Fix",$G21,$G21*(1+$H21)^(2039-$E21)))))) | AE21: =IF($A21="","",IF(2040<$E21,"",IF($D21="Manuell","",IF(2040>$E21+$F21,IF($D21="Fix",$G21,$G21*(1+$H21)^($F21)),IF($D21="Fix",$G21,$G21*(1+$H21)^(2040-$E21)))))) | AF21: =IF($A21="","",IF(2041<$E21,"",IF($D21="Manuell","",IF(2041>$E21+$F21,IF($D21="Fix",$G21,$G21*(1+$H21)^($F21)),IF($D21="Fix",$G21,$G21*(1+$H21)^(2041-$E21)))))) | AG21: =IF($A21="","",IF(2042<$E21,"",IF($D21="Manuell","",IF(2042>$E21+$F21,IF($D21="Fix",$G21,$G21*(1+$H21)^($F21)),IF($D21="Fix",$G21,$G21*(1+$H21)^(2042-$E21)))))) | AH21: =IF($A21="","",IF(2043<$E21,"",IF($D21="Manuell","",IF(2043>$E21+$F21,IF($D21="Fix",$G21,$G21*(1+$H21)^($F21)),IF($D21="Fix",$G21,$G21*(1+$H21)^(2043-$E21)))))) | AI21: =IF($A21="","",IF(2044<$E21,"",IF($D21="Manuell","",IF(2044>$E21+$F21,IF($D21="Fix",$G21,$G21*(1+$H21)^($F21)),IF($D21="Fix",$G21,$G21*(1+$H21)^(2044-$E21)))))) | AJ21: =IF($A21="","",IF(2045<$E21,"",IF($D21="Manuell","",IF(2045>$E21+$F21,IF($D21="Fix",$G21,$G21*(1+$H21)^($F21)),IF($D21="Fix",$G21,$G21*(1+$H21)^(2045-$E21)))))) | AK21: =IF($A21="","",IF(2046<$E21,"",IF($D21="Manuell","",IF(2046>$E21+$F21,IF($D21="Fix",$G21,$G21*(1+$H21)^($F21)),IF($D21="Fix",$G21,$G21*(1+$H21)^(2046-$E21)))))) | AL21: =IF($A21="","",IF(2047<$E21,"",IF($D21="Manuell","",IF(2047>$E21+$F21,IF($D21="Fix",$G21,$G21*(1+$H21)^($F21)),IF($D21="Fix",$G21,$G21*(1+$H21)^(2047-$E21)))))) | AM21: =IF($A21="","",IF(2048<$E21,"",IF($D21="Manuell","",IF(2048>$E21+$F21,IF($D21="Fix",$G21,$G21*(1+$H21)^($F21)),IF($D21="Fix",$G21,$G21*(1+$H21)^(2048-$E21)))))) | AN21: =IF($A21="","",IF(2049<$E21,"",IF($D21="Manuell","",IF(2049>$E21+$F21,IF($D21="Fix",$G21,$G21*(1+$H21)^($F21)),IF($D21="Fix",$G21,$G21*(1+$H21)^(2049-$E21)))))) | AO21: =IF($A21="","",IF(2050<$E21,"",IF($D21="Manuell","",IF(2050>$E21+$F21,IF($D21="Fix",$G21,$G21*(1+$H21)^($F21)),IF($D21="Fix",$G21,$G21*(1+$H21)^(2050-$E21)))))) | AP21: =IF($A21="","",IF(2051<$E21,"",IF($D21="Manuell","",IF(2051>$E21+$F21,IF($D21="Fix",$G21,$G21*(1+$H21)^($F21)),IF($D21="Fix",$G21,$G21*(1+$H21)^(2051-$E21)))))) | AQ21: =IF($A21="","",IF(2052<$E21,"",IF($D21="Manuell","",IF(2052>$E21+$F21,IF($D21="Fix",$G21,$G21*(1+$H21)^($F21)),IF($D21="Fix",$G21,$G21*(1+$H21)^(2052-$E21)))))) | AR21: =IF($A21="","",IF(2053<$E21,"",IF($D21="Manuell","",IF(2053>$E21+$F21,IF($D21="Fix",$G21,$G21*(1+$H21)^($F21)),IF($D21="Fix",$G21,$G21*(1+$H21)^(2053-$E21)))))) | AS21: =IF($A21="","",IF(2054<$E21,"",IF($D21="Manuell","",IF(2054>$E21+$F21,IF($D21="Fix",$G21,$G21*(1+$H21)^($F21)),IF($D21="Fix",$G21,$G21*(1+$H21)^(2054-$E21)))))) | AT21: =IF($A21="","",IF(2055<$E21,"",IF($D21="Manuell","",IF(2055>$E21+$F21,IF($D21="Fix",$G21,$G21*(1+$H21)^($F21)),IF($D21="Fix",$G21,$G21*(1+$H21)^(2055-$E21))))))
... I103: =IF($A103="","",IF(2018<$E103,"",IF($D103="Manuell","",IF(2018>$E103+$F103,IF($D103="Fix",$G103,$G103*(1+$H103)^($F103)),IF($D103="Fix",$G103,$G103*(1+$H103)^(2018-$E103)))))) | J103: =IF($A103="","",IF(2019<$E103,"",IF($D103="Manuell","",IF(2019>$E103+$F103,IF($D103="Fix",$G103,$G103*(1+$H103)^($F103)),IF($D103="Fix",$G103,$G103*(1+$H103)^(2019-$E103)))))) | K103: =IF($A103="","",IF(2020<$E103,"",IF($D103="Manuell","",IF(2020>$E103+$F103,IF($D103="Fix",$G103,$G103*(1+$H103)^($F103)),IF($D103="Fix",$G103,$G103*(1+$H103)^(2020-$E103)))))) | L103: =IF($A103="","",IF(2021<$E103,"",IF($D103="Manuell","",IF(2021>$E103+$F103,IF($D103="Fix",$G103,$G103*(1+$H103)^($F103)),IF($D103="Fix",$G103,$G103*(1+$H103)^(2021-$E103)))))) | M103: =IF($A103="","",IF(2022<$E103,"",IF($D103="Manuell","",IF(2022>$E103+$F103,IF($D103="Fix",$G103,$G103*(1+$H103)^($F103)),IF($D103="Fix",$G103,$G103*(1+$H103)^(2022-$E103)))))) | N103: =IF($A103="","",IF(2023<$E103,"",IF($D103="Manuell","",IF(2023>$E103+$F103,IF($D103="Fix",$G103,$G103*(1+$H103)^($F103)),IF($D103="Fix",$G103,$G103*(1+$H103)^(2023-$E103)))))) | O103: =IF($A103="","",IF(2024<$E103,"",IF($D103="Manuell","",IF(2024>$E103+$F103,IF($D103="Fix",$G103,$G103*(1+$H103)^($F103)),IF($D103="Fix",$G103,$G103*(1+$H103)^(2024-$E103)))))) | P103: =IF($A103="","",IF(2025<$E103,"",IF($D103="Manuell","",IF(2025>$E103+$F103,IF($D103="Fix",$G103,$G103*(1+$H103)^($F103)),IF($D103="Fix",$G103,$G103*(1+$H103)^(2025-$E103)))))) | Q103: =IF($A103="","",IF(2026<$E103,"",IF($D103="Manuell","",IF(2026>$E103+$F103,IF($D103="Fix",$G103,$G103*(1+$H103)^($F103)),IF($D103="Fix",$G103,$G103*(1+$H103)^(2026-$E103)))))) | R103: =IF($A103="","",IF(2027<$E103,"",IF($D103="Manuell","",IF(2027>$E103+$F103,IF($D103="Fix",$G103,$G103*(1+$H103)^($F103)),IF($D103="Fix",$G103,$G103*(1+$H103)^(2027-$E103)))))) | S103: =IF($A103="","",IF(2028<$E103,"",IF($D103="Manuell","",IF(2028>$E103+$F103,IF($D103="Fix",$G103,$G103*(1+$H103)^($F103)),IF($D103="Fix",$G103,$G103*(1+$H103)^(2028-$E103)))))) | T103: =IF($A103="","",IF(2029<$E103,"",IF($D103="Manuell","",IF(2029>$E103+$F103,IF($D103="Fix",$G103,$G103*(1+$H103)^($F103)),IF($D103="Fix",$G103,$G103*(1+$H103)^(2029-$E103)))))) | U103: =IF($A103="","",IF(2030<$E103,"",IF($D103="Manuell","",IF(2030>$E103+$F103,IF($D103="Fix",$G103,$G103*(1+$H103)^($F103)),IF($D103="Fix",$G103,$G103*(1+$H103)^(2030-$E103)))))) | V103: =IF($A103="","",IF(2031<$E103,"",IF($D103="Manuell","",IF(2031>$E103+$F103,IF($D103="Fix",$G103,$G103*(1+$H103)^($F103)),IF($D103="Fix",$G103,$G103*(1+$H103)^(2031-$E103)))))) | W103: =IF($A103="","",IF(2032<$E103,"",IF($D103="Manuell","",IF(2032>$E103+$F103,IF($D103="Fix",$G103,$G103*(1+$H103)^($F103)),IF($D103="Fix",$G103,$G103*(1+$H103)^(2032-$E103)))))) | X103: =IF($A103="","",IF(2033<$E103,"",IF($D103="Manuell","",IF(2033>$E103+$F103,IF($D103="Fix",$G103,$G103*(1+$H103)^($F103)),IF($D103="Fix",$G103,$G103*(1+$H103)^(2033-$E103)))))) | Y103: =IF($A103="","",IF(2034<$E103,"",IF($D103="Manuell","",IF(2034>$E103+$F103,IF($D103="Fix",$G103,$G103*(1+$H103)^($F103)),IF($D103="Fix",$G103,$G103*(1+$H103)^(2034-$E103)))))) | Z103: =IF($A103="","",IF(2035<$E103,"",IF($D103="Manuell","",IF(2035>$E103+$F103,IF($D103="Fix",$G103,$G103*(1+$H103)^($F103)),IF($D103="Fix",$G103,$G103*(1+$H103)^(2035-$E103)))))) | AA103: =IF($A103="","",IF(2036<$E103,"",IF($D103="Manuell","",IF(2036>$E103+$F103,IF($D103="Fix",$G103,$G103*(1+$H103)^($F103)),IF($D103="Fix",$G103,$G103*(1+$H103)^(2036-$E103)))))) | AB103: =IF($A103="","",IF(2037<$E103,"",IF($D103="Manuell","",IF(2037>$E103+$F103,IF($D103="Fix",$G103,$G103*(1+$H103)^($F103)),IF($D103="Fix",$G103,$G103*(1+$H103)^(2037-$E103)))))) | AC103: =IF($A103="","",IF(2038<$E103,"",IF($D103="Manuell","",IF(2038>$E103+$F103,IF($D103="Fix",$G103,$G103*(1+$H103)^($F103)),IF($D103="Fix",$G103,$G103*(1+$H103)^(2038-$E103)))))) | AD103: =IF($A103="","",IF(2039<$E103,"",IF($D103="Manuell","",IF(2039>$E103+$F103,IF($D103="Fix",$G103,$G103*(1+$H103)^($F103)),IF($D103="Fix",$G103,$G103*(1+$H103)^(2039-$E103)))))) | AE103: =IF($A103="","",IF(2040<$E103,"",IF($D103="Manuell","",IF(2040>$E103+$F103,IF($D103="Fix",$G103,$G103*(1+$H103)^($F103)),IF($D103="Fix",$G103,$G103*(1+$H103)^(2040-$E103)))))) | AF103: =IF($A103="","",IF(2041<$E103,"",IF($D103="Manuell","",IF(2041>$E103+$F103,IF($D103="Fix",$G103,$G103*(1+$H103)^($F103)),IF($D103="Fix",$G103,$G103*(1+$H103)^(2041-$E103)))))) | AG103: =IF($A103="","",IF(2042<$E103,"",IF($D103="Manuell","",IF(2042>$E103+$F103,IF($D103="Fix",$G103,$G103*(1+$H103)^($F103)),IF($D103="Fix",$G103,$G103*(1+$H103)^(2042-$E103)))))) | AH103: =IF($A103="","",IF(2043<$E103,"",IF($D103="Manuell","",IF(2043>$E103+$F103,IF($D103="Fix",$G103,$G103*(1+$H103)^($F103)),IF($D103="Fix",$G103,$G103*(1+$H103)^(2043-$E103)))))) | AI103: =IF($A103="","",IF(2044<$E103,"",IF($D103="Manuell","",IF(2044>$E103+$F103,IF($D103="Fix",$G103,$G103*(1+$H103)^($F103)),IF($D103="Fix",$G103,$G103*(1+$H103)^(2044-$E103)))))) | AJ103: =IF($A103="","",IF(2045<$E103,"",IF($D103="Manuell","",IF(2045>$E103+$F103,IF($D103="Fix",$G103,$G103*(1+$H103)^($F103)),IF($D103="Fix",$G103,$G103*(1+$H103)^(2045-$E103)))))) | AK103: =IF($A103="","",IF(2046<$E103,"",IF($D103="Manuell","",IF(2046>$E103+$F103,IF($D103="Fix",$G103,$G103*(1+$H103)^($F103)),IF($D103="Fix",$G103,$G103*(1+$H103)^(2046-$E103)))))) | AL103: =IF($A103="","",IF(2047<$E103,"",IF($D103="Manuell","",IF(2047>$E103+$F103,IF($D103="Fix",$G103,$G103*(1+$H103)^($F103)),IF($D103="Fix",$G103,$G103*(1+$H103)^(2047-$E103)))))) | AM103: =IF($A103="","",IF(2048<$E103,"",IF($D103="Manuell","",IF(2048>$E103+$F103,IF($D103="Fix",$G103,$G103*(1+$H103)^($F103)),IF($D103="Fix",$G103,$G103*(1+$H103)^(2048-$E103)))))) | AN103: =IF($A103="","",IF(2049<$E103,"",IF($D103="Manuell","",IF(2049>$E103+$F103,IF($D103="Fix",$G103,$G103*(1+$H103)^($F103)),IF($D103="Fix",$G103,$G103*(1+$H103)^(2049-$E103)))))) | AO103: =IF($A103="","",IF(2050<$E103,"",IF($D103="Manuell","",IF(2050>$E103+$F103,IF($D103="Fix",$G103,$G103*(1+$H103)^($F103)),IF($D103="Fix",$G103,$G103*(1+$H103)^(2050-$E103)))))) | AP103: =IF($A103="","",IF(2051<$E103,"",IF($D103="Manuell","",IF(2051>$E103+$F103,IF($D103="Fix",$G103,$G103*(1+$H103)^($F103)),IF($D103="Fix",$G103,$G103*(1+$H103)^(2051-$E103)))))) | AQ103: =IF($A103="","",IF(2052<$E103,"",IF($D103="Manuell","",IF(2052>$E103+$F103,IF($D103="Fix",$G103,$G103*(1+$H103)^($F103)),IF($D103="Fix",$G103,$G103*(1+$H103)^(2052-$E103)))))) | AR103: =IF($A103="","",IF(2053<$E103,"",IF($D103="Manuell","",IF(2053>$E103+$F103,IF($D103="Fix",$G103,$G103*(1+$H103)^($F103)),IF($D103="Fix",$G103,$G103*(1+$H103)^(2053-$E103)))))) | AS103: =IF($A103="","",IF(2054<$E103,"",IF($D103="Manuell","",IF(2054>$E103+$F103,IF($D103="Fix",$G103,$G103*(1+$H103)^($F103)),IF($D103="Fix",$G103,$G103*(1+$H103)^(2054-$E103)))))) | AT103: =IF($A103="","",IF(2055<$E103,"",IF($D103="Manuell","",IF(2055>$E103+$F103,IF($D103="Fix",$G103,$G103*(1+$H103)^($F103)),IF($D103="Fix",$G103,$G103*(1+$H103)^(2055-$E103))))))

Sheet Actions
A1: ID | B1: Action Name | C1: Beschreibung | D1: Verantwortlich | E1: Startdatum | F1: Zieldatum (Go-Live) | G1: NH KPI | H1: KPI Einheit | I1: KPI Baseline p.a. | J1: Impact Typ | K1: Impact Wert | L1: Monetarisierung Fix €/Einheit | M1: Monetarisierungs-Variable | N1: Abschreibungsdauer (Jahre) | O1: CAPEX Equipment | P1: CAPEX Installation | Q1: CAPEX Software | R1: CAPEX Beratung | S1: CAPEX Sonstiges | T1: CAPEX Total | U1: OPEX Wartung | V1: OPEX Lizenzen | W1: OPEX Personal | X1: OPEX Sonstiges | Y1: OPEX Total | Z1: Sonst. Nutzen € p.a. | AA1: Sonst. Kosten € p.a. | AB1: Warum/Wieso (Begründung) | AC1: Notizen/Annahmen
A2: A001 | B2: LED-Umrüstung | C2: Austausch Beleuchtung auf LED | D2: Owner A | E2: 46054 | F2: 46174 | G2: Energieverbrauch | H2: kWh | I2: 120000 | J2: % | K2: 0.15 | L2: 0.25 | M2: Strompreis | N2: 7 | O2: 15000 | P2: 2000 | Q2: 0 | R2: 0 | S2: 1000 | T2: =SUM(O2:S2) | U2: 200 | V2: 0 | W2: 300 | X2: 0 | Y2: =SUM(U2:X2) | Z2: 0 | AA2: 0 | AB2: Reduktion Strombedarf durch effizientere Beleuchtung.
A3: A002 | B3: Druckluft-Leckagen reduzieren | C3: Leckage-Programm und Monitoring | D3: Owner B | E3: 46023 | F3: 46113 | G3: Energieverbrauch | H3: kWh | I3: 80000 | J3: % | K3: 0.08 | L3: 0.25 | M3: Strompreis | N3: 3 | O3: 2000 | P3: 500 | Q3: 2000 | R3: 0 | S3: 0 | T3: =SUM(O3:S3) | U3: 150 | V3: 500 | W3: 200 | X3: 0 | Y3: =SUM(U3:X3) | Z3: 0 | AA3: 0 | AB3: Schnelle Effizienzgewinne, geringe Investition.
A4: A003 | B4: BMS Optimierung | C4: Gebäudeleittechnik optimieren | D4: Owner C | E4: 46082 | F4: 46296 | G4: Energieverbrauch | H4: kWh | I4: 250000 | J4: % | K4: 0.05 | L4: 0.25 | M4: Strompreis | N4: 5 | O4: 0 | P4: 0 | Q4: 15000 | R4: 0 | S4: 0 | T4: =SUM(O4:S4) | U4: 500 | V4: 3000 | W4: 5000 | X4: 0 | Y4: =SUM(U4:X4) | Z4: 0 | AA4: 0 | AB4: Reduziert Lastspitzen und Grundlast.
A5: A004 | B5: Wärmerückgewinnung | C5: Abwärme nutzen, Gasbedarf senken | D5: Owner D | E5: 46388 | F5: 46722 | G5: Gasverbrauch | H5: kWh | I5: 500000 | J5: % | K5: 0.12 | L5: 0.09 | M5: Gaspreis | N5: 10 | O5: 60000 | P5: 15000 | Q5: 0 | R5: 5000 | S5: 0 | T5: =SUM(O5:S5) | U5: 1500 | V5: 0 | W5: 1500 | X5: 0 | Y5: =SUM(U5:X5) | Z5: 0 | AA5: 0 | AB5: Energieeffizienz, mittlere Komplexität.
A6: A005 | B6: Fuhrpark optimieren | C6: Dieselverbrauch senken durch Fahrtraining | D6: Owner E | E6: 46539 | F6: 46661 | G6: Dieselverbrauch | H6: L | I6: 60000 | J6: % | K6: 0.08 | L6: 1.6 | M6: Dieselpreis | N6: 1 | O6: 2000 | P6: 0 | Q6: 0 | R6: 0 | S6: 0 | T6: =SUM(O6:S6) | U6: 500 | V6: 0 | W6: 500 | X6: 0 | Y6: =SUM(U6:X6) | Z6: 0 | AA6: 0 | AB6: Geringe CAPEX, schneller Effekt.
A7: A006 | B7: PV Dachanlage | C7: Eigenstrom erzeugen, Netzbezug reduzieren | D7: Owner F | E7: 46753 | F7: 46997 | G7: Energieverbrauch | H7: kWh | J7: absolut | K7: 180000 | L7: 0.25 | M7: Strompreis | N7: 20 | O7: 220000 | P7: 20000 | Q7: 0 | R7: 0 | S7: 10000 | T7: =SUM(O7:S7) | U7: 3000 | V7: 0 | W7: 0 | X7: 0 | Y7: =SUM(U7:X7) | Z7: 0 | AA7: 0 | AB7: Langfristige Einsparungen.
A8: A007 | B8: Verpackung reduzieren | C8: Materialeinsatz senken, Re-Design | D8: Owner G | E8: 46143 | F8: 46327 | G8: Plastikverbrauch | H8: kg | I8: 40000 | J8: % | K8: 0.2 | L8: 1.8 | M8: Plastikpreis | N8: 2 | O8: 0 | P8: 0 | Q8: 5000 | R8: 0 | S8: 0 | T8: =SUM(O8:S8) | U8: 0 | V8: 0 | W8: 2000 | X8: 0 | Y8: =SUM(U8:X8) | Z8: 0 | AA8: 0 | AB8: Kosten und Materialeinsatz reduzieren.
A9: A008 | B9: Abfalltrennung verbessern | C9: Restmüll reduzieren, bessere Sortierung | D9: Owner H | E9: 46113 | F9: 46388 | G9: Abfallmenge | H9: t | I9: 800 | J9: % | K9: 0.15 | L9: 150 | M9: Entsorgungspreis | N9: 3 | O9: 3000 | P9: 0 | Q9: 2000 | R9: 0 | S9: 0 | T9: =SUM(O9:S9) | U9: 500 | V9: 0 | W9: 500 | X9: 0 | Y9: =SUM(U9:X9) | Z9: 0 | AA9: 0 | AB9: Laufende Einsparung bei Entsorgung.
A10: A009 | B10: Wassereffizienz | C10: Armaturen und Prozesse optimieren | D10: Owner I | E10: 46419 | F10: 46600 | G10: Wasserverbrauch | H10: m3 | I10: 20000 | J10: % | K10: 0.1 | L10: 2.5 | M10: Wasserpreis | N10: 5 | O10: 8000 | P10: 2000 | Q10: 0 | R10: 0 | S10: 0 | T10: =SUM(O10:S10) | U10: 200 | V10: 0 | W10: 300 | X10: 0 | Y10: =SUM(U10:X10) | Z10: 0 | AA10: 0 | AB10: Reduziert Wasserbedarf.
A11: A010 | B11: Prozessoptimierung Produktion | C11: Energieeffizienz, Start 2029, Go-Live 2030 | D11: Owner J | E11: 47119 | F11: 47543 | G11: Energieverbrauch | H11: kWh | I11: 600000 | J11: % | K11: 0.06 | L11: 0.25 | M11: Strompreis | N11: 8 | O11: 40000 | P11: 10000 | Q11: 15000 | R11: 0 | S11: 0 | T11: =SUM(O11:S11) | U11: 1500 | V11: 0 | W11: 2000 | X11: 0 | Y11: =SUM(U11:X11) | Z11: 0 | AA11: 0 | AB11: Test für spätere Startjahre, nutzt 2030er Preise.
T12: =SUM(O12:S12) | Y12: =SUM(U12:X12)
T13: =SUM(O13:S13) | Y13: =SUM(U13:X13)
T14: =SUM(O14:S14) | Y14: =SUM(U14:X14)
T15: =SUM(O15:S15) | Y15: =SUM(U15:X15)
T16: =SUM(O16:S16) | Y16: =SUM(U16:X16)
T17: =SUM(O17:S17) | Y17: =SUM(U17:X17)
T18: =SUM(O18:S18) | Y18: =SUM(U18:X18)
T19: =SUM(O19:S19) | Y19: =SUM(U19:X19)
T20: =SUM(O20:S20) | Y20: =SUM(U20:X20)
T21: =SUM(O21:S21) | Y21: =SUM(U21:X21)
T22: =SUM(O22:S22) | Y22: =SUM(U22:X22)
T23: =SUM(O23:S23) | Y23: =SUM(U23:X23)
... T201: =SUM(O201:S201) | Y201: =SUM(U201:X201)

Sheet Helper
A1: KPI_Liste (Spill)
A2: =SORT(UNIQUE(FILTER(Actions!G2:G201,Actions!G2:G201<>"")))

Sheet Action_Rechner
A1: Action-Rechner (Detailansicht)
A2: Tipp: Wähle eine Action-ID. Eingaben stehen im Blatt Actions. Variablen werden je Kalenderjahr gematcht.
A3: Action auswählen (ID)
A5: Stammdaten & Annahmen
A6: Action Name | B6: =IFERROR(INDEX(Actions!$B:$B, MATCH($B$3, Actions!$A:$A, 0)), "")
A7: Beschreibung | B7: =IFERROR(INDEX(Actions!$C:$C, MATCH($B$3, Actions!$A:$A, 0)), "")
A8: Verantwortlich | B8: =IFERROR(INDEX(Actions!$D:$D, MATCH($B$3, Actions!$A:$A, 0)), "")
A9: Startdatum | B9: =IFERROR(INDEX(Actions!$E:$E, MATCH($B$3, Actions!$A:$A, 0)), "")
A10: Zieldatum (Go-Live) | B10: =IFERROR(INDEX(Actions!$F:$F, MATCH($B$3, Actions!$A:$A, 0)), "")
A11: NH KPI | B11: =IFERROR(INDEX(Actions!$G:$G, MATCH($B$3, Actions!$A:$A, 0)), "")
A12: KPI Einheit | B12: =IFERROR(INDEX(Actions!$H:$H, MATCH($B$3, Actions!$A:$A, 0)), "")
A13: KPI Baseline p.a. | B13: =IFERROR(INDEX(Actions!$I:$I, MATCH($B$3, Actions!$A:$A, 0)), "")
A14: Impact Typ | B14: =IFERROR(INDEX(Actions!$J:$J, MATCH($B$3, Actions!$A:$A, 0)), "")
A15: Impact Wert | B15: =IFERROR(INDEX(Actions!$K:$K, MATCH($B$3, Actions!$A:$A, 0)), "")
A16: Monetarisierung Fix €/Einheit | B16: =IFERROR(INDEX(Actions!$L:$L, MATCH($B$3, Actions!$A:$A, 0)), "")
A17: Monetarisierungs-Variable | B17: =IFERROR(INDEX(Actions!$M:$M, MATCH($B$3, Actions!$A:$A, 0)), "")
A18: Abschreibungsdauer (Jahre) | B18: =IFERROR(INDEX(Actions!$N:$N, MATCH($B$3, Actions!$A:$A, 0)), "")
A19: CAPEX Total | B19: =IFERROR(INDEX(Actions!$T:$T, MATCH($B$3, Actions!$A:$A, 0)), "") | D19: Sonst. Nutzen € p.a. | E19: =IFERROR(INDEX(Actions!$Z:$Z, MATCH($B$3, Actions!$A:$A, 0)), "")
A20: OPEX Total | B20: =IFERROR(INDEX(Actions!$Y:$Y, MATCH($B$3, Actions!$A:$A, 0)), "") | D20: Sonst. Kosten € p.a. | E20: =IFERROR(INDEX(Actions!$AA:$AA, MATCH($B$3, Actions!$A:$A, 0)), "")
A22: Berechnungen
A24: KPI-Reduktion p.a. (Einheiten) | B24: =IF($B$14="%", $B$13*$B$15, $B$15) | C24: =B12
A25: Diskontsatz | B25: =DiscountRate
A26: TaxRate | B26: =TaxRate
A27: Horizont (Jahre) | B27: =HorizonYears
A30: Jahr-Index | B30: Kalenderjahr | C30: Faktor Go-Live | D30: €/Einheit (fix oder Variable) | E30: Nutzen (€) | F30: OPEX (€) | G30: Abschreibung (€) | H30: EBIT (€) | I30: Steuern (€) | J30: Netto CF Nachsteuer (€) | K30: Kum. CF Nachsteuer (€) | L30: Diskontfaktor | M30: Disk. CF Nachsteuer (€) | N30: Kum. disk. CF Nachsteuer (€)
A31: 0 | B31: =IF($B$9="","",YEAR($B$9)+A31) | C31: =IF(B31="","",IF(B31<YEAR($B$10),0,IF(B31>YEAR($B$10),1,(12-MONTH($B$10)+1)/12))) | D31: =IF($B$17="",$B$16,IFERROR(IF(INDEX(Variablen!$I:$AT, MATCH($B$17, Variablen!$A:$A, 0), MATCH(B31, Variablen!$I$3:$AT$3, 0))="",$B$16,INDEX(Variablen!$I:$AT, MATCH($B$17, Variablen!$A:$A, 0), MATCH(B31, Variablen!$I$3:$AT$3, 0))),$B$16)) | E31: =$B$24*D31*C31 + $E$19*C31 | F31: =$B$20*C31 + $E$20*C31 | G31: =IF(OR($B$18="",$B$18<=0),0,($B$19/$B$18)*(IF(OR($B$18="",$B$18<=0),0,IF(B31<YEAR($B$10),0,IF(B31>=YEAR($B$10)+$B$18,0,IF(B31=YEAR($B$10),(12-MONTH($B$10)+1)/12,1)))))) | H31: =E31-F31-G31 | I31: =IF(H31>0,H31*$B$26,0) | J31: =E31-F31-I31-IF(A31=0,$B$19,0) | K31: =J31 | L31: =1/(1+$B$25)^(A31) | M31: =J31*L31 | N31: =M31
A32: 1 | B32: =IF($B$9="","",YEAR($B$9)+A32) | C32: =IF(B32="","",IF(B32<YEAR($B$10),0,IF(B32>YEAR($B$10),1,(12-MONTH($B$10)+1)/12))) | D32: =IF($B$17="",$B$16,IFERROR(IF(INDEX(Variablen!$I:$AT, MATCH($B$17, Variablen!$A:$A, 0), MATCH(B32, Variablen!$I$3:$AT$3, 0))="",$B$16,INDEX(Variablen!$I:$AT, MATCH($B$17, Variablen!$A:$A, 0), MATCH(B32, Variablen!$I$3:$AT$3, 0))),$B$16)) | E32: =$B$24*D32*C32 + $E$19*C32 | F32: =$B$20*C32 + $E$20*C32 | G32: =IF(OR($B$18="",$B$18<=0),0,($B$19/$B$18)*(IF(OR($B$18="",$B$18<=0),0,IF(B32<YEAR($B$10),0,IF(B32>=YEAR($B$10)+$B$18,0,IF(B32=YEAR($B$10),(12-MONTH($B$10)+1)/12,1)))))) | H32: =E32-F32-G32 | I32: =IF(H32>0,H32*$B$26,0) | J32: =E32-F32-I32-IF(A32=0,$B$19,0) | K32: =K31+J32 | L32: =1/(1+$B$25)^(A32) | M32: =J32*L32 | N32: =N31+M32
A33: 2 | B33: =IF($B$9="","",YEAR($B$9)+A33) | C33: =IF(B33="","",IF(B33<YEAR($B$10),0,IF(B33>YEAR($B$10),1,(12-MONTH($B$10)+1)/12))) | D33: =IF($B$17="",$B$16,IFERROR(IF(INDEX(Variablen!$I:$AT, MATCH($B$17, Variablen!$A:$A, 0), MATCH(B33, Variablen!$I$3:$AT$3, 0))="",$B$16,INDEX(Variablen!$I:$AT, MATCH($B$17, Variablen!$A:$A, 0), MATCH(B33, Variablen!$I$3:$AT$3, 0))),$B$16)) | E33: =$B$24*D33*C33 + $E$19*C33 | F33: =$B$20*C33 + $E$20*C33 | G33: =IF(OR($B$18="",$B$18<=0),0,($B$19/$B$18)*(IF(OR($B$18="",$B$18<=0),0,IF(B33<YEAR($B$10),0,IF(B33>=YEAR($B$10)+$B$18,0,IF(B33=YEAR($B$10),(12-MONTH($B$10)+1)/12,1)))))) | H33: =E33-F33-G33 | I33: =IF(H33>0,H33*$B$26,0) | J33: =E33-F33-I33-IF(A33=0,$B$19,0) | K33: =K32+J33 | L33: =1/(1+$B$25)^(A33) | M33: =J33*L33 | N33: =N32+M33
A34: 3 | B34: =IF($B$9="","",YEAR($B$9)+A34) | C34: =IF(B34="","",IF(B34<YEAR($B$10),0,IF(B34>YEAR($B$10),1,(12-MONTH($B$10)+1)/12))) | D34: =IF($B$17="",$B$16,IFERROR(IF(INDEX(Variablen!$I:$AT, MATCH($B$17, Variablen!$A:$A, 0), MATCH(B34, Variablen!$I$3:$AT$3, 0))="",$B$16,INDEX(Variablen!$I:$AT, MATCH($B$17, Variablen!$A:$A, 0), MATCH(B34, Variablen!$I$3:$AT$3, 0))),$B$16)) | E34: =$B$24*D34*C34 + $E$19*C34 | F34: =$B$20*C34 + $E$20*C34 | G34: =IF(OR($B$18="",$B$18<=0),0,($B$19/$B$18)*(IF(OR($B$18="",$B$18<=0),0,IF(B34<YEAR($B$10),0,IF(B34>=YEAR($B$10)+$B$18,0,IF(B34=YEAR($B$10),(12-MONTH($B$10)+1)/12,1)))))) | H34: =E34-F34-G34 | I34: =IF(H34>0,H34*$B$26,0) | J34: =E34-F34-I34-IF(A34=0,$B$19,0) | K34: =K33+J34 | L34: =1/(1+$B$25)^(A34) | M34: =J34*L34 | N34: =N33+M34
A35: 4 | B35: =IF($B$9="","",YEAR($B$9)+A35) | C35: =IF(B35="","",IF(B35<YEAR($B$10),0,IF(B35>YEAR($B$10),1,(12-MONTH($B$10)+1)/12))) | D35: =IF($B$17="",$B$16,IFERROR(IF(INDEX(Variablen!$I:$AT, MATCH($B$17, Variablen!$A:$A, 0), MATCH(B35, Variablen!$I$3:$AT$3, 0))="",$B$16,INDEX(Variablen!$I:$AT, MATCH($B$17, Variablen!$A:$A, 0), MATCH(B35, Variablen!$I$3:$AT$3, 0))),$B$16)) | E35: =$B$24*D35*C35 + $E$19*C35 | F35: =$B$20*C35 + $E$20*C35 | G35: =IF(OR($B$18="",$B$18<=0),0,($B$19/$B$18)*(IF(OR($B$18="",$B$18<=0),0,IF(B35<YEAR($B$10),0,IF(B35>=YEAR($B$10)+$B$18,0,IF(B35=YEAR($B$10),(12-MONTH($B$10)+1)/12,1)))))) | H35: =E35-F35-G35 | I35: =IF(H35>0,H35*$B$26,0) | J35: =E35-F35-I35-IF(A35=0,$B$19,0) | K35: =K34+J35 | L35: =1/(1+$B$25)^(A35) | M35: =J35*L35 | N35: =N34+M35
A36: 5 | B36: =IF($B$9="","",YEAR($B$9)+A36) | C36: =IF(B36="","",IF(B36<YEAR($B$10),0,IF(B36>YEAR($B$10),1,(12-MONTH($B$10)+1)/12))) | D36: =IF($B$17="",$B$16,IFERROR(IF(INDEX(Variablen!$I:$AT, MATCH($B$17, Variablen!$A:$A, 0), MATCH(B36, Variablen!$I$3:$AT$3, 0))="",$B$16,INDEX(Variablen!$I:$AT, MATCH($B$17, Variablen!$A:$A, 0), MATCH(B36, Variablen!$I$3:$AT$3, 0))),$B$16)) | E36: =$B$24*D36*C36 + $E$19*C36 | F36: =$B$20*C36 + $E$20*C36 | G36: =IF(OR($B$18="",$B$18<=0),0,($B$19/$B$18)*(IF(OR($B$18="",$B$18<=0),0,IF(B36<YEAR($B$10),0,IF(B36>=YEAR($B$10)+$B$18,0,IF(B36=YEAR($B$10),(12-MONTH($B$10)+1)/12,1)))))) | H36: =E36-F36-G36 | I36: =IF(H36>0,H36*$B$26,0) | J36: =E36-F36-I36-IF(A36=0,$B$19,0) | K36: =K35+J36 | L36: =1/(1+$B$25)^(A36) | M36: =J36*L36 | N36: =N35+M36
A37: 6 | B37: =IF($B$9="","",YEAR($B$9)+A37) | C37: =IF(B37="","",IF(B37<YEAR($B$10),0,IF(B37>YEAR($B$10),1,(12-MONTH($B$10)+1)/12))) | D37: =IF($B$17="",$B$16,IFERROR(IF(INDEX(Variablen!$I:$AT, MATCH($B$17, Variablen!$A:$A, 0), MATCH(B37, Variablen!$I$3:$AT$3, 0))="",$B$16,INDEX(Variablen!$I:$AT, MATCH($B$17, Variablen!$A:$A, 0), MATCH(B37, Variablen!$I$3:$AT$3, 0))),$B$16)) | E37: =$B$24*D37*C37 + $E$19*C37 | F37: =$B$20*C37 + $E$20*C37 | G37: =IF(OR($B$18="",$B$18<=0),0,($B$19/$B$18)*(IF(OR($B$18="",$B$18<=0),0,IF(B37<YEAR($B$10),0,IF(B37>=YEAR($B$10)+$B$18,0,IF(B37=YEAR($B$10),(12-MONTH($B$10)+1)/12,1)))))) | H37: =E37-F37-G37 | I37: =IF(H37>0,H37*$B$26,0) | J37: =E37-F37-I37-IF(A37=0,$B$19,0) | K37: =K36+J37 | L37: =1/(1+$B$25)^(A37) | M37: =J37*L37 | N37: =N36+M37
A38: 7 | B38: =IF($B$9="","",YEAR($B$9)+A38) | C38: =IF(B38="","",IF(B38<YEAR($B$10),0,IF(B38>YEAR($B$10),1,(12-MONTH($B$10)+1)/12))) | D38: =IF($B$17="",$B$16,IFERROR(IF(INDEX(Variablen!$I:$AT, MATCH($B$17, Variablen!$A:$A, 0), MATCH(B38, Variablen!$I$3:$AT$3, 0))="",$B$16,INDEX(Variablen!$I:$AT, MATCH($B$17, Variablen!$A:$A, 0), MATCH(B38, Variablen!$I$3:$AT$3, 0))),$B$16)) | E38: =$B$24*D38*C38 + $E$19*C38 | F38: =$B$20*C38 + $E$20*C38 | G38: =IF(OR($B$18="",$B$18<=0),0,($B$19/$B$18)*(IF(OR($B$18="",$B$18<=0),0,IF(B38<YEAR($B$10),0,IF(B38>=YEAR($B$10)+$B$18,0,IF(B38=YEAR($B$10),(12-MONTH($B$10)+1)/12,1)))))) | H38: =E38-F38-G38 | I38: =IF(H38>0,H38*$B$26,0) | J38: =E38-F38-I38-IF(A38=0,$B$19,0) | K38: =K37+J38 | L38: =1/(1+$B$25)^(A38) | M38: =J38*L38 | N38: =N37+M38
A39: 8 | B39: =IF($B$9="","",YEAR($B$9)+A39) | C39: =IF(B39="","",IF(B39<YEAR($B$10),0,IF(B39>YEAR($B$10),1,(12-MONTH($B$10)+1)/12))) | D39: =IF($B$17="",$B$16,IFERROR(IF(INDEX(Variablen!$I:$AT, MATCH($B$17, Variablen!$A:$A, 0), MATCH(B39, Variablen!$I$3:$AT$3, 0))="",$B$16,INDEX(Variablen!$I:$AT, MATCH($B$17, Variablen!$A:$A, 0), MATCH(B39, Variablen!$I$3:$AT$3, 0))),$B$16)) | E39: =$B$24*D39*C39 + $E$19*C39 | F39: =$B$20*C39 + $E$20*C39 | G39: =IF(OR($B$18="",$B$18<=0),0,($B$19/$B$18)*(IF(OR($B$18="",$B$18<=0),0,IF(B39<YEAR($B$10),0,IF(B39>=YEAR($B$10)+$B$18,0,IF(B39=YEAR($B$10),(12-MONTH($B$10)+1)/12,1)))))) | H39: =E39-F39-G39 | I39: =IF(H39>0,H39*$B$26,0) | J39: =E39-F39-I39-IF(A39=0,$B$19,0) | K39: =K38+J39 | L39: =1/(1+$B$25)^(A39) | M39: =J39*L39 | N39: =N38+M39
A40: 9 | B40: =IF($B$9="","",YEAR($B$9)+A40) | C40: =IF(B40="","",IF(B40<YEAR($B$10),0,IF(B40>YEAR($B$10),1,(12-MONTH($B$10)+1)/12))) | D40: =IF($B$17="",$B$16,IFERROR(IF(INDEX(Variablen!$I:$AT, MATCH($B$17, Variablen!$A:$A, 0), MATCH(B40, Variablen!$I$3:$AT$3, 0))="",$B$16,INDEX(Variablen!$I:$AT, MATCH($B$17, Variablen!$A:$A, 0), MATCH(B40, Variablen!$I$3:$AT$3, 0))),$B$16)) | E40: =$B$24*D40*C40 + $E$19*C40 | F40: =$B$20*C40 + $E$20*C40 | G40: =IF(OR($B$18="",$B$18<=0),0,($B$19/$B$18)*(IF(OR($B$18="",$B$18<=0),0,IF(B40<YEAR($B$10),0,IF(B40>=YEAR($B$10)+$B$18,0,IF(B40=YEAR($B$10),(12-MONTH($B$10)+1)/12,1)))))) | H40: =E40-F40-G40 | I40: =IF(H40>0,H40*$B$26,0) | J40: =E40-F40-I40-IF(A40=0,$B$19,0) | K40: =K39+J40 | L40: =1/(1+$B$25)^(A40) | M40: =J40*L40 | N40: =N39+M40
A41: 10 | B41: =IF($B$9="","",YEAR($B$9)+A41) | C41: =IF(B41="","",IF(B41<YEAR($B$10),0,IF(B41>YEAR($B$10),1,(12-MONTH($B$10)+1)/12))) | D41: =IF($B$17="",$B$16,IFERROR(IF(INDEX(Variablen!$I:$AT, MATCH($B$17, Variablen!$A:$A, 0), MATCH(B41, Variablen!$I$3:$AT$3, 0))="",$B$16,INDEX(Variablen!$I:$AT, MATCH($B$17, Variablen!$A:$A, 0), MATCH(B41, Variablen!$I$3:$AT$3, 0))),$B$16)) | E41: =$B$24*D41*C41 + $E$19*C41 | F41: =$B$20*C41 + $E$20*C41 | G41: =IF(OR($B$18="",$B$18<=0),0,($B$19/$B$18)*(IF(OR($B$18="",$B$18<=0),0,IF(B41<YEAR($B$10),0,IF(B41>=YEAR($B$10)+$B$18,0,IF(B41=YEAR($B$10),(12-MONTH($B$10)+1)/12,1)))))) | H41: =E41-F41-G41 | I41: =IF(H41>0,H41*$B$26,0) | J41: =E41-F41-I41-IF(A41=0,$B$19,0) | K41: =K40+J41 | L41: =1/(1+$B$25)^(A41) | M41: =J41*L41 | N41: =N40+M41
A42: 11 | B42: =IF($B$9="","",YEAR($B$9)+A42) | C42: =IF(B42="","",IF(B42<YEAR($B$10),0,IF(B42>YEAR($B$10),1,(12-MONTH($B$10)+1)/12))) | D42: =IF($B$17="",$B$16,IFERROR(IF(INDEX(Variablen!$I:$AT, MATCH($B$17, Variablen!$A:$A, 0), MATCH(B42, Variablen!$I$3:$AT$3, 0))="",$B$16,INDEX(Variablen!$I:$AT, MATCH($B$17, Variablen!$A:$A, 0), MATCH(B42, Variablen!$I$3:$AT$3, 0))),$B$16)) | E42: =$B$24*D42*C42 + $E$19*C42 | F42: =$B$20*C42 + $E$20*C42 | G42: =IF(OR($B$18="",$B$18<=0),0,($B$19/$B$18)*(IF(OR($B$18="",$B$18<=0),0,IF(B42<YEAR($B$10),0,IF(B42>=YEAR($B$10)+$B$18,0,IF(B42=YEAR($B$10),(12-MONTH($B$10)+1)/12,1)))))) | H42: =E42-F42-G42 | I42: =IF(H42>0,H42*$B$26,0) | J42: =E42-F42-I42-IF(A42=0,$B$19,0) | K42: =K41+J42 | L42: =1/(1+$B$25)^(A42) | M42: =J42*L42 | N42: =N41+M42
A43: 12 | B43: =IF($B$9="","",YEAR($B$9)+A43) | C43: =IF(B43="","",IF(B43<YEAR($B$10),0,IF(B43>YEAR($B$10),1,(12-MONTH($B$10)+1)/12))) | D43: =IF($B$17="",$B$16,IFERROR(IF(INDEX(Variablen!$I:$AT, MATCH($B$17, Variablen!$A:$A, 0), MATCH(B43, Variablen!$I$3:$AT$3, 0))="",$B$16,INDEX(Variablen!$I:$AT, MATCH($B$17, Variablen!$A:$A, 0), MATCH(B43, Variablen!$I$3:$AT$3, 0))),$B$16)) | E43: =$B$24*D43*C43 + $E$19*C43 | F43: =$B$20*C43 + $E$20*C43 | G43: =IF(OR($B$18="",$B$18<=0),0,($B$19/$B$18)*(IF(OR($B$18="",$B$18<=0),0,IF(B43<YEAR($B$10),0,IF(B43>=YEAR($B$10)+$B$18,0,IF(B43=YEAR($B$10),(12-MONTH($B$10)+1)/12,1)))))) | H43: =E43-F43-G43 | I43: =IF(H43>0,H43*$B$26,0) | J43: =E43-F43-I43-IF(A43=0,$B$19,0) | K43: =K42+J43 | L43: =1/(1+$B$25)^(A43) | M43: =J43*L43 | N43: =N42+M43
... A51: 20 | B51: =IF($B$9="","",YEAR($B$9)+A51) | C51: =IF(B51="","",IF(B51<YEAR($B$10),0,IF(B51>YEAR($B$10),1,(12-MONTH($B$10)+1)/12))) | D51: =IF($B$17="",$B$16,IFERROR(IF(INDEX(Variablen!$I:$AT, MATCH($B$17, Variablen!$A:$A, 0), MATCH(B51, Variablen!$I$3:$AT$3, 0))="",$B$16,INDEX(Variablen!$I:$AT, MATCH($B$17, Variablen!$A:$A, 0), MATCH(B51, Variablen!$I$3:$AT$3, 0))),$B$16)) | E51: =$B$24*D51*C51 + $E$19*C51 | F51: =$B$20*C51 + $E$20*C51 | G51: =IF(OR($B$18="",$B$18<=0),0,($B$19/$B$18)*(IF(OR($B$18="",$B$18<=0),0,IF(B51<YEAR($B$10),0,IF(B51>=YEAR($B$10)+$B$18,0,IF(B51=YEAR($B$10),(12-MONTH($B$10)+1)/12,1)))))) | H51: =E51-F51-G51 | I51: =IF(H51>0,H51*$B$26,0) | J51: =E51-F51-I51-IF(A51=0,$B$19,0) | K51: =K50+J51 | L51: =1/(1+$B$25)^(A51) | M51: =J51*L51 | N51: =N50+M51
A53: Kennzahlen
A55: Kapitalwert (NPV) Nachsteuer € | B55: =SUM(OFFSET($M$31,0,0,MIN(HorizonYears,20)+1,1))
A56: IRR Nachsteuer | B56: =IFERROR(IRR(OFFSET($J$31,0,0,MIN(HorizonYears,20)+1,1)),"n/a")
A57: Amortisation (Payback) Nachsteuer (Jahr-Index) | B57: =IFERROR(MATCH(TRUE,OFFSET($K$31,0,0,MIN(HorizonYears,20)+1,1)>=0,0)-1,"n/a")
A58: Diskontierte KPI-Reduktion (Einheiten) | B58: =SUMPRODUCT(OFFSET($L$31,0,0,MIN(HorizonYears,20)+1,1),OFFSET($C$31,0,0,MIN(HorizonYears,20)+1,1))*$B$24
A59: MACC (€/Einheit KPI) | B59: =IFERROR(-B55/B58,"n/a")

Sheet Portfolio_Calc
A1: Portfolio_Calc (technisches Rechenblatt)
A2: Inputs & Annahmen | S2: Cashflows je Jahr (Nachsteuer) | AN2: Kumulierter Cashflow | BI2: Diskontierte KPI-Reduktion je Jahr | CD2: Kennzahlen
A3: ID | B3: Action | C3: Owner | D3: Start | E3: GoLive | F3: KPI | G3: Einheit | H3: Baseline | I3: ImpactTyp | J3: Impact | K3: KPI_Reduktion_p.a. | L3: FixPrice | M3: VarName | N3: DepY | O3: CAPEX | P3: OPEX | Q3: OtherBen | R3: OtherCost | S3: CF_0 | T3: CF_1 | U3: CF_2 | V3: CF_3 | W3: CF_4 | X3: CF_5 | Y3: CF_6 | Z3: CF_7 | AA3: CF_8 | AB3: CF_9 | AC3: CF_10 | AD3: CF_11 | AE3: CF_12 | AF3: CF_13 | AG3: CF_14 | AH3: CF_15 | AI3: CF_16 | AJ3: CF_17 | AK3: CF_18 | AL3: CF_19 | AM3: CF_20 | AN3: KumCF_0 | AO3: KumCF_1 | AP3: KumCF_2 | AQ3: KumCF_3 | AR3: KumCF_4 | AS3: KumCF_5 | AT3: KumCF_6 | AU3: KumCF_7 | AV3: KumCF_8 | AW3: KumCF_9 | AX3: KumCF_10 | AY3: KumCF_11 | AZ3: KumCF_12 | BA3: KumCF_13 | BB3: KumCF_14 | BC3: KumCF_15 | BD3: KumCF_16 | BE3: KumCF_17 | BF3: KumCF_18 | BG3: KumCF_19 | BH3: KumCF_20 | BI3: DiscRed_0 | BJ3: DiscRed_1 | BK3: DiscRed_2 | BL3: DiscRed_3 | BM3: DiscRed_4 | BN3: DiscRed_5 | BO3: DiscRed_6 | BP3: DiscRed_7 | BQ3: DiscRed_8 | BR3: DiscRed_9 | BS3: DiscRed_10 | BT3: DiscRed_11 | BU3: DiscRed_12 | BV3: DiscRed_13 | BW3: DiscRed_14 | BX3: DiscRed_15 | BY3: DiscRed_16 | BZ3: DiscRed_17 | CA3: DiscRed_18 | CB3: DiscRed_19 | CC3: DiscRed_20 | CD3: NPV | CE3: IRR | CF3: Payback | CG3: DiscRed_Total | CH3: MACC_EUR_pro_Einheit
A4: =Actions!A2 | B4: =Actions!B2 | C4: =Actions!D2 | D4: =Actions!E2 | E4: =Actions!F2 | F4: =Actions!G2 | G4: =Actions!H2 | H4: =Actions!I2 | I4: =Actions!J2 | J4: =Actions!K2 | K4: =IF(A4="","",IF(I4="%",H4*J4,J4)) | L4: =Actions!L2 | M4: =Actions!M2 | N4: =Actions!N2 | O4: =Actions!T2 | P4: =Actions!Y2 | Q4: =Actions!Z2 | R4: =Actions!AA2 | S4: =IF(A4="","",((K4)*(IF(M4="",L4,IFERROR(IF(INDEX(Variablen!$I:$AT, MATCH(M4, Variablen!$A:$A, 0), MATCH((YEAR(D4)+0), Variablen!$I$3:$AT$3, 0))="",L4,INDEX(Variablen!$I:$AT, MATCH(M4, Variablen!$A:$A, 0), MATCH((YEAR(D4)+0), Variablen!$I$3:$AT$3, 0))),L4)))*(IF((YEAR(D4)+0)<YEAR(E4),0,IF((YEAR(D4)+0)>YEAR(E4),1,(12-MONTH(E4)+1)/12))) + (Q4)*(IF((YEAR(D4)+0)<YEAR(E4),0,IF((YEAR(D4)+0)>YEAR(E4),1,(12-MONTH(E4)+1)/12))))-((P4)*(IF((YEAR(D4)+0)<YEAR(E4),0,IF((YEAR(D4)+0)>YEAR(E4),1,(12-MONTH(E4)+1)/12))) + (R4)*(IF((YEAR(D4)+0)<YEAR(E4),0,IF((YEAR(D4)+0)>YEAR(E4),1,(12-MONTH(E4)+1)/12))))-(IF((((K4)*(IF(M4="",L4,IFERROR(IF(INDEX(Variablen!$I:$AT, MATCH(M4, Variablen!$A:$A, 0), MATCH((YEAR(D4)+0), Variablen!$I$3:$AT$3, 0))="",L4,INDEX(Variablen!$I:$AT, MATCH(M4, Variablen!$A:$A, 0), MATCH((YEAR(D4)+0), Variablen!$I$3:$AT$3, 0))),L4)))*(IF((YEAR(D4)+0)<YEAR(E4),0,IF((YEAR(D4)+0)>YEAR(E4),1,(12-MONTH(E4)+1)/12))) + (Q4)*(IF((YEAR(D4)+0)<YEAR(E4),0,IF((YEAR(D4)+0)>YEAR(E4),1,(12-MONTH(E4)+1)/12))))-((P4)*(IF((YEAR(D4)+0)<YEAR(E4),0,IF((YEAR(D4)+0)>YEAR(E4),1,(12-MONTH(E4)+1)/12))) + (R4)*(IF((YEAR(D4)+0)<YEAR(E4),0,IF((YEAR(D4)+0)>YEAR(E4),1,(12-MONTH(E4)+1)/12))))-(IF(OR(N4="",N4<=0),0,(O4/N4)*(IF(OR(N4="",N4<=0),0,IF((YEAR(D4)+0)<YEAR(E4),0,IF((YEAR(D4)+0)>=YEAR(E4)+N4,0,IF((YEAR(D4)+0)=YEAR(E4),(12-MONTH(E4)+1)/12,1))))))))>0,(((K4)*(IF(M4="",L4,IFERROR(IF(INDEX(Variablen!$I:$AT, MATCH(M4, Variablen!$A:$A, 0), MATCH((YEAR(D4)+0), Variablen!$I$3:$AT$3, 0))="",L4,INDEX(Variablen!$I:$AT, MATCH(M4, Variablen!$A:$A, 0), MATCH((YEAR(D4)+0), Variablen!$I$3:$AT$3, 0))),L4)))*(IF((YEAR(D4)+0)<YEAR(E4),0,IF((YEAR(D4)+0)>YEAR(E4),1,(12-MONTH(E4)+1)/12))) + (Q4)*(IF((YEAR(D4)+0)<YEAR(E4),0,IF((YEAR(D4)+0)>YEAR(E4),1,(12-MONTH(E4)+1)/12))))-((P4)*(IF((YEAR(D4)+0)<YEAR(E4),0,IF((YEAR(D4)+0)>YEAR(E4),1,(12-MONTH(E4)+1)/12))) + (R4)*(IF((YEAR(D4)+0)<YEAR(E4),0,IF((YEAR(D4)+0)>YEAR(E4),1,(12-MONTH(E4)+1)/12))))-(IF(OR(N4="",N4<=0),0,(O4/N4)*(IF(OR(N4="",N4<=0),0,IF((YEAR(D4)+0)<YEAR(E4),0,IF((YEAR(D4)+0)>=YEAR(E4)+N4,0,IF((YEAR(D4)+0)=YEAR(E4),(12-MONTH(E4)+1)/12,1))))))))*TaxRate,0))-IF(0=0,O4,0)) | T4: =IF(A4="","",((K4)*(IF(M4="",L4,IFERROR(IF(INDEX(Variablen!$I:$AT, MATCH(M4, Variablen!$A:$A, 0), MATCH((YEAR(D4)+1), Variablen!$I$3:$AT$3, 0))="",L4,INDEX(Variablen!$I:$AT, MATCH(M4, Variablen!$A:$A, 0), MATCH((YEAR(D4)+1), Variablen!$I$3:$AT$3, 0))),L4)))*(IF((YEAR(D4)+1)<YEAR(E4),0,IF((YEAR(D4)+1)>YEAR(E4),1,(12-MONTH(E4)+1)/12))) + (Q4)*(IF((YEAR(D4)+1)<YEAR(E4),0,IF((YEAR(D4)+1)>YEAR(E4),1,(12-MONTH(E4)+1)/12))))-((P4)*(IF((YEAR(D4)+1)<YEAR(E4),0,IF((YEAR(D4)+1)>YEAR(E4),1,(12-MONTH(E4)+1)/12))) + (R4)*(IF((YEAR(D4)+1)<YEAR(E4),0,IF((YEAR(D4)+1)>YEAR(E4),1,(12-MONTH(E4)+1)/12))))-(IF((((K4)*(IF(M4="",L4,IFERROR(IF(INDEX(Variablen!$I:$AT, MATCH(M4, Variablen!$A:$A, 0), MATCH((YEAR(D4)+1), Variablen!$I$3:$AT$3, 0))="",L4,INDEX(Variablen!$I:$AT, MATCH(M4, Variablen!$A:$A, 0), MATCH((YEAR(D4)+1), Variablen!$I$3:$AT$3, 0))),L4)))*(IF((YEAR(D4)+1)<YEAR(E4),0,IF((YEAR(D4)+1)>YEAR(E4),1,(12-MONTH(E4)+1)/12))) + (Q4)*(IF((YEAR(D4)+1)<YEAR(E4),0,IF((YEAR(D4)+1)>YEAR(E4),1,(12-MONTH(E4)+1)/12))))-((P4)*(IF((YEAR(D4)+1)<YEAR(E4),0,IF((YEAR(D4)+1)>YEAR(E4),1,(12-MONTH(E4)+1)/12))) + (R4)*(IF((YEAR(D4)+1)<YEAR(E4),0,IF((YEAR(D4)+1)>YEAR(E4),1,(12-MONTH(E4)+1)/12))))-(IF(OR(N4="",N4<=0),0,(O4/N4)*(IF(OR(N4="",N4<=0),0,IF((YEAR(D4)+1)<YEAR(E4),0,IF((YEAR(D4)+1)>=YEAR(E4)+N4,0,IF((YEAR(D4)+1)=YEAR(E4),(12-MONTH(E4)+1)/12,1))))))))>0,(((K4)*(IF(M4="",L4,IFERROR(IF(INDEX(Variablen!$I:$AT, MATCH(M4, Variablen!$A:$A, 0), MATCH((YEAR(D4)+1), Variablen!$I$3:$AT$3, 0))="",L4,INDEX(Variablen!$I:$AT, MATCH(M4, Variablen!$A:$A, 0), MATCH((YEAR(D4)+1), Variablen!$I$3:$AT$3, 0))),L4)))*(IF((YEAR(D4)+1)<YEAR(E4),0,IF((YEAR(D4)+1)>YEAR(E4),1,(12-MONTH(E4)+1)/12))) + (Q4)*(IF((YEAR(D4)+1)<YEAR(E4),0,IF((YEAR(D4)+1)>YEAR(E4),1,(12-MONTH(E4)+1)/12))))-((P4)*(IF((YEAR(D4)+1)<YEAR(E4),0,IF((YEAR(D4)+1)>YEAR(E4),1,(12-MONTH(E4)+1)/12))) + (R4)*(IF((YEAR(D4)+1)<YEAR(E4),0,IF((YEAR(D4)+1)>YEAR(E4),1,(12-MONTH(E4)+1)/12))))-(IF(OR(N4="",N4<=0),0,(O4/N4)*(IF(OR(N4="",N4<=0),0,IF((YEAR(D4)+1)<YEAR(E4),0,IF((YEAR(D4)+1)>=YEAR(E4)+N4,0,IF((YEAR(D4)+1)=YEAR(E4),(12-MONTH(E4)+1)/12,1))))))))*TaxRate,0))-IF(1=0,O4,0)) | U4: =IF(A4="","",((K4)*(IF(M4="",L4,IFERROR(IF(INDEX(Variablen!$I:$AT, MATCH(M4, Variablen!$A:$A, 0), MATCH((YEAR(D4)+2), Variablen!$I$3:$AT$3, 0))="",L4,INDEX(Variablen!$I:$AT, MATCH(M4, Variablen!$A:$A, 0), MATCH((YEAR(D4)+2), Variablen!$I$3:$AT$3, 0))),L4)))*(IF((YEAR(D4)+2)<YEAR(E4),0,IF((YEAR(D4)+2)>YEAR(E4),1,(12-MONTH(E4)+1)/12))) + (Q4)*(IF((YEAR(D4)+2)<YEAR(E4),0,IF((YEAR(D4)+2)>YEAR(E4),1,(12-MONTH(E4)+1)/12))))-((P4)*(IF((YEAR(D4)+2)<YEAR(E4),0,IF((YEAR(D4)+2)>YEAR(E4),1,(12-MONTH(E4)+1)/12))) + (R4)*(IF((YEAR(D4)+2)<YEAR(E4),0,IF((YEAR(D4)+2)>YEAR(E4),1,(12-MONTH(E4)+1)/12))))-(IF((((K4)*(IF(M4="",L4,IFERROR(IF(INDEX(Variablen!$I:$AT, MATCH(M4, Variablen!$A:$A, 0), MATCH((YEAR(D4)+2), Variablen!$I$3:$AT$3, 0))="",L4,INDEX(Variablen!$I:$AT, MATCH(M4, Variablen!$A:$A, 0), MATCH((YEAR(D4)+2), Variablen!$I$3:$AT$3, 0))),L4)))*(IF((YEAR(D4)+2)<YEAR(E4),0,IF((YEAR(D4)+2)>YEAR(E4),1,(12-MONTH(E4)+1)/12))) + (Q4)*(IF((YEAR(D4)+2)<YEAR(E4),0,IF((YEAR(D4)+2)>YEAR(E4),1,(12-MONTH(E4)+1)/12))))-((P4)*(IF((YEAR(D4)+2)<YEAR(E4),0,IF((YEAR(D4)+2)>YEAR(E4),1,(12-MONTH(E4)+1)/12))) + (R4)*(IF((YEAR(D4)+2)<YEAR(E4),0,IF((YEAR(D4)+2)>YEAR(E4),1,(12-MONTH(E4)+1)/12))))-(IF(OR(N4="",N4<=0),0,(O4/N4)*(IF(OR(N4="",N4<=0),0,IF((YEAR(D4)+2)<YEAR(E4),0,IF((YEAR(D4)+2)>=YEAR(E4)+N4,0,IF((YEAR(D4)+2)=YEAR(E4),(12-MONTH(E4)+1)/12,1))))))))>0,(((K4)*(IF(M4="",L4,IFERROR(IF(INDEX(Variablen!$I:$AT, MATCH(M4, Variablen!$A:$A, 0), MATCH((YEAR(D4)+2), Variablen!$I$3:$AT$3, 0))="",L4,INDEX(Variablen!$I:$AT, MATCH(M4, Variablen!$A:$A, 0), MATCH((YEAR(D4)+2), Variablen!$I$3:$AT$3, 0))),L4)))*(IF((YEAR(D4)+2)<YEAR(E4),0,IF((YEAR(D4)+2)>YEAR(E4),1,(12-MONTH(E4)+1)/12))) + (Q4)*(IF((YEAR(D4)+2)<YEAR(E4),0,IF((YEAR(D4)+2)>YEAR(E4),1,(12-MONTH(E4)+1)/12))))-((P4)*(IF((YEAR(D4)+2)<YEAR(E4),0,IF((YEAR(D4)+2)>YEAR(E4),1,(12-MONTH(E4)+1)/12))) + (R4)*(IF((YEAR(D4)+2)<YEAR(E4),0,IF((YEAR(D4)+2)>YEAR(E4),1,(12-MONTH(E4)+1)/12))))-(IF(OR(N4="",N4<=0),0,(O4/N4)*(IF(OR(N4="",N4<=0),0,IF((YEAR(D4)+2)<YEAR(E4),0,IF((YEAR(D4)+2)>=YEAR(E4)+N4,0,IF((YEAR(D4)+2)=YEAR(E4),(12-MONTH(E4)+1)/12,1))))))))*TaxRate,0))-IF(2=0,O4,0)) | V4: =IF(A4="","",((K4)*(IF(M4="",L4,IFERROR(IF(INDEX(Variablen!$I:$AT, MATCH(M4, Variablen!$A:$A, 0), MATCH((YEAR(D4)+3), Variablen!$I$3:$AT$3, 0))="",L4,INDEX(Variablen!$I:$AT, MATCH(M4, Variablen!$A:$A, 0), MATCH((YEAR(D4)+3), Variablen!$I$3:$AT$3, 0))),L4)))*(IF((YEAR(D4)+3)<YEAR(E4),0,IF((YEAR(D4)+3)>YEAR(E4),1,(12-MONTH(E4)+1)/12))) + (Q4)*(IF((YEAR(D4)+3)<YEAR(E4),0,IF((YEAR(D4)+3)>YEAR(E4),1,(12-MONTH(E4)+1)/12))))-((P4)*(IF((YEAR(D4)+3)<YEAR(E4),0,IF((YEAR(D4)+3)>YEAR(E4),1,(12-MONTH(E4)+1)/12))) + (R4)*(IF((YEAR(D4)+3)<YEAR(E4),0,IF((YEAR(D4)+3)>YEAR(E4),1,(12-MONTH(E4)+1)/12))))-(IF((((K4)*(IF(M4="",L4,IFERROR(IF(INDEX(Variablen!$I:$AT, MATCH(M4, Variablen!$A:$A, 0), MATCH((YEAR(D4)+3), Variablen!$I$3:$AT$3, 0))="",L4,INDEX(Variablen!$I:$AT, MATCH(M4, Variablen!$A:$A, 0), MATCH((YEAR(D4)+3), Variablen!$I$3:$AT$3, 0))),L4)))*(IF((YEAR(D4)+3)<YEAR(E4),0,IF((YEAR(D4)+3)>YEAR(E4),1,(12-MONTH(E4)+1)/12))) + (Q4)*(IF((YEAR(D4)+3)<YEAR(E4),0,IF((YEAR(D4)+3)>YEAR(E4),1,(12-MONTH(E4)+1)/12))))-((P4)*(IF((YEAR(D4)+3)<YEAR(E4),0,IF((YEAR(D4)+3)>YEAR(E4),1,(12-MONTH(E4)+1)/12))) + (R4)*(IF((YEAR(D4)+3)<YEAR(E4),0,IF((YEAR(D4)+3)>YEAR(E4),1,(12-MONTH(E4)+1)/12))))-(IF(OR(N4="",N4<=0),0,(O4/N4)*(IF(OR(N4="",N4<=0),0,IF((YEAR(D4)+3)<YEAR(E4),0,IF((YEAR(D4)+3)>=YEAR(E4)+N4,0,IF((YEAR(D4)+3)=YEAR(E4),(12-MONTH(E4)+1)/12,1))))))))>0,(((K4)*(IF(M4="",L4,IFERROR(IF(INDEX(Variablen!$I:$AT, MATCH(M4, Variablen!$A:$A, 0), MATCH((YEAR(D4)+3), Variablen!$I$3:$AT$3, 0))="",L4,INDEX(Variablen!$I:$AT, MATCH(M4, Variablen!$A:$A, 0), MATCH((YEAR(D4)+3), Variablen!$I$3:$AT$3, 0))),L4)))*(IF((YEAR(D4)+3)<YEAR(E4),0,IF((YEAR(D4)+3)>YEAR(E4),1,(12-MONTH(E4)+1)/12))) + (Q4)*(IF((YEAR(D4)+3)<YEAR(E4),0,IF((YEAR(D4)+3)>YEAR(E4),1,(12-MONTH(E4)+1)/12))))-((P4)*(IF((YEAR(D4)+3)<YEAR(E4),0,IF((YEAR(D4)+3)>YEAR(E4),1,(12-MONTH(E4)+1)/12))) + (R4)*(IF((YEAR(D4)+3)<YEAR(E4),0,IF((YEAR(D4)+3)>YEAR(E4),1,(12-MONTH(E4)+1)/12))))-(IF(OR(N4="",N4<=0),0,(O4/N4)*(IF(OR(N4="",N4<=0),0,IF((YEAR(D4)+3)<YEAR(E4),0,IF((YEAR(D4)+3)>=YEAR(E4)+N4,0,IF((YEAR(D4)+3)=YEAR(E4),(12-MONTH(E4)+1)/12,1))))))))*TaxRate,0))-IF(3=0,O4,0)) | W4: =IF(A4="","",((K4)*(IF(M4="",L4,IFERROR(IF(INDEX(Variablen!$I:$AT, MATCH(M4, Variablen!$A:$A, 0), MATCH((YEAR(D4)+4), Variablen!$I$3:$AT$3, 0))="",L4,INDEX(Variablen!$I:$AT, MATCH(M4, Variablen!$A:$A, 0), MATCH((YEAR(D4)+4), Variablen!$I$3:$AT$3, 0))),L4)))*(IF((YEAR(D4)+4)<YEAR(E4),0,IF((YEAR(D4)+4)>YEAR(E4),1,(12-MONTH(E4)+1)/12))) + (Q4)*(IF((YEAR(D4)+4)<YEAR(E4),0,IF((YEAR(D4)+4)>YEAR(E4),1,(12-MONTH(E4)+1)/12))))-((P4)*(IF((YEAR(D4)+4)<YEAR(E4),0,IF((YEAR(D4)+4)>YEAR(E4),1,(12-MONTH(E4)+1)/12))) + (R4)*(IF((YEAR(D4)+4)<YEAR(E4),0,IF((YEAR(D4)+4)>YEAR(E4),1,(12-MONTH(E4)+1)/12))))-(IF((((K4)*(IF(M4="",L4,IFERROR(IF(INDEX(Variablen!$I:$AT, MATCH(M4, Variablen!$A:$A, 0), MATCH((YEAR(D4)+4), Variablen!$I$3:$AT$3, 0))="",L4,INDEX(Variablen!$I:$AT, MATCH(M4, Variablen!$A:$A, 0), MATCH((YEAR(D4)+4), Variablen!$I$3:$AT$3, 0))),L4)))*(IF((YEAR(D4)+4)<YEAR(E4),0,IF((YEAR(D4)+4)>YEAR(E4),1,(12-MONTH(E4)+1)/12))) + (Q4)*(IF((YEAR(D4)+4)<YEAR(E4),0,IF((YEAR(D4)+4)>YEAR(E4),1,(12-MONTH(E4)+1)/12))))-((P4)*(IF((YEAR(D4)+4)<YEAR(E4),0,IF((YEAR(D4)+4)>YEAR(E4),1,(12-MONTH(E4)+1)/12))) + (R4)*(IF((YEAR(D4)+4)<YEAR(E4),0,IF((YEAR(D4)+4)>YEAR(E4),1,(12-MONTH(E4)+1)/12))))-(IF(OR(N4="",N4<=0),0,(O4/N4)*(IF(OR(N4="",N4<=0),0,IF((YEAR(D4)+4)<YEAR(E4),0,IF((YEAR(D4)+4)>=YEAR(E4)+N4,0,IF((YEAR(D4)+4)=YEAR(E4),(12-MONTH(E4)+1)/12,1))))))))>0,(((K4)*(IF(M4="",L4,IFERROR(IF(INDEX(Variablen!$I:$AT, MATCH(M4, Variablen!$A:$A, 0), MATCH((YEAR(D4)+4), Variablen!$I$3:$AT$3, 0))="",L4,INDEX(Variablen!$I:$AT, MATCH(M4, Variablen!$A:$A, 0), MATCH((YEAR(D4)+4), Variablen!$I$3:$AT$3, 0))),L4)))*(IF((YEAR(D4)+4)<YEAR(E4),0,IF((YEAR(D4)+4)>YEAR(E4),1,(12-MONTH(E4)+1)/12))) + (Q4)*(IF((YEAR(D4)+4)<YEAR(E4),0,IF((YEAR(D4)+4)>YEAR(E4),1,(12-MONTH(E4)+1)/12))))-((P4)*(IF((YEAR(D4)+4)<YEAR(E4),0,IF((YEAR(D4)+4)>YEAR(E4),1,(12-MONTH(E4)+1)/12))) + (R4)*(IF((YEAR(D4)+4)<YEAR(E4),0,IF((YEAR(D4)+4)>YEAR(E4),1,(12-MONTH(E4)+1)/12))))-(IF(OR(N4="",N4<=0),0,(O4/N4)*(IF(OR(N4="",N4<=0),0,IF((YEAR(D4)+4)<YEAR(E4),0,IF((YEAR(D4)+4)>=YEAR(E4)+N4,0,IF((YEAR(D4)+4)=YEAR(E4),(12-MONTH(E4)+1)/12,1))))))))*TaxRate,0))-IF(4=0,O4,0)) | X4: =IF(A4="","",((K4)*(IF(M4="",L4,IFERROR(IF(INDEX(Variablen!$I:$AT, MATCH(M4, Variablen!$A:$A, 0), MATCH((YEAR(D4)+5), Variablen!$I$3:$AT$3, 0))="",L4,INDEX(Variablen!$I:$AT, MATCH(M4, Variablen!$A:$A, 0), MATCH((YEAR(D4)+5), Variablen!$I$3:$AT$3, 0))),L4)))*(IF((YEAR(D4)+5)<YEAR(E4),0,IF((YEAR(D4)+5)>YEAR(E4),1,(12-MONTH(E4)+1)/12))) + (Q4)*(IF((YEAR(D4)+5)<YEAR(E4),0,IF((YEAR(D4)+5)>YEAR(E4),1,(12-MONTH(E4)+1)/12))))-((P4)*(IF((YEAR(D4)+5)<YEAR(E4),0,IF((YEAR(D4)+5)>YEAR(E4),1,(12-MONTH(E4)+1)/12))) + (R4)*(IF((YEAR(D4)+5)<YEAR(E4),0,IF((YEAR(D4)+5)>YEAR(E4),1,(12-MONTH(E4)+1)/12))))-(IF((((K4)*(IF(M4="",L4,IFERROR(IF(INDEX(Variablen!$I:$AT, MATCH(M4, Variablen!$A:$A, 0), MATCH((YEAR(D4)+5), Variablen!$I$3:$AT$3, 0))="",L4,INDEX(Variablen!$I:$AT, MATCH(M4, Variablen!$A:$A, 0), MATCH((YEAR(D4)+5), Variablen!$I$3:$AT$3, 0))),L4)))*(IF((YEAR(D4)+5)<YEAR(E4),0,IF((YEAR(D4)+5)>YEAR(E4),1,(12-MONTH(E4)+1)/12))) + (Q4)*(IF((YEAR(D4)+5)<YEAR(E4),0,IF((YEAR(D4)+5)>YEAR(E4),1,(12-MONTH(E4)+1)/12))))-((P4)*(IF((YEAR(D4)+5)<YEAR(E4),0,IF((YEAR(D4)+5)>YEAR(E4),1,(12-MONTH(E4)+1)/12))) + (R4)*(IF((YEAR(D4)+5)<YEAR(E4),0,IF((YEAR(D4)+5)>YEAR(E4),1,(12-MONTH(E4)+1)/12))))-(IF(OR(N4="",N4<=0),0,(O4/N4)*(IF(OR(N4="",N4<=0),0,IF((YEAR(D4)+5)<YEAR(E4),0,IF((YEAR(D4)+5)>=YEAR(E4)+N4,0,IF((YEAR(D4)+5)=YEAR(E4),(12-MONTH(E4)+1)/12,1))))))))>0,(((K4)*(IF(M4="",L4,IFERROR(IF(INDEX(Variablen!$I:$AT, MATCH(M4, Variablen!$A:$A, 0), MATCH((YEAR(D4)+5), Variablen!$I$3:$AT$3, 0))="",L4,INDEX(Variablen!$I:$AT, MATCH(M4, Variablen!$A:$A, 0), MATCH((YEAR(D4)+5), Variablen!$I$3:$AT$3, 0))),L4)))*(IF((YEAR(D4)+5)<YEAR(E4),0,IF((YEAR(D4)+5)>YEAR(E4),1,(12-MONTH(E4)+1)/12))) + (Q4)*(IF((YEAR(D4)+5)<YEAR(E4),0,IF((YEAR(D4)+5)>YEAR(E4),1,(12-MONTH(E4)+1)/12))))-((P4)*(IF((YEAR(D4)+5)<YEAR(E4),0,IF((YEAR(D4)+5)>YEAR(E4),1,(12-MONTH(E4)+1)/12))) + (R4)*(IF((YEAR(D4)+5)<YEAR(E4),0,IF((YEAR(D4)+5)>YEAR(E4),1,(12-MONTH(E4)+1)/12))))-(IF(OR(N4="",N4<=0),0,(O4/N4)*(IF(OR(N4="",N4<=0),0,IF((YEAR(D4)+5)<YEAR(E4),0,IF((YEAR(D4)+5)>=YEAR(E4)+N4,0,IF((YEAR(D4)+5)=YEAR(E4),(12-MONTH(E4)+1)/12,1))))))))*TaxRate,0))-IF(5=0,O4,0)) | Y4: =IF(A4="","",((K4)*(IF(M4="",L4,IFERROR(IF(INDEX(Variablen!$I:$AT, MATCH(M4, Variablen!$A:$A, 0), MATCH((YEAR(D4)+6), Variablen!$I$3:$AT$3, 0))="",L4,INDEX(Variablen!$I:$AT, MATCH(M4, Variablen!$A:$A, 0), MATCH((YEAR(D4)+6), Variablen!$I$3:$AT$3, 0))),L4)))*(IF((YEAR(D4)+6)<YEAR(E4),0,IF((YEAR(D4)+6)>YEAR(E4),1,(12-MONTH(E4)+1)/12))) + (Q4)*(IF((YEAR(D4)+6)<YEAR(E4),0,IF((YEAR(D4)+6)>YEAR(E4),1,(12-MONTH(E4)+1)/12))))-((P4)*(IF((YEAR(D4)+6)<YEAR(E4),0,IF((YEAR(D4)+6)>YEAR(E4),1,(12-MONTH(E4)+1)/12))) + (R4)*(IF((YEAR(D4)+6)<YEAR(E4),0,IF((YEAR(D4)+6)>YEAR(E4),1,(12-MONTH(E4)+1)/12))))-(IF((((K4)*(IF(M4="",L4,IFERROR(IF(INDEX(Variablen!$I:$AT, MATCH(M4, Variablen!$A:$A, 0), MATCH((YEAR(D4)+6), Variablen!$I$3:$AT$3, 0))="",L4,INDEX(Variablen!$I:$AT, MATCH(M4, Variablen!$A:$A, 0), MATCH((YEAR(D4)+6), Variablen!$I$3:$AT$3, 0))),L4)))*(IF((YEAR(D4)+6)<YEAR(E4),0,IF((YEAR(D4)+6)>YEAR(E4),1,(12-MONTH(E4)+1)/12))) + (Q4)*(IF((YEAR(D4)+6)<YEAR(E4),0,IF((YEAR(D4)+6)>YEAR(E4),1,(12-MONTH(E4)+1)/12))))-((P4)*(IF((YEAR(D4)+6)<YEAR(E4),0,IF((YEAR(D4)+6)>YEAR(E4),1,(12-MONTH(E4)+1)/12))) + (R4)*(IF((YEAR(D4)+6)<YEAR(E4),0,IF((YEAR(D4)+6)>YEAR(E4),1,(12-MONTH(E4)+1)/12))))-(IF(OR(N4="",N4<=0),0,(O4/N4)*(IF(OR(N4="",N4<=0),0,IF((YEAR(D4)+6)<YEAR(E4),0,IF((YEAR(D4)+6)>=YEAR(E4)+N4,0,IF((YEAR(D4)+6)=YEAR(E4),(12-MONTH(E4)+1)/12,1))))))))>0,(((K4)*(IF(M4="",L4,IFERROR(IF(INDEX(Variablen!$I:$AT, MATCH(M4, Variablen!$A:$A, 0), MATCH((YEAR(D4)+6), Variablen!$I$3:$AT$3, 0))="",L4,INDEX(Variablen!$I:$AT, MATCH(M4, Variablen!$A:$A, 0), MATCH((YEAR(D4)+6), Variablen!$I$3:$AT$3, 0))),L4)))*(IF((YEAR(D4)+6)<YEAR(E4),0,IF((YEAR(D4)+6)>YEAR(E4),1,(12-MONTH(E4)+1)/12))) + (Q4)*(IF((YEAR(D4)+6)<YEAR(E4),0,IF((YEAR(D4)+6)>YEAR(E4),1,(12-MONTH(E4)+1)/12))))-((P4)*(IF((YEAR(D4)+6)<YEAR(E4),0,IF((YEAR(D4)+6)>YEAR(E4),1,(12-MONTH(E4)+1)/12))) + (R4)*(IF((YEAR(D4)+6)<YEAR(E4),0,IF((YEAR(D4)+6)>YEAR(E4),1,(12-MONTH(E4)+1)/12))))-(IF(OR(N4="",N4<=0),0,(O4/N4)*(IF(OR(N4="",N4<=0),0,IF((YEAR(D4)+6)<YEAR(E4),0,IF((YEAR(D4)+6)>=YEAR(E4)+N4,0,IF((YEAR(D4)+6)=YEAR(E4),(12-MONTH(E4)+1)/12,1))))))))*TaxRate,0))-IF(6=0,O4,0)) | Z4: =IF(A4="","",((K4)*(IF(M4="",L4,IFERROR(IF(INDEX(Variablen!$I:$AT, MATCH(M4, Variablen!$A:$A, 0), MATCH((YEAR(D4)+7), Variablen!$I$3:$AT$3, 0))="",L4,INDEX(Variablen!$I:$AT, MATCH(M4, Variablen!$A:$A, 0), MATCH((YEAR(D4)+7), Variablen!$I$3:$AT$3, 0))),L4)))*(IF((YEAR(D4)+7)<YEAR(E4),0,IF((YEAR(D4)+7)>YEAR(E4),1,(12-MONTH(E4)+1)/12))) + (Q4)*(IF((YEAR(D4)+7)<YEAR(E4),0,IF((YEAR(D4)+7)>YEAR(E4),1,(12-MONTH(E4)+1)/12))))-((P4)*(IF((YEAR(D4)+7)<YEAR(E4),0,IF((YEAR(D4)+7)>YEAR(E4),1,(12-MONTH(E4)+1)/12))) + (R4)*(IF((YEAR(D4)+7)<YEAR(E4),0,IF((YEAR(D4)+7)>YEAR(E4),1,(12-MONTH(E4)+1)/12))))-(IF((((K4)*(IF(M4="",L4,IFERROR(IF(INDEX(Variablen!$I:$AT, MATCH(M4, Variablen!$A:$A, 0), MATCH((YEAR(D4)+7), Variablen!$I$3:$AT$3, 0))="",L4,INDEX(Variablen!$I:$AT, MATCH(M4, Variablen!$A:$A, 0), MATCH((YEAR(D4)+7), Variablen!$I$3:$AT$3, 0))),L4)))*(IF((YEAR(D4)+7)<YEAR(E4),0,IF((YEAR(D4)+7)>YEAR(E4),1,(12-MONTH(E4)+1)/12))) + (Q4)*(IF((YEAR(D4)+7)<YEAR(E4),0,IF((YEAR(D4)+7)>YEAR(E4),1,(12-MONTH(E4)+1)/12))))-((P4)*(IF((YEAR(D4)+7)<YEAR(E4),0,IF((YEAR(D4)+7)>YEAR(E4),1,(12-MONTH(E4)+1)/12))) + (R4)*(IF((YEAR(D4)+7)<YEAR(E4),0,IF((YEAR(D4)+7)>YEAR(E4),1,(12-MONTH(E4)+1)/12))))-(IF(OR(N4="",N4<=0),0,(O4/N4)*(IF(OR(N4="",N4<=0),0,IF((YEAR(D4)+7)<YEAR(E4),0,IF((YEAR(D4)+7)>=YEAR(E4)+N4,0,IF((YEAR(D4)+7)=YEAR(E4),(12-MONTH(E4)+1)/12,1))))))))>0,(((K4)*(IF(M4="",L4,IFERROR(IF(INDEX(Variablen!$I:$AT, MATCH(M4, Variablen!$A:$A, 0), MATCH((YEAR(D4)+7), Variablen!$I$3:$AT$3, 0))="",L4,INDEX(Variablen!$I:$AT, MATCH(M4, Variablen!$A:$A, 0), MATCH((YEAR(D4)+7), Variablen!$I$3:$AT$3, 0))),L4)))*(IF((YEAR(D4)+7)<YEAR(E4),0,IF((YEAR(D4)+7)>YEAR(E4),1,(12-MONTH(E4)+1)/12))) + (Q4)*(IF((YEAR(D4)+7)<YEAR(E4),0,IF((YEAR(D4)+7)>YEAR(E4),1,(12-MONTH(E4)+1)/12))))-((P4)*(IF((YEAR(D4)+7)<YEAR(E4),0,IF((YEAR(D4)+7)>YEAR(E4),1,(12-MONTH(E4)+1)/12))) + (R4)*(IF((YEAR(D4)+7)<YEAR(E4),0,IF((YEAR(D4)+7)>YEAR(E4),1,(12-MONTH(E4)+1)/12))))-(IF(OR(N4="",N4<=0),0,(O4/N4)*(IF(OR(N4="",N4<=0),0,IF((YEAR(D4)+7)<YEAR(E4),0,IF((YEAR(D4)+7)>=YEAR(E4)+N4,0,IF((YEAR(D4)+7)=YEAR(E4),(12-MONTH(E4)+1)/12,1))))))))*TaxRate,0))-IF(7=0,O4,0)) | AA4: =IF(A4="","",((K4)*(IF(M4="",L4,IFERROR(IF(INDEX(Variablen!$I:$AT, MATCH(M4, Variablen!$A:$A, 0), MATCH((YEAR(D4)+8), Variablen!$I$3:$AT$3, 0))="",L4,INDEX(Variablen!$I:$AT, MATCH(M4, Variablen!$A:$A, 0), MATCH((YEAR(D4)+8), Variablen!$I$3:$AT$3, 0))),L4)))*(IF((YEAR(D4)+8)<YEAR(E4),0,IF((YEAR(D4)+8)>YEAR(E4),1,(12-MONTH(E4)+1)/12))) + (Q4)*(IF((YEAR(D4)+8)<YEAR(E4),0,IF((YEAR(D4)+8)>YEAR(E4),1,(12-MONTH(E4)+1)/12))))-((P4)*(IF((YEAR(D4)+8)<YEAR(E4),0,IF((YEAR(D4)+8)>YEAR(E4),1,(12-MONTH(E4)+1)/12))) + (R4)*(IF((YEAR(D4)+8)<YEAR(E4),0,IF((YEAR(D4)+8)>YEAR(E4),1,(12-MONTH(E4)+1)/12))))-(IF((((K4)*(IF(M4="",L4,IFERROR(IF(INDEX(Variablen!$I:$AT, MATCH(M4, Variablen!$A:$A, 0), MATCH((YEAR(D4)+8), Variablen!$I$3:$AT$3, 0))="",L4,INDEX(Variablen!$I:$AT, MATCH(M4, Variablen!$A:$A, 0), MATCH((YEAR(D4)+8), Variablen!$I$3:$AT$3, 0))),L4)))*(IF((YEAR(D4)+8)<YEAR(E4),0,IF((YEAR(D4)+8)>YEAR(E4),1,(12-MONTH(E4)+1)/12))) + (Q4)*(IF((YEAR(D4)+8)<YEAR(E4),0,IF((YEAR(D4)+8)>YEAR(E4),1,(12-MONTH(E4)+1)/12))))-((P4)*(IF((YEAR(D4)+8)<YEAR(E4),0,IF((YEAR(D4)+8)>YEAR(E4),1,(12-MONTH(E4)+1)/12))) + (R4)*(IF((YEAR(D4)+8)<YEAR(E4),0,IF((YEAR(D4)+8)>YEAR(E4),1,(12-MONTH(E4)+1)/12))))-(IF(OR(N4="",N4<=0),0,(O4/N4)*(IF(OR(N4="",N4<=0),0,IF((YEAR(D4)+8)<YEAR(E4),0,IF((YEAR(D4)+8)>=YEAR(E4)+N4,0,IF((YEAR(D4)+8)=YEAR(E4),(12-MONTH(E4)+1)/12,1))))))))>0,(((K4)*(IF(M4="",L4,IFERROR(IF(INDEX(Variablen!$I:$AT, MATCH(M4, Variablen!$A:$A, 0), MATCH((YEAR(D4)+8), Variablen!$I$3:$AT$3, 0))="",L4,INDEX(Variablen!$I:$AT, MATCH(M4, Variablen!$A:$A, 0), MATCH((YEAR(D4)+8), Variablen!$I$3:$AT$3, 0))),L4)))*(IF((YEAR(D4)+8)<YEAR(E4),0,IF((YEAR(D4)+8)>YEAR(E4),1,(12-MONTH(E4)+1)/12))) + (Q4)*(IF((YEAR(D4)+8)<YEAR(E4),0,IF((YEAR(D4)+8)>YEAR(E4),1,(12-MONTH(E4)+1)/12))))-((P4)*(IF((YEAR(D4)+8)<YEAR(E4),0,IF((YEAR(D4)+8)>YEAR(E4),1,(12-MONTH(E4)+1)/12))) + (R4)*(IF((YEAR(D4)+8)<YEAR(E4),0,IF((YEAR(D4)+8)>YEAR(E4),1,(12-MONTH(E4)+1)/12))))-(IF(OR(N4="",N4<=0),0,(O4/N4)*(IF(OR(N4="",N4<=0),0,IF((YEAR(D4)+8)<YEAR(E4),0,IF((YEAR(D4)+8)>=YEAR(E4)+N4,0,IF((YEAR(D4)+8)=YEAR(E4),(12-MONTH(E4)+1)/12,1))))))))*TaxRate,0))-IF(8=0,O4,0)) | AB4: =IF(A4="","",((K4)*(IF(M4="",L4,IFERROR(IF(INDEX(Variablen!$I:$AT, MATCH(M4, Variablen!$A:$A, 0), MATCH((YEAR(D4)+9), Variablen!$I$3:$AT$3, 0))="",L4,INDEX(Variablen!$I:$AT, MATCH(M4, Variablen!$A:$A, 0), MATCH((YEAR(D4)+9), Variablen!$I$3:$AT$3, 0))),L4)))*(IF((YEAR(D4)+9)<YEAR(E4),0,IF((YEAR(D4)+9)>YEAR(E4),1,(12-MONTH(E4)+1)/12))) + (Q4)*(IF((YEAR(D4)+9)<YEAR(E4),0,IF((YEAR(D4)+9)>YEAR(E4),1,(12-MONTH(E4)+1)/12))))-((P4)*(IF((YEAR(D4)+9)<YEAR(E4),0,IF((YEAR(D4)+9)>YEAR(E4),1,(12-MONTH(E4)+1)/12))) + (R4)*(IF((YEAR(D4)+9)<YEAR(E4),0,IF((YEAR(D4)+9)>YEAR(E4),1,(12-MONTH(E4)+1)/12))))-(IF((((K4)*(IF(M4="",L4,IFERROR(IF(INDEX(Variablen!$I:$AT, MATCH(M4, Variablen!$A:$A, 0), MATCH((YEAR(D4)+9), Variablen!$I$3:$AT$3, 0))="",L4,INDEX(Variablen!$I:$AT, MATCH(M4, Variablen!$A:$A, 0), MATCH((YEAR(D4)+9), Variablen!$I$3:$AT$3, 0))),L4)))*(IF((YEAR(D4)+9)<YEAR(E4),0,IF((YEAR(D4)+9)>YEAR(E4),1,(12-MONTH(E4)+1)/12))) + (Q4)*(IF((YEAR(D4)+9)<YEAR(E4),0,IF((YEAR(D4)+9)>YEAR(E4),1,(12-MONTH(E4)+1)/12))))-((P4)*(IF((YEAR(D4)+9)<YEAR(E4),0,IF((YEAR(D4)+9)>YEAR(E4),1,(12-MONTH(E4)+1)/12))) + (R4)*(IF((YEAR(D4)+9)<YEAR(E4),0,IF((YEAR(D4)+9)>YEAR(E4),1,(12-MONTH(E4)+1)/12))))-(IF(OR(N4="",N4<=0),0,(O4/N4)*(IF(OR(N4="",N4<=0),0,IF((YEAR(D4)+9)<YEAR(E4),0,IF((YEAR(D4)+9)>=YEAR(E4)+N4,0,IF((YEAR(D4)+9)=YEAR(E4),(12-MONTH(E4)+1)/12,1))))))))>0,(((K4)*(IF(M4="",L4,IFERROR(IF(INDEX(Variablen!$I:$AT, MATCH(M4, Variablen!$A:$A, 0), MATCH((YEAR(D4)+9), Variablen!$I$3:$AT$3, 0))="",L4,INDEX(Variablen!$I:$AT, MATCH(M4, Variablen!$A:$A, 0), MATCH((YEAR(D4)+9), Variablen!$I$3:$AT$3, 0))),L4)))*(IF((YEAR(D4)+9)<YEAR(E4),0,IF((YEAR(D4)+9)>YEAR(E4),1,(12-MONTH(E4)+1)/12))) + (Q4)*(IF((YEAR(D4)+9)<YEAR(E4),0,IF((YEAR(D4)+9)>YEAR(E4),1,(12-MONTH(E4)+1)/12))))-((P4)*(IF((YEAR(D4)+9)<YEAR(E4),0,IF((YEAR(D4)+9)>YEAR(E4),1,(12-MONTH(E4)+1)/12))) + (R4)*(IF((YEAR(D4)+9)<YEAR(E4),0,IF((YEAR(D4)+9)>YEAR(E4),1,(12-MONTH(E4)+1)/12))))-(IF(OR(N4="",N4<=0),0,(O4/N4)*(IF(OR(N4="",N4<=0),0,IF((YEAR(D4)+9)<YEAR(E4),0,IF((YEAR(D4)+9)>=YEAR(E4)+N4,0,IF((YEAR(D4)+9)=YEAR(E4),(12-MONTH(E4)+1)/12,1))))))))*TaxRate,0))-IF(9=0,O4,0)) | AC4: =IF(A4="","",((K4)*(IF(M4="",L4,IFERROR(IF(INDEX(Variablen!$I:$AT, MATCH(M4, Variablen!$A:$A, 0), MATCH((YEAR(D4)+10), Variablen!$I$3:$AT$3, 0))="",L4,INDEX(Variablen!$I:$AT, MATCH(M4, Variablen!$A:$A, 0), MATCH((YEAR(D4)+10), Variablen!$I$3:$AT$3, 0))),L4)))*(IF((YEAR(D4)+10)<YEAR(E4),0,IF((YEAR(D4)+10)>YEAR(E4),1,(12-MONTH(E4)+1)/12))) + (Q4)*(IF((YEAR(D4)+10)<YEAR(E4),0,IF((YEAR(D4)+10)>YEAR(E4),1,(12-MONTH(E4)+1)/12))))-((P4)*(IF((YEAR(D4)+10)<YEAR(E4),0,IF((YEAR(D4)+10)>YEAR(E4),1,(12-MONTH(E4)+1)/12))) + (R4)*(IF((YEAR(D4)+10)<YEAR(E4),0,IF((YEAR(D4)+10)>YEAR(E4),1,(12-MONTH(E4)+1)/12))))-(IF((((K4)*(IF(M4="",L4,IFERROR(IF(INDEX(Variablen!$I:$AT, MATCH(M4, Variablen!$A:$A, 0), MATCH((YEAR(D4)+10), Variablen!$I$3:$AT$3, 0))="",L4,INDEX(Variablen!$I:$AT, MATCH(M4, Variablen!$A:$A, 0), MATCH((YEAR(D4)+10), Variablen!$I$3:$AT$3, 0))),L4)))*(IF((YEAR(D4)+10)<YEAR(E4),0,IF((YEAR(D4)+10)>YEAR(E4),1,(12-MONTH(E4)+1)/12))) + (Q4)*(IF((YEAR(D4)+10)<YEAR(E4),0,IF((YEAR(D4)+10)>YEAR(E4),1,(12-MONTH(E4)+1)/12))))-((P4)*(IF((YEAR(D4)+10)<YEAR(E4),0,IF((YEAR(D4)+10)>YEAR(E4),1,(12-MONTH(E4)+1)/12))) + (R4)*(IF((YEAR(D4)+10)<YEAR(E4),0,IF((YEAR(D4)+10)>YEAR(E4),1,(12-MONTH(E4)+1)/12))))-(IF(OR(N4="",N4<=0),0,(O4/N4)*(IF(OR(N4="",N4<=0),0,IF((YEAR(D4)+10)<YEAR(E4),0,IF((YEAR(D4)+10)>=YEAR(E4)+N4,0,IF((YEAR(D4)+10)=YEAR(E4),(12-MONTH(E4)+1)/12,1))))))))>0,(((K4)*(IF(M4="",L4,IFERROR(IF(INDEX(Variablen!$I:$AT, MATCH(M4, Variablen!$A:$A, 0), MATCH((YEAR(D4)+10), Variablen!$I$3:$AT$3, 0))="",L4,INDEX(Variablen!$I:$AT, MATCH(M4, Variablen!$A:$A, 0), MATCH((YEAR(D4)+10), Variablen!$I$3:$AT$3, 0))),L4)))*(IF((YEAR(D4)+10)<YEAR(E4),0,IF((YEAR(D4)+10)>YEAR(E4),1,(12-MONTH(E4)+1)/12))) + (Q4)*(IF((YEAR(D4)+10)<YEAR(E4),0,IF((YEAR(D4)+10)>YEAR(E4),1,(12-MONTH(E4)+1)/12))))-((P4)*(IF((YEAR(D4)+10)<YEAR(E4),0,IF((YEAR(D4)+10)>YEAR(E4),1,(12-MONTH(E4)+1)/12))) + (R4)*(IF((YEAR(D4)+10)<YEAR(E4),0,IF((YEAR(D4)+10)>YEAR(E4),1,(12-MONTH(E4)+1)/12))))-(IF(OR(N4="",N4<=0),0,(O4/N4)*(IF(OR(N4="",N4<=0),0,IF((YEAR(D4)+10)<YEAR(E4),0,IF((YEAR(D4)+10)>=YEAR(E4)+N4,0,IF((YEAR(D4)+10)=YEAR(E4),(12-MONTH(E4)+1)/12,1))))))))*TaxRate,0))-IF(10=0,O4,0)) | AD4: =IF(A4="","",((K4)*(IF(M4="",L4,IFERROR(IF(INDEX(Variablen!$I:$AT, MATCH(M4, Variablen!$A:$A, 0), MATCH((YEAR(D4)+11), Variablen!$I$3:$AT$3, 0))="",L4,INDEX(Variablen!$I:$AT, MATCH(M4, Variablen!$A:$A, 0), MATCH((YEAR(D4)+11), Variablen!$I$3:$AT$3, 0))),L4)))*(IF((YEAR(D4)+11)<YEAR(E4),0,IF((YEAR(D4)+11)>YEAR(E4),1,(12-MONTH(E4)+1)/12))) + (Q4)*(IF((YEAR(D4)+11)<YEAR(E4),0,IF((YEAR(D4)+11)>YEAR(E4),1,(12-MONTH(E4)+1)/12))))-((P4)*(IF((YEAR(D4)+11)<YEAR(E4),0,IF((YEAR(D4)+11)>YEAR(E4),1,(12-MONTH(E4)+1)/12))) + (R4)*(IF((YEAR(D4)+11)<YEAR(E4),0,IF((YEAR(D4)+11)>YEAR(E4),1,(12-MONTH(E4)+1)/12))))-(IF((((K4)*(IF(M4="",L4,IFERROR(IF(INDEX(Variablen!$I:$AT, MATCH(M4, Variablen!$A:$A, 0), MATCH((YEAR(D4)+11), Variablen!$I$3:$AT$3, 0))="",L4,INDEX(Variablen!$I:$AT, MATCH(M4, Variablen!$A:$A, 0), MATCH((YEAR(D4)+11), Variablen!$I$3:$AT$3, 0))),L4)))*(IF((YEAR(D4)+11)<YEAR(E4),0,IF((YEAR(D4)+11)>YEAR(E4),1,(12-MONTH(E4)+1)/12))) + (Q4)*(IF((YEAR(D4)+11)<YEAR(E4),0,IF((YEAR(D4)+11)>YEAR(E4),1,(12-MONTH(E4)+1)/12))))-((P4)*(IF((YEAR(D4)+11)<YEAR(E4),0,IF((YEAR(D4)+11)>YEAR(E4),1,(12-MONTH(E4)+1)/12))) + (R4)*(IF((YEAR(D4)+11)<YEAR(E4),0,IF((YEAR(D4)+11)>YEAR(E4),1,(12-MONTH(E4)+1)/12))))-(IF(OR(N4="",N4<=0),0,(O4/N4)*(IF(OR(N4="",N4<=0),0,IF((YEAR(D4)+11)<YEAR(E4),0,IF((YEAR(D4)+11)>=YEAR(E4)+N4,0,IF((YEAR(D4)+11)=YEAR(E4),(12-MONTH(E4)+1)/12,1))))))))>0,(((K4)*(IF(M4="",L4,IFERROR(IF(INDEX(Variablen!$I:$AT, MATCH(M4, Variablen!$A:$A, 0), MATCH((YEAR(D4)+11), Variablen!$I$3:$AT$3, 0))="",L4,INDEX(Variablen!$I:$AT, MATCH(M4, Variablen!$A:$A, 0), MATCH((YEAR(D4)+11), Variablen!$I$3:$AT$3, 0))),L4)))*(IF((YEAR(D4)+11)<YEAR(E4),0,IF((YEAR(D4)+11)>YEAR(E4),1,(12-MONTH(E4)+1)/12))) + (Q4)*(IF((YEAR(D4)+11)<YEAR(E4),0,IF((YEAR(D4)+11)>YEAR(E4),1,(12-MONTH(E4)+1)/12))))-((P4)*(IF((YEAR(D4)+11)<YEAR(E4),0,IF((YEAR(D4)+11)>YEAR(E4),1,(12-MONTH(E4)+1)/12))) + (R4)*(IF((YEAR(D4)+11)<YEAR(E4),0,IF((YEAR(D4)+11)>YEAR(E4),1,(12-MONTH(E4)+1)/12))))-(IF(OR(N4="",N4<=0),0,(O4/N4)*(IF(OR(N4="",N4<=0),0,IF((YEAR(D4)+11)<YEAR(E4),0,IF((YEAR(D4)+11)>=YEAR(E4)+N4,0,IF((YEAR(D4)+11)=YEAR(E4),(12-MONTH(E4)+1)/12,1))))))))*TaxRate,0))-IF(11=0,O4,0)) | AE4: =IF(A4="","",((K4)*(IF(M4="",L4,IFERROR(IF(INDEX(Variablen!$I:$AT, MATCH(M4, Variablen!$A:$A, 0), MATCH((YEAR(D4)+12), Variablen!$I$3:$AT$3, 0))="",L4,INDEX(Variablen!$I:$AT, MATCH(M4, Variablen!$A:$A, 0), MATCH((YEAR(D4)+12), Variablen!$I$3:$AT$3, 0))),L4)))*(IF((YEAR(D4)+12)<YEAR(E4),0,IF((YEAR(D4)+12)>YEAR(E4),1,(12-MONTH(E4)+1)/12))) + (Q4)*(IF((YEAR(D4)+12)<YEAR(E4),0,IF((YEAR(D4)+12)>YEAR(E4),1,(12-MONTH(E4)+1)/12))))-((P4)*(IF((YEAR(D4)+12)<YEAR(E4),0,IF((YEAR(D4)+12)>YEAR(E4),1,(12-MONTH(E4)+1)/12))) + (R4)*(IF((YEAR(D4)+12)<YEAR(E4),0,IF((YEAR(D4)+12)>YEAR(E4),1,(12-MONTH(E4)+1)/12))))-(IF((((K4)*(IF(M4="",L4,IFERROR(IF(INDEX(Variablen!$I:$AT, MATCH(M4, Variablen!$A:$A, 0), MATCH((YEAR(D4)+12), Variablen!$I$3:$AT$3, 0))="",L4,INDEX(Variablen!$I:$AT, MATCH(M4, Variablen!$A:$A, 0), MATCH((YEAR(D4)+12), Variablen!$I$3:$AT$3, 0))),L4)))*(IF((YEAR(D4)+12)<YEAR(E4),0,IF((YEAR(D4)+12)>YEAR(E4),1,(12-MONTH(E4)+1)/12))) + (Q4)*(IF((YEAR(D4)+12)<YEAR(E4),0,IF((YEAR(D4)+12)>YEAR(E4),1,(12-MONTH(E4)+1)/12))))-((P4)*(IF((YEAR(D4)+12)<YEAR(E4),0,IF((YEAR(D4)+12)>YEAR(E4),1,(12-MONTH(E4)+1)/12))) + (R4)*(IF((YEAR(D4)+12)<YEAR(E4),0,IF((YEAR(D4)+12)>YEAR(E4),1,(12-MONTH(E4)+1)/12))))-(IF(OR(N4="",N4<=0),0,(O4/N4)*(IF(OR(N4="",N4<=0),0,IF((YEAR(D4)+12)<YEAR(E4),0,IF((YEAR(D4)+12)>=YEAR(E4)+N4,0,IF((YEAR(D4)+12)=YEAR(E4),(12-MONTH(E4)+1)/12,1))))))))>0,(((K4)*(IF(M4="",L4,IFERROR(IF(INDEX(Variablen!$I:$AT, MATCH(M4, Variablen!$A:$A, 0), MATCH((YEAR(D4)+12), Variablen!$I$3:$AT$3, 0))="",L4,INDEX(Variablen!$I:$AT, MATCH(M4, Variablen!$A:$A, 0), MATCH((YEAR(D4)+12), Variablen!$I$3:$AT$3, 0))),L4)))*(IF((YEAR(D4)+12)<YEAR(E4),0,IF((YEAR(D4)+12)>YEAR(E4),1,(12-MONTH(E4)+1)/12))) + (Q4)*(IF((YEAR(D4)+12)<YEAR(E4),0,IF((YEAR(D4)+12)>YEAR(E4),1,(12-MONTH(E4)+1)/12))))-((P4)*(IF((YEAR(D4)+12)<YEAR(E4),0,IF((YEAR(D4)+12)>YEAR(E4),1,(12-MONTH(E4)+1)/12))) + (R4)*(IF((YEAR(D4)+12)<YEAR(E4),0,IF((YEAR(D4)+12)>YEAR(E4),1,(12-MONTH(E4)+1)/12))))-(IF(OR(N4="",N4<=0),0,(O4/N4)*(IF(OR(N4="",N4<=0),0,IF((YEAR(D4)+12)<YEAR(E4),0,IF((YEAR(D4)+12)>=YEAR(E4)+N4,0,IF((YEAR(D4)+12)=YEAR(E4),(12-MONTH(E4)+1)/12,1))))))))*TaxRate,0))-IF(12=0,O4,0)) | AF4: =IF(A4="","",((K4)*(IF(M4="",L4,IFERROR(IF(INDEX(Variablen!$I:$AT, MATCH(M4, Variablen!$A:$A, 0), MATCH((YEAR(D4)+13), Variablen!$I$3:$AT$3, 0))="",L4,INDEX(Variablen!$I:$AT, MATCH(M4, Variablen!$A:$A, 0), MATCH((YEAR(D4)+13), Variablen!$I$3:$AT$3, 0))),L4)))*(IF((YEAR(D4)+13)<YEAR(E4),0,IF((YEAR(D4)+13)>YEAR(E4),1,(12-MONTH(E4)+1)/12))) + (Q4)*(IF((YEAR(D4)+13)<YEAR(E4),0,IF((YEAR(D4)+13)>YEAR(E4),1,(12-MONTH(E4)+1)/12))))-((P4)*(IF((YEAR(D4)+13)<YEAR(E4),0,IF((YEAR(D4)+13)>YEAR(E4),1,(12-MONTH(E4)+1)/12))) + (R4)*(IF((YEAR(D4)+13)<YEAR(E4),0,IF((YEAR(D4)+13)>YEAR(E4),1,(12-MONTH(E4)+1)/12))))-(IF((((K4)*(IF(M4="",L4,IFERROR(IF(INDEX(Variablen!$I:$AT, MATCH(M4, Variablen!$A:$A, 0), MATCH((YEAR(D4)+13), Variablen!$I$3:$AT$3, 0))="",L4,INDEX(Variablen!$I:$AT, MATCH(M4, Variablen!$A:$A, 0), MATCH((YEAR(D4)+13), Variablen!$I$3:$AT$3, 0))),L4)))*(IF((YEAR(D4)+13)<YEAR(E4),0,IF((YEAR(D4)+13)>YEAR(E4),1,(12-MONTH(E4)+1)/12))) + (Q4)*(IF((YEAR(D4)+13)<YEAR(E4),0,IF((YEAR(D4)+13)>YEAR(E4),1,(12-MONTH(E4)+1)/12))))-((P4)*(IF((YEAR(D4)+13)<YEAR(E4),0,IF((YEAR(D4)+13)>YEAR(E4),1,(12-MONTH(E4)+1)/12))) + (R4)*(IF((YEAR(D4)+13)<YEAR(E4),0,IF((YEAR(D4)+13)>YEAR(E4),1,(12-MONTH(E4)+1)/12))))-(IF(OR(N4="",N4<=0),0,(O4/N4)*(IF(OR(N4="",N4<=0),0,IF((YEAR(D4)+13)<YEAR(E4),0,IF((YEAR(D4)+13)>=YEAR(E4)+N4,0,IF((YEAR(D4)+13)=YEAR(E4),(12-MONTH(E4)+1)/12,1))))))))>0,(((K4)*(IF(M4="",L4,IFERROR(IF(INDEX(Variablen!$I:$AT, MATCH(M4, Variablen!$A:$A, 0), MATCH((YEAR(D4)+13), Variablen!$I$3:$AT$3, 0))="",L4,INDEX(Variablen!$I:$AT, MATCH(M4, Variablen!$A:$A, 0), MATCH((YEAR(D4)+13), Variablen!$I$3:$AT$3, 0))),L4)))*(IF((YEAR(D4)+13)<YEAR(E4),0,IF((YEAR(D4)+13)>YEAR(E4),1,(12-MONTH(E4)+1)/12))) + (Q4)*(IF((YEAR(D4)+13)<YEAR(E4),0,IF((YEAR(D4)+13)>YEAR(E4),1,(12-MONTH(E4)+1)/12))))-((P4)*(IF((YEAR(D4)+13)<YEAR(E4),0,IF((YEAR(D4)+13)>YEAR(E4),1,(12-MONTH(E4)+1)/12))) + (R4)*(IF((YEAR(D4)+13)<YEAR(E4),0,IF((YEAR(D4)+13)>YEAR(E4),1,(12-MONTH(E4)+1)/12))))-(IF(OR(N4="",N4<=0),0,(O4/N4)*(IF(OR(N4="",N4<=0),0,IF((YEAR(D4)+13)<YEAR(E4),0,IF((YEAR(D4)+13)>=YEAR(E4)+N4,0,IF((YEAR(D4)+13)=YEAR(E4),(12-MONTH(E4)+1)/12,1))))))))*TaxRate,0))-IF(13=0,O4,0)) | AG4: =IF(A4="","",((K4)*(IF(M4="",L4,IFERROR(IF(INDEX(Variablen!$I:$AT, MATCH(M4, Variablen!$A:$A, 0), MATCH((YEAR(D4)+14), Variablen!$I$3:$AT$3, 0))="",L4,INDEX(Variablen!$I:$AT, MATCH(M4, Variablen!$A:$A, 0), MATCH((YEAR(D4)+14), Variablen!$I$3:$AT$3, 0))),L4)))*(IF((YEAR(D4)+14)<YEAR(E4),0,IF((YEAR(D4)+14)>YEAR(E4),1,(12-MONTH(E4)+1)/12))) + (Q4)*(IF((YEAR(D4)+14)<YEAR(E4),0,IF((YEAR(D4)+14)>YEAR(E4),1,(12-MONTH(E4)+1)/12))))-((P4)*(IF((YEAR(D4)+14)<YEAR(E4),0,IF((YEAR(D4)+14)>YEAR(E4),1,(12-MONTH(E4)+1)/12))) + (R4)*(IF((YEAR(D4)+14)<YEAR(E4),0,IF((YEAR(D4)+14)>YEAR(E4),1,(12-MONTH(E4)+1)/12))))-(IF((((K4)*(IF(M4="",L4,IFERROR(IF(INDEX(Variablen!$I:$AT, MATCH(M4, Variablen!$A:$A, 0), MATCH((YEAR(D4)+14), Variablen!$I$3:$AT$3, 0))="",L4,INDEX(Variablen!$I:$AT, MATCH(M4, Variablen!$A:$A, 0), MATCH((YEAR(D4)+14), Variablen!$I$3:$AT$3, 0))),L4)))*(IF((YEAR(D4)+14)<YEAR(E4),0,IF((YEAR(D4)+14)>YEAR(E4),1,(12-MONTH(E4)+1)/12))) + (Q4)*(IF((YEAR(D4)+14)<YEAR(E4),0,IF((YEAR(D4)+14)>YEAR(E4),1,(12-MONTH(E4)+1)/12))))-((P4)*(IF((YEAR(D4)+14)<YEAR(E4),0,IF((YEAR(D4)+14)>YEAR(E4),1,(12-MONTH(E4)+1)/12))) + (R4)*(IF((YEAR(D4)+14)<YEAR(E4),0,IF((YEAR(D4)+14)>YEAR(E4),1,(12-MONTH(E4)+1)/12))))-(IF(OR(N4="",N4<=0),0,(O4/N4)*(IF(OR(N4="",N4<=0),0,IF((YEAR(D4)+14)<YEAR(E4),0,IF((YEAR(D4)+14)>=YEAR(E4)+N4,0,IF((YEAR(D4)+14)=YEAR(E4),(12-MONTH(E4)+1)/12,1))))))))>0,(((K4)*(IF(M4="",L4,IFERROR(IF(INDEX(Variablen!$I:$AT, MATCH(M4, Variablen!$A:$A, 0), MATCH((YEAR(D4)+14), Variablen!$I$3:$AT$3, 0))="",L4,INDEX(Variablen!$I:$AT, MATCH(M4, Variablen!$A:$A, 0), MATCH((YEAR(D4)+14), Variablen!$I$3:$AT$3, 0))),L4)))*(IF((YEAR(D4)+14)<YEAR(E4),0,IF((YEAR(D4)+14)>YEAR(E4),1,(12-MONTH(E4)+1)/12))) + (Q4)*(IF((YEAR(D4)+14)<YEAR(E4),0,IF((YEAR(D4)+14)>YEAR(E4),1,(12-MONTH(E4)+1)/12))))-((P4)*(IF((YEAR(D4)+14)<YEAR(E4),0,IF((YEAR(D4)+14)>YEAR(E4),1,(12-MONTH(E4)+1)/12))) + (R4)*(IF((YEAR(D4)+14)<YEAR(E4),0,IF((YEAR(D4)+14)>YEAR(E4),1,(12-MONTH(E4)+1)/12))))-(IF(OR(N4="",N4<=0),0,(O4/N4)*(IF(OR(N4="",N4<=0),0,IF((YEAR(D4)+14)<YEAR(E4),0,IF((YEAR(D4)+14)>=YEAR(E4)+N4,0,IF((YEAR(D4)+14)=YEAR(E4),(12-MONTH(E4)+1)/12,1))))))))*TaxRate,0))-IF(14=0,O4,0)) | AH4: =IF(A4="","",((K4)*(IF(M4="",L4,IFERROR(IF(INDEX(Variablen!$I:$AT, MATCH(M4, Variablen!$A:$A, 0), MATCH((YEAR(D4)+15), Variablen!$I$3:$AT$3, 0))="",L4,INDEX(Variablen!$I:$AT, MATCH(M4, Variablen!$A:$A, 0), MATCH((YEAR(D4)+15), Variablen!$I$3:$AT$3, 0))),L4)))*(IF((YEAR(D4)+15)<YEAR(E4),0,IF((YEAR(D4)+15)>YEAR(E4),1,(12-MONTH(E4)+1)/12))) + (Q4)*(IF((YEAR(D4)+15)<YEAR(E4),0,IF((YEAR(D4)+15)>YEAR(E4),1,(12-MONTH(E4)+1)/12))))-((P4)*(IF((YEAR(D4)+15)<YEAR(E4),0,IF((YEAR(D4)+15)>YEAR(E4),1,(12-MONTH(E4)+1)/12))) + (R4)*(IF((YEAR(D4)+15)<YEAR(E4),0,IF((YEAR(D4)+15)>YEAR(E4),1,(12-MONTH(E4)+1)/12))))-(IF((((K4)*(IF(M4="",L4,IFERROR(IF(INDEX(Variablen!$I:$AT, MATCH(M4, Variablen!$A:$A, 0), MATCH((YEAR(D4)+15), Variablen!$I$3:$AT$3, 0))="",L4,INDEX(Variablen!$I:$AT, MATCH(M4, Variablen!$A:$A, 0), MATCH((YEAR(D4)+15), Variablen!$I$3:$AT$3, 0))),L4)))*(IF((YEAR(D4)+15)<YEAR(E4),0,IF((YEAR(D4)+15)>YEAR(E4),1,(12-MONTH(E4)+1)/12))) + (Q4)*(IF((YEAR(D4)+15)<YEAR(E4),0,IF((YEAR(D4)+15)>YEAR(E4),1,(12-MONTH(E4)+1)/12))))-((P4)*(IF((YEAR(D4)+15)<YEAR(E4),0,IF((YEAR(D4)+15)>YEAR(E4),1,(12-MONTH(E4)+1)/12))) + (R4)*(IF((YEAR(D4)+15)<YEAR(E4),0,IF((YEAR(D4)+15)>YEAR(E4),1,(12-MONTH(E4)+1)/12))))-(IF(OR(N4="",N4<=0),0,(O4/N4)*(IF(OR(N4="",N4<=0),0,IF((YEAR(D4)+15)<YEAR(E4),0,IF((YEAR(D4)+15)>=YEAR(E4)+N4,0,IF((YEAR(D4)+15)=YEAR(E4),(12-MONTH(E4)+1)/12,1))))))))>0,(((K4)*(IF(M4="",L4,IFERROR(IF(INDEX(Variablen!$I:$AT, MATCH(M4, Variablen!$A:$A, 0), MATCH((YEAR(D4)+15), Variablen!$I$3:$AT$3, 0))="",L4,INDEX(Variablen!$I:$AT, MATCH(M4, Variablen!$A:$A, 0), MATCH((YEAR(D4)+15), Variablen!$I$3:$AT$3, 0))),L4)))*(IF((YEAR(D4)+15)<YEAR(E4),0,IF((YEAR(D4)+15)>YEAR(E4),1,(12-MONTH(E4)+1)/12))) + (Q4)*(IF((YEAR(D4)+15)<YEAR(E4),0,IF((YEAR(D4)+15)>YEAR(E4),1,(12-MONTH(E4)+1)/12))))-((P4)*(IF((YEAR(D4)+15)<YEAR(E4),0,IF((YEAR(D4)+15)>YEAR(E4),1,(12-MONTH(E4)+1)/12))) + (R4)*(IF((YEAR(D4)+15)<YEAR(E4),0,IF((YEAR(D4)+15)>YEAR(E4),1,(12-MONTH(E4)+1)/12))))-(IF(OR(N4="",N4<=0),0,(O4/N4)*(IF(OR(N4="",N4<=0),0,IF((YEAR(D4)+15)<YEAR(E4),0,IF((YEAR(D4)+15)>=YEAR(E4)+N4,0,IF((YEAR(D4)+15)=YEAR(E4),(12-MONTH(E4)+1)/12,1))))))))*TaxRate,0))-IF(15=0,O4,0)) | AI4: =IF(A4="","",((K4)*(IF(M4="",L4,IFERROR(IF(INDEX(Variablen!$I:$AT, MATCH(M4, Variablen!$A:$A, 0), MATCH((YEAR(D4)+16), Variablen!$I$3:$AT$3, 0))="",L4,INDEX(Variablen!$I:$AT, MATCH(M4, Variablen!$A:$A, 0), MATCH((YEAR(D4)+16), Variablen!$I$3:$AT$3, 0))),L4)))*(IF((YEAR(D4)+16)<YEAR(E4),0,IF((YEAR(D4)+16)>YEAR(E4),1,(12-MONTH(E4)+1)/12))) + (Q4)*(IF((YEAR(D4)+16)<YEAR(E4),0,IF((YEAR(D4)+16)>YEAR(E4),1,(12-MONTH(E4)+1)/12))))-((P4)*(IF((YEAR(D4)+16)<YEAR(E4),0,IF((YEAR(D4)+16)>YEAR(E4),1,(12-MONTH(E4)+1)/12))) + (R4)*(IF((YEAR(D4)+16)<YEAR(E4),0,IF((YEAR(D4)+16)>YEAR(E4),1,(12-MONTH(E4)+1)/12))))-(IF((((K4)*(IF(M4="",L4,IFERROR(IF(INDEX(Variablen!$I:$AT, MATCH(M4, Variablen!$A:$A, 0), MATCH((YEAR(D4)+16), Variablen!$I$3:$AT$3, 0))="",L4,INDEX(Variablen!$I:$AT, MATCH(M4, Variablen!$A:$A, 0), MATCH((YEAR(D4)+16), Variablen!$I$3:$AT$3, 0))),L4)))*(IF((YEAR(D4)+16)<YEAR(E4),0,IF((YEAR(D4)+16)>YEAR(E4),1,(12-MONTH(E4)+1)/12))) + (Q4)*(IF((YEAR(D4)+16)<YEAR(E4),0,IF((YEAR(D4)+16)>YEAR(E4),1,(12-MONTH(E4)+1)/12))))-((P4)*(IF((YEAR(D4)+16)<YEAR(E4),0,IF((YEAR(D4)+16)>YEAR(E4),1,(12-MONTH(E4)+1)/12))) + (R4)*(IF((YEAR(D4)+16)<YEAR(E4),0,IF((YEAR(D4)+16)>YEAR(E4),1,(12-MONTH(E4)+1)/12))))-(IF(OR(N4="",N4<=0),0,(O4/N4)*(IF(OR(N4="",N4<=0),0,IF((YEAR(D4)+16)<YEAR(E4),0,IF((YEAR(D4)+16)>=YEAR(E4)+N4,0,IF((YEAR(D4)+16)=YEAR(E4),(12-MONTH(E4)+1)/12,1))))))))>0,(((K4)*(IF(M4="",L4,IFERROR(IF(INDEX(Variablen!$I:$AT, MATCH(M4, Variablen!$A:$A, 0), MATCH((YEAR(D4)+16), Variablen!$I$3:$AT$3, 0))="",L4,INDEX(Variablen!$I:$AT, MATCH(M4, Variablen!$A:$A, 0), MATCH((YEAR(D4)+16), Variablen!$I$3:$AT$3, 0))),L4)))*(IF((YEAR(D4)+16)<YEAR(E4),0,IF((YEAR(D4)+16)>YEAR(E4),1,(12-MONTH(E4)+1)/12))) + (Q4)*(IF((YEAR(D4)+16)<YEAR(E4),0,IF((YEAR(D4)+16)>YEAR(E4),1,(12-MONTH(E4)+1)/12))))-((P4)*(IF((YEAR(D4)+16)<YEAR(E4),0,IF((YEAR(D4)+16)>YEAR(E4),1,(12-MONTH(E4)+1)/12))) + (R4)*(IF((YEAR(D4)+16)<YEAR(E4),0,IF((YEAR(D4)+16)>YEAR(E4),1,(12-MONTH(E4)+1)/12))))-(IF(OR(N4="",N4<=0),0,(O4/N4)*(IF(OR(N4="",N4<=0),0,IF((YEAR(D4)+16)<YEAR(E4),0,IF((YEAR(D4)+16)>=YEAR(E4)+N4,0,IF((YEAR(D4)+16)=YEAR(E4),(12-MONTH(E4)+1)/12,1))))))))*TaxRate,0))-IF(16=0,O4,0)) | AJ4: =IF(A4="","",((K4)*(IF(M4="",L4,IFERROR(IF(INDEX(Variablen!$I:$AT, MATCH(M4, Variablen!$A:$A, 0), MATCH((YEAR(D4)+17), Variablen!$I$3:$AT$3, 0))="",L4,INDEX(Variablen!$I:$AT, MATCH(M4, Variablen!$A:$A, 0), MATCH((YEAR(D4)+17), Variablen!$I$3:$AT$3, 0))),L4)))*(IF((YEAR(D4)+17)<YEAR(E4),0,IF((YEAR(D4)+17)>YEAR(E4),1,(12-MONTH(E4)+1)/12))) + (Q4)*(IF((YEAR(D4)+17)<YEAR(E4),0,IF((YEAR(D4)+17)>YEAR(E4),1,(12-MONTH(E4)+1)/12))))-((P4)*(IF((YEAR(D4)+17)<YEAR(E4),0,IF((YEAR(D4)+17)>YEAR(E4),1,(12-MONTH(E4)+1)/12))) + (R4)*(IF((YEAR(D4)+17)<YEAR(E4),0,IF((YEAR(D4)+17)>YEAR(E4),1,(12-MONTH(E4)+1)/12))))-(IF((((K4)*(IF(M4="",L4,IFERROR(IF(INDEX(Variablen!$I:$AT, MATCH(M4, Variablen!$A:$A, 0), MATCH((YEAR(D4)+17), Variablen!$I$3:$AT$3, 0))="",L4,INDEX(Variablen!$I:$AT, MATCH(M4, Variablen!$A:$A, 0), MATCH((YEAR(D4)+17), Variablen!$I$3:$AT$3, 0))),L4)))*(IF((YEAR(D4)+17)<YEAR(E4),0,IF((YEAR(D4)+17)>YEAR(E4),1,(12-MONTH(E4)+1)/12))) + (Q4)*(IF((YEAR(D4)+17)<YEAR(E4),0,IF((YEAR(D4)+17)>YEAR(E4),1,(12-MONTH(E4)+1)/12))))-((P4)*(IF((YEAR(D4)+17)<YEAR(E4),0,IF((YEAR(D4)+17)>YEAR(E4),1,(12-MONTH(E4)+1)/12))) + (R4)*(IF((YEAR(D4)+17)<YEAR(E4),0,IF((YEAR(D4)+17)>YEAR(E4),1,(12-MONTH(E4)+1)/12))))-(IF(OR(N4="",N4<=0),0,(O4/N4)*(IF(OR(N4="",N4<=0),0,IF((YEAR(D4)+17)<YEAR(E4),0,IF((YEAR(D4)+17)>=YEAR(E4)+N4,0,IF((YEAR(D4)+17)=YEAR(E4),(12-MONTH(E4)+1)/12,1))))))))>0,(((K4)*(IF(M4="",L4,IFERROR(IF(INDEX(Variablen!$I:$AT, MATCH(M4, Variablen!$A:$A, 0), MATCH((YEAR(D4)+17), Variablen!$I$3:$AT$3, 0))="",L4,INDEX(Variablen!$I:$AT, MATCH(M4, Variablen!$A:$A, 0), MATCH((YEAR(D4)+17), Variablen!$I$3:$AT$3, 0))),L4)))*(IF((YEAR(D4)+17)<YEAR(E4),0,IF((YEAR(D4)+17)>YEAR(E4),1,(12-MONTH(E4)+1)/12))) + (Q4)*(IF((YEAR(D4)+17)<YEAR(E4),0,IF((YEAR(D4)+17)>YEAR(E4),1,(12-MONTH(E4)+1)/12))))-((P4)*(IF((YEAR(D4)+17)<YEAR(E4),0,IF((YEAR(D4)+17)>YEAR(E4),1,(12-MONTH(E4)+1)/12))) + (R4)*(IF((YEAR(D4)+17)<YEAR(E4),0,IF((YEAR(D4)+17)>YEAR(E4),1,(12-MONTH(E4)+1)/12))))-(IF(OR(N4="",N4<=0),0,(O4/N4)*(IF(OR(N4="",N4<=0),0,IF((YEAR(D4)+17)<YEAR(E4),0,IF((YEAR(D4)+17)>=YEAR(E4)+N4,0,IF((YEAR(D4)+17)=YEAR(E4),(12-MONTH(E4)+1)/12,1))))))))*TaxRate,0))-IF(17=0,O4,0)) | AK4: =IF(A4="","",((K4)*(IF(M4="",L4,IFERROR(IF(INDEX(Variablen!$I:$AT, MATCH(M4, Variablen!$A:$A, 0), MATCH((YEAR(D4)+18), Variablen!$I$3:$AT$3, 0))="",L4,INDEX(Variablen!$I:$AT, MATCH(M4, Variablen!$A:$A, 0), MATCH((YEAR(D4)+18), Variablen!$I$3:$AT$3, 0))),L4)))*(IF((YEAR(D4)+18)<YEAR(E4),0,IF((YEAR(D4)+18)>YEAR(E4),1,(12-MONTH(E4)+1)/12))) + (Q4)*(IF((YEAR(D4)+18)<YEAR(E4),0,IF((YEAR(D4)+18)>YEAR(E4),1,(12-MONTH(E4)+1)/12))))-((P4)*(IF((YEAR(D4)+18)<YEAR(E4),0,IF((YEAR(D4)+18)>YEAR(E4),1,(12-MONTH(E4)+1)/12))) + (R4)*(IF((YEAR(D4)+18)<YEAR(E4),0,IF((YEAR(D4)+18)>YEAR(E4),1,(12-MONTH(E4)+1)/12))))-(IF((((K4)*(IF(M4="",L4,IFERROR(IF(INDEX(Variablen!$I:$AT, MATCH(M4, Variablen!$A:$A, 0), MATCH((YEAR(D4)+18), Variablen!$I$3:$AT$3, 0))="",L4,INDEX(Variablen!$I:$AT, MATCH(M4, Variablen!$A:$A, 0), MATCH((YEAR(D4)+18), Variablen!$I$3:$AT$3, 0))),L4)))*(IF((YEAR(D4)+18)<YEAR(E4),0,IF((YEAR(D4)+18)>YEAR(E4),1,(12-MONTH(E4)+1)/12))) + (Q4)*(IF((YEAR(D4)+18)<YEAR(E4),0,IF((YEAR(D4)+18)>YEAR(E4),1,(12-MONTH(E4)+1)/12))))-((P4)*(IF((YEAR(D4)+18)<YEAR(E4),0,IF((YEAR(D4)+18)>YEAR(E4),1,(12-MONTH(E4)+1)/12))) + (R4)*(IF((YEAR(D4)+18)<YEAR(E4),0,IF((YEAR(D4)+18)>YEAR(E4),1,(12-MONTH(E4)+1)/12))))-(IF(OR(N4="",N4<=0),0,(O4/N4)*(IF(OR(N4="",N4<=0),0,IF((YEAR(D4)+18)<YEAR(E4),0,IF((YEAR(D4)+18)>=YEAR(E4)+N4,0,IF((YEAR(D4)+18)=YEAR(E4),(12-MONTH(E4)+1)/12,1))))))))>0,(((K4)*(IF(M4="",L4,IFERROR(IF(INDEX(Variablen!$I:$AT, MATCH(M4, Variablen!$A:$A, 0), MATCH((YEAR(D4)+18), Variablen!$I$3:$AT$3, 0))="",L4,INDEX(Variablen!$I:$AT, MATCH(M4, Variablen!$A:$A, 0), MATCH((YEAR(D4)+18), Variablen!$I$3:$AT$3, 0))),L4)))*(IF((YEAR(D4)+18)<YEAR(E4),0,IF((YEAR(D4)+18)>YEAR(E4),1,(12-MONTH(E4)+1)/12))) + (Q4)*(IF((YEAR(D4)+18)<YEAR(E4),0,IF((YEAR(D4)+18)>YEAR(E4),1,(12-MONTH(E4)+1)/12))))-((P4)*(IF((YEAR(D4)+18)<YEAR(E4),0,IF((YEAR(D4)+18)>YEAR(E4),1,(12-MONTH(E4)+1)/12))) + (R4)*(IF((YEAR(D4)+18)<YEAR(E4),0,IF((YEAR(D4)+18)>YEAR(E4),1,(12-MONTH(E4)+1)/12))))-(IF(OR(N4="",N4<=0),0,(O4/N4)*(IF(OR(N4="",N4<=0),0,IF((YEAR(D4)+18)<YEAR(E4),0,IF((YEAR(D4)+18)>=YEAR(E4)+N4,0,IF((YEAR(D4)+18)=YEAR(E4),(12-MONTH(E4)+1)/12,1))))))))*TaxRate,0))-IF(18=0,O4,0)) | AL4: =IF(A4="","",((K4)*(IF(M4="",L4,IFERROR(IF(INDEX(Variablen!$I:$AT, MATCH(M4, Variablen!$A:$A, 0), MATCH((YEAR(D4)+19), Variablen!$I$3:$AT$3, 0))="",L4,INDEX(Variablen!$I:$AT, MATCH(M4, Variablen!$A:$A, 0), MATCH((YEAR(D4)+19), Variablen!$I$3:$AT$3, 0))),L4)))*(IF((YEAR(D4)+19)<YEAR(E4),0,IF((YEAR(D4)+19)>YEAR(E4),1,(12-MONTH(E4)+1)/12))) + (Q4)*(IF((YEAR(D4)+19)<YEAR(E4),0,IF((YEAR(D4)+19)>YEAR(E4),1,(12-MONTH(E4)+1)/12))))-((P4)*(IF((YEAR(D4)+19)<YEAR(E4),0,IF((YEAR(D4)+19)>YEAR(E4),1,(12-MONTH(E4)+1)/12))) + (R4)*(IF((YEAR(D4)+19)<YEAR(E4),0,IF((YEAR(D4)+19)>YEAR(E4),1,(12-MONTH(E4)+1)/12))))-(IF((((K4)*(IF(M4="",L4,IFERROR(IF(INDEX(Variablen!$I:$AT, MATCH(M4, Variablen!$A:$A, 0), MATCH((YEAR(D4)+19), Variablen!$I$3:$AT$3, 0))="",L4,INDEX(Variablen!$I:$AT, MATCH(M4, Variablen!$A:$A, 0), MATCH((YEAR(D4)+19), Variablen!$I$3:$AT$3, 0))),L4)))*(IF((YEAR(D4)+19)<YEAR(E4),0,IF((YEAR(D4)+19)>YEAR(E4),1,(12-MONTH(E4)+1)/12))) + (Q4)*(IF((YEAR(D4)+19)<YEAR(E4),0,IF((YEAR(D4)+19)>YEAR(E4),1,(12-MONTH(E4)+1)/12))))-((P4)*(IF((YEAR(D4)+19)<YEAR(E4),0,IF((YEAR(D4)+19)>YEAR(E4),1,(12-MONTH(E4)+1)/12))) + (R4)*(IF((YEAR(D4)+19)<YEAR(E4),0,IF((YEAR(D4)+19)>YEAR(E4),1,(12-MONTH(E4)+1)/12))))-(IF(OR(N4="",N4<=0),0,(O4/N4)*(IF(OR(N4="",N4<=0),0,IF((YEAR(D4)+19)<YEAR(E4),0,IF((YEAR(D4)+19)>=YEAR(E4)+N4,0,IF((YEAR(D4)+19)=YEAR(E4),(12-MONTH(E4)+1)/12,1))))))))>0,(((K4)*(IF(M4="",L4,IFERROR(IF(INDEX(Variablen!$I:$AT, MATCH(M4, Variablen!$A:$A, 0), MATCH((YEAR(D4)+19), Variablen!$I$3:$AT$3, 0))="",L4,INDEX(Variablen!$I:$AT, MATCH(M4, Variablen!$A:$A, 0), MATCH((YEAR(D4)+19), Variablen!$I$3:$AT$3, 0))),L4)))*(IF((YEAR(D4)+19)<YEAR(E4),0,IF((YEAR(D4)+19)>YEAR(E4),1,(12-MONTH(E4)+1)/12))) + (Q4)*(IF((YEAR(D4)+19)<YEAR(E4),0,IF((YEAR(D4)+19)>YEAR(E4),1,(12-MONTH(E4)+1)/12))))-((P4)*(IF((YEAR(D4)+19)<YEAR(E4),0,IF((YEAR(D4)+19)>YEAR(E4),1,(12-MONTH(E4)+1)/12))) + (R4)*(IF((YEAR(D4)+19)<YEAR(E4),0,IF((YEAR(D4)+19)>YEAR(E4),1,(12-MONTH(E4)+1)/12))))-(IF(OR(N4="",N4<=0),0,(O4/N4)*(IF(OR(N4="",N4<=0),0,IF((YEAR(D4)+19)<YEAR(E4),0,IF((YEAR(D4)+19)>=YEAR(E4)+N4,0,IF((YEAR(D4)+19)=YEAR(E4),(12-MONTH(E4)+1)/12,1))))))))*TaxRate,0))-IF(19=0,O4,0)) | AM4: =IF(A4="","",((K4)*(IF(M4="",L4,IFERROR(IF(INDEX(Variablen!$I:$AT, MATCH(M4, Variablen!$A:$A, 0), MATCH((YEAR(D4)+20), Variablen!$I$3:$AT$3, 0))="",L4,INDEX(Variablen!$I:$AT, MATCH(M4, Variablen!$A:$A, 0), MATCH((YEAR(D4)+20), Variablen!$I$3:$AT$3, 0))),L4)))*(IF((YEAR(D4)+20)<YEAR(E4),0,IF((YEAR(D4)+20)>YEAR(E4),1,(12-MONTH(E4)+1)/12))) + (Q4)*(IF((YEAR(D4)+20)<YEAR(E4),0,IF((YEAR(D4)+20)>YEAR(E4),1,(12-MONTH(E4)+1)/12))))-((P4)*(IF((YEAR(D4)+20)<YEAR(E4),0,IF((YEAR(D4)+20)>YEAR(E4),1,(12-MONTH(E4)+1)/12))) + (R4)*(IF((YEAR(D4)+20)<YEAR(E4),0,IF((YEAR(D4)+20)>YEAR(E4),1,(12-MONTH(E4)+1)/12))))-(IF((((K4)*(IF(M4="",L4,IFERROR(IF(INDEX(Variablen!$I:$AT, MATCH(M4, Variablen!$A:$A, 0), MATCH((YEAR(D4)+20), Variablen!$I$3:$AT$3, 0))="",L4,INDEX(Variablen!$I:$AT, MATCH(M4, Variablen!$A:$A, 0), MATCH((YEAR(D4)+20), Variablen!$I$3:$AT$3, 0))),L4)))*(IF((YEAR(D4)+20)<YEAR(E4),0,IF((YEAR(D4)+20)>YEAR(E4),1,(12-MONTH(E4)+1)/12))) + (Q4)*(IF((YEAR(D4)+20)<YEAR(E4),0,IF((YEAR(D4)+20)>YEAR(E4),1,(12-MONTH(E4)+1)/12))))-((P4)*(IF((YEAR(D4)+20)<YEAR(E4),0,IF((YEAR(D4)+20)>YEAR(E4),1,(12-MONTH(E4)+1)/12))) + (R4)*(IF((YEAR(D4)+20)<YEAR(E4),0,IF((YEAR(D4)+20)>YEAR(E4),1,(12-MONTH(E4)+1)/12))))-(IF(OR(N4="",N4<=0),0,(O4/N4)*(IF(OR(N4="",N4<=0),0,IF((YEAR(D4)+20)<YEAR(E4),0,IF((YEAR(D4)+20)>=YEAR(E4)+N4,0,IF((YEAR(D4)+20)=YEAR(E4),(12-MONTH(E4)+1)/12,1))))))))>0,(((K4)*(IF(M4="",L4,IFERROR(IF(INDEX(Variablen!$I:$AT, MATCH(M4, Variablen!$A:$A, 0), MATCH((YEAR(D4)+20), Variablen!$I$3:$AT$3, 0))="",L4,INDEX(Variablen!$I:$AT, MATCH(M4, Variablen!$A:$A, 0), MATCH((YEAR(D4)+20), Variablen!$I$3:$AT$3, 0))),L4)))*(IF((YEAR(D4)+20)<YEAR(E4),0,IF((YEAR(D4)+20)>YEAR(E4),1,(12-MONTH(E4)+1)/12))) + (Q4)*(IF((YEAR(D4)+20)<YEAR(E4),0,IF((YEAR(D4)+20)>YEAR(E4),1,(12-MONTH(E4)+1)/12))))-((P4)*(IF((YEAR(D4)+20)<YEAR(E4),0,IF((YEAR(D4)+20)>YEAR(E4),1,(12-MONTH(E4)+1)/12))) + (R4)*(IF((YEAR(D4)+20)<YEAR(E4),0,IF((YEAR(D4)+20)>YEAR(E4),1,(12-MONTH(E4)+1)/12))))-(IF(OR(N4="",N4<=0),0,(O4/N4)*(IF(OR(N4="",N4<=0),0,IF((YEAR(D4)+20)<YEAR(E4),0,IF((YEAR(D4)+20)>=YEAR(E4)+N4,0,IF((YEAR(D4)+20)=YEAR(E4),(12-MONTH(E4)+1)/12,1))))))))*TaxRate,0))-IF(20=0,O4,0)) | AN4: =IF(A4="","",S4) | AO4: =IF(A4="","",AN4+T4) | AP4: =IF(A4="","",AO4+U4) | AQ4: =IF(A4="","",AP4+V4) | AR4: =IF(A4="","",AQ4+W4) | AS4: =IF(A4="","",AR4+X4) | AT4: =IF(A4="","",AS4+Y4) | AU4: =IF(A4="","",AT4+Z4) | AV4: =IF(A4="","",AU4+AA4) | AW4: =IF(A4="","",AV4+AB4) | AX4: =IF(A4="","",AW4+AC4) | AY4: =IF(A4="","",AX4+AD4) | AZ4: =IF(A4="","",AY4+AE4) | BA4: =IF(A4="","",AZ4+AF4) | BB4: =IF(A4="","",BA4+AG4) | BC4: =IF(A4="","",BB4+AH4) | BD4: =IF(A4="","",BC4+AI4) | BE4: =IF(A4="","",BD4+AJ4) | BF4: =IF(A4="","",BE4+AK4) | BG4: =IF(A4="","",BF4+AL4) | BH4: =IF(A4="","",BG4+AM4) | BI4: =IF(A4="","",(K4)*(IF((YEAR(D4)+0)<YEAR(E4),0,IF((YEAR(D4)+0)>YEAR(E4),1,(12-MONTH(E4)+1)/12)))*(1/(1+DiscountRate)^0)) | BJ4: =IF(A4="","",(K4)*(IF((YEAR(D4)+1)<YEAR(E4),0,IF((YEAR(D4)+1)>YEAR(E4),1,(12-MONTH(E4)+1)/12)))*(1/(1+DiscountRate)^1)) | BK4: =IF(A4="","",(K4)*(IF((YEAR(D4)+2)<YEAR(E4),0,IF((YEAR(D4)+2)>YEAR(E4),1,(12-MONTH(E4)+1)/12)))*(1/(1+DiscountRate)^2)) | BL4: =IF(A4="","",(K4)*(IF((YEAR(D4)+3)<YEAR(E4),0,IF((YEAR(D4)+3)>YEAR(E4),1,(12-MONTH(E4)+1)/12)))*(1/(1+DiscountRate)^3)) | BM4: =IF(A4="","",(K4)*(IF((YEAR(D4)+4)<YEAR(E4),0,IF((YEAR(D4)+4)>YEAR(E4),1,(12-MONTH(E4)+1)/12)))*(1/(1+DiscountRate)^4)) | BN4: =IF(A4="","",(K4)*(IF((YEAR(D4)+5)<YEAR(E4),0,IF((YEAR(D4)+5)>YEAR(E4),1,(12-MONTH(E4)+1)/12)))*(1/(1+DiscountRate)^5)) | BO4: =IF(A4="","",(K4)*(IF((YEAR(D4)+6)<YEAR(E4),0,IF((YEAR(D4)+6)>YEAR(E4),1,(12-MONTH(E4)+1)/12)))*(1/(1+DiscountRate)^6)) | BP4: =IF(A4="","",(K4)*(IF((YEAR(D4)+7)<YEAR(E4),0,IF((YEAR(D4)+7)>YEAR(E4),1,(12-MONTH(E4)+1)/12)))*(1/(1+DiscountRate)^7)) | BQ4: =IF(A4="","",(K4)*(IF((YEAR(D4)+8)<YEAR(E4),0,IF((YEAR(D4)+8)>YEAR(E4),1,(12-MONTH(E4)+1)/12)))*(1/(1+DiscountRate)^8)) | BR4: =IF(A4="","",(K4)*(IF((YEAR(D4)+9)<YEAR(E4),0,IF((YEAR(D4)+9)>YEAR(E4),1,(12-MONTH(E4)+1)/12)))*(1/(1+DiscountRate)^9)) | BS4: =IF(A4="","",(K4)*(IF((YEAR(D4)+10)<YEAR(E4),0,IF((YEAR(D4)+10)>YEAR(E4),1,(12-MONTH(E4)+1)/12)))*(1/(1+DiscountRate)^10)) | BT4: =IF(A4="","",(K4)*(IF((YEAR(D4)+11)<YEAR(E4),0,IF((YEAR(D4)+11)>YEAR(E4),1,(12-MONTH(E4)+1)/12)))*(1/(1+DiscountRate)^11)) | BU4: =IF(A4="","",(K4)*(IF((YEAR(D4)+12)<YEAR(E4),0,IF((YEAR(D4)+12)>YEAR(E4),1,(12-MONTH(E4)+1)/12)))*(1/(1+DiscountRate)^12)) | BV4: =IF(A4="","",(K4)*(IF((YEAR(D4)+13)<YEAR(E4),0,IF((YEAR(D4)+13)>YEAR(E4),1,(12-MONTH(E4)+1)/12)))*(1/(1+DiscountRate)^13)) | BW4: =IF(A4="","",(K4)*(IF((YEAR(D4)+14)<YEAR(E4),0,IF((YEAR(D4)+14)>YEAR(E4),1,(12-MONTH(E4)+1)/12)))*(1/(1+DiscountRate)^14)) | BX4: =IF(A4="","",(K4)*(IF((YEAR(D4)+15)<YEAR(E4),0,IF((YEAR(D4)+15)>YEAR(E4),1,(12-MONTH(E4)+1)/12)))*(1/(1+DiscountRate)^15)) | BY4: =IF(A4="","",(K4)*(IF((YEAR(D4)+16)<YEAR(E4),0,IF((YEAR(D4)+16)>YEAR(E4),1,(12-MONTH(E4)+1)/12)))*(1/(1+DiscountRate)^16)) | BZ4: =IF(A4="","",(K4)*(IF((YEAR(D4)+17)<YEAR(E4),0,IF((YEAR(D4)+17)>YEAR(E4),1,(12-MONTH(E4)+1)/12)))*(1/(1+DiscountRate)^17)) | CA4: =IF(A4="","",(K4)*(IF((YEAR(D4)+18)<YEAR(E4),0,IF((YEAR(D4)+18)>YEAR(E4),1,(12-MONTH(E4)+1)/12)))*(1/(1+DiscountRate)^18)) | CB4: =IF(A4="","",(K4)*(IF((YEAR(D4)+19)<YEAR(E4),0,IF((YEAR(D4)+19)>YEAR(E4),1,(12-MONTH(E4)+1)/12)))*(1/(1+DiscountRate)^19)) | CC4: =IF(A4="","",(K4)*(IF((YEAR(D4)+20)<YEAR(E4),0,IF((YEAR(D4)+20)>YEAR(E4),1,(12-MONTH(E4)+1)/12)))*(1/(1+DiscountRate)^20)) | CD4: =IF(A4="","",S4/(1+DiscountRate)^0+T4/(1+DiscountRate)^1+U4/(1+DiscountRate)^2+V4/(1+DiscountRate)^3+W4/(1+DiscountRate)^4+X4/(1+DiscountRate)^5+Y4/(1+DiscountRate)^6+Z4/(1+DiscountRate)^7+AA4/(1+DiscountRate)^8+AB4/(1+DiscountRate)^9+AC4/(1+DiscountRate)^10+AD4/(1+DiscountRate)^11+AE4/(1+DiscountRate)^12+AF4/(1+DiscountRate)^13+AG4/(1+DiscountRate)^14+AH4/(1+DiscountRate)^15+AI4/(1+DiscountRate)^16+AJ4/(1+DiscountRate)^17+AK4/(1+DiscountRate)^18+AL4/(1+DiscountRate)^19+AM4/(1+DiscountRate)^20) | CE4: =IF(A4="","",IFERROR(IRR(OFFSET(S4,0,0,1,MIN(HorizonYears,20)+1)),"n/a")) | CF4: =IF(A4="","",IFERROR(MATCH(TRUE,OFFSET(AN4,0,0,1,MIN(HorizonYears,20)+1)>=0,0)-1,"n/a")) | CG4: =IF(A4="","",SUM(OFFSET(BI4,0,0,1,MIN(HorizonYears,20)+1))) | CH4: =IF(A4="","",IFERROR(-CD4/CG4,"n/a"))
